Workbook
Name BizName: Settings!$B$5
Name BSAD: BS_AD_Lookup!$A$2:$B$6940
Name FAT_MULT: Settings!$B$58
Name PartyTypes: Settings!$J$16:$J$55
Name PayModes: Settings!$F$16:$F$55
Name Products: Settings!$H$16:$H$55
Name RateTypes: Settings!$K$16:$K$55
Name SNF_MULT: Settings!$B$59
Name Statuses: Settings!$I$16:$I$55
Name TxnTypes: Settings!$G$16:$G$55
Name Units: Settings!$E$16:$E$55

Sheet Dashboard
A1: 🐄 [Your Dairy Plant Name] — 📊 Accounts Dashboard — all figures auto-calculate from your entries
A2: 💰 TOTAL SALES | C2: 📦 TOTAL PURCHASES | E2: 📋 STOCK VALUE | G2: ⚠️ LOW STOCK ITEMS
A3: =SUM(Sales_Entry!J3:J1859) -> 3734275.3 | C3: =SUM(Purchase_Entry!P3:P1326) -> 3264264.2 | E3: =SUM(Stock_Master!I:I) | G3: =COUNTIF(Stock_Master!J:J,"⚠ Reorder") -> 5
A4: \
A5: 📤 RECEIVABLES | C5: 📥 PAYABLES | E5: 👥 TOTAL PARTIES | G5: 💰 DAYBOOK BALANCE
A6: =SUMIF(Party_Master!H:H,">0",Party_Master!H:H) -> 1773410.2 | C6: =-SUMIF(Party_Master!H:H,"<0",Party_Master!H:H) -> 1165789.6 | E6: =COUNTA(Party_Master!A3:A498) -> 66 | G6: =IFERROR(LOOKUP(2,1/(Daybook!H3:H502<>""),Daybook!H3:H502),0) -> 70776.15
A7: 📈 NET PROFIT / LOSS (Sales − Purchases): | D7: =SUM(Sales_Entry!J22:J1859)-SUM(Purchase_Entry!P9:P1326) -> 544021.07
A10: Metric | B10: Amount
A11: Total Sales | B11: =SUM(Sales_Entry!J22:J1859) -> 3202290.3
A12: Total Purchases | B12: =SUM(Purchase_Entry!P9:P1326) -> 2658269.2
A13: Stock Value | B13: =SUM(Stock_Master!I3:I41) -> -215069
A104: BS date filter works on TEXT. Type e.g. 2083/03/32 in BS format; day-32 is auto-capped to 31 in calculations.

Sheet Profit_Loss
A1: 🐄 [Your Dairy Plant Name] — 📈 Profit & Loss Account — company financial status
A3: From Date ► | B3: =IFERROR(VLOOKUP(TEXT($B$4,"yyyy/mm/dd"),BSAD,2,FALSE),IFERROR(VLOOKUP($B$4,BSAD,2,FALSE),"")) -> 46202 | C3: To Date ► | D3: =IFERROR(VLOOKUP(TEXT($D$4,"yyyy/mm/dd"),BSAD,2,FALSE),IFERROR(VLOOKUP($D$4,BSAD,2,FALSE),"")) -> 46281
A4: ="For period: "&TEXT($B$3,"dd-mmm-yyyy")&" to "&TEXT($D$3,"dd-mmm-yyyy") -> For period: 29-Jun-2026 to 16-Sep-2026 | B4: 66915 | D4: 66992
A6: 💰 INCOME
A7: Total Sales Revenue | C7: =SUMIFS(Sales_Entry!$J:$J,Sales_Entry!$B:$B,">="&$B$3,Sales_Entry!$B:$B,"<="&$D$3) -> 3734275.3
A8: Other Income (from Daybook receipts) | C8: =SUMIFS(Daybook!$G:$G,Daybook!$D:$D,"Receipt",Daybook!$B:$B,">="&$B$3,Daybook!$B:$B,"<="&$D$3) -> 0
A9: GROSS INCOME (A) | C9: =C7 -> 3734275.3
A11: 📦 COST OF GOODS / PURCHASES
A12: CASH INVESTMENT | C12: =SUMIFS(Party_Ledger!H:H,Party_Ledger!D:D,"KESHAB GAUTAM",Party_Ledger!$B:$B,">="&$B$3,Party_Ledger!$B:$B,"<="&$D$3) -> 400000
A13: Total Purchases (milk & materials) | C13: =SUMIFS(Purchase_Entry!$P:$P,Purchase_Entry!$B:$B,">="&$B$3,Purchase_Entry!$B:$B,"<="&$D$3) -> 3264264.2
A14: TOTAL COST (B) | C14: =C13+C12 -> 3664264.2
A16: GROSS PROFIT (A − B) | C16: =C9-C14 -> 70011.071
A18: 💸 OPERATING EXPENSES (FROM PETTY CASH)
A19: Total Payments/EXPENSES | C19: =SUMIFS(Party_Ledger!G:G,Party_Ledger!D:D,"Payment",Party_Ledger!$B:$B,">="&$B$3,Party_Ledger!$B:$B,"<="&$D$3) -> 179955
A20: Total Office Expenses | C20: =SUMIFS(Party_Ledger!G:G,Party_Ledger!D:D,"OFFICE EXPENSES",Party_Ledger!$B:$B,">="&$B$3,Party_Ledger!$B:$B,"<="&$D$3) -> 33513
A21: Total Advance | C21: =(SUMIFS(Party_Ledger!G:G,Party_Ledger!D:D,"Advance",Party_Ledger!$B:$B,">="&$B$3,Party_Ledger!$B:$B,"<="&$D$3))-(SUMIFS(Party_Ledger!H:H,Party_Ledger!D:D,"Advance Returned",Party_Ledger!$B:$B,">="&$B$3,Party_Ledger!$B:$B,"<="&$D$3)) -> 284940
A22: TOTAL EXPENSES (C) | C22: =C20+C19 -> 213468
A24: 🏆 NET PROFIT / (LOSS) = Gross Profit − Expenses | C24: =C16-C22 -> -143456.93
A26: Company Status: | C26: =IF(C24>0,"✅ PROFIT — Healthy",IF(C24=0,"➖ Break-even","🔴 LOSS — Review costs")) -> 🔴 LOSS — Review costs
A27: Net Profit Margin %: | C27: =IF(C9=0,0,C24/C9) -> -0.038416271

Sheet Receivable_Payable
A1: =BizName -> PRARAMBHA DAIRY SUPPLIERS
A2: RECEIVABLES & PAYABLES — party balances for selected period
A4: From Date ► | B4: =IFERROR(VLOOKUP(TEXT($B$5,"yyyy/mm/dd"),BSAD,2,FALSE),IFERROR(VLOOKUP($B$5,BSAD,2,FALSE),"")) -> 46202 | C4: To Date ► | D4: =IFERROR(VLOOKUP(TEXT($D$5,"yyyy/mm/dd"),BSAD,2,FALSE),IFERROR(VLOOKUP($D$5,BSAD,2,FALSE),"")) -> 46280 | E4: Total Receivable: | F4: =SUMIF(E8:E76,">0") -> 1738678.2
A5: ="Period: "&TEXT($B$4,"dd-mmm-yyyy")&" to "&TEXT($D$4,"dd-mmm-yyyy") -> Period: 29-Jun-2026 to 15-Sep-2026 | B5: 2083/03/15 | D5: 2083/05/30 | E5: Total Payable: | F5: =-SUMIF(E8:E76,"<0") -> 1139309.6
A7: Party Name | B7: Type | C7: Debit (Dr) | D7: Credit (Cr) | E7: Net Balance | F7: Class
A8: =Party_Master!$A3 -> A KALIKA CANTEEN | B8: =Party_Master!$B3 -> Customer | C8: =SUMIFS(Party_Ledger!$G:$G,Party_Ledger!$C:$C,$A8,Party_Ledger!$B:$B,">="&$B$4,Party_Ledger!$B:$B,"<="&$D$4) -> 33150 | D8: =SUMIFS(Party_Ledger!$H:$H,Party_Ledger!$C:$C,$A8,Party_Ledger!$B:$B,">="&$B$4,Party_Ledger!$B:$B,"<="&$D$4) -> 5950 | E8: =C8-D8 -> 27200 | F8: =IF(ROUND(E8,0)=0,"Settled",IF(E8>0,"Receivable","Payable")) -> Receivable
A9: =Party_Master!$A4 -> A1 KALIKA CANTEEN | B9: =Party_Master!$B4 -> Customer | C9: =SUMIFS(Party_Ledger!$G:$G,Party_Ledger!$C:$C,$A9,Party_Ledger!$B:$B,">="&$B$4,Party_Ledger!$B:$B,"<="&$D$4) -> 45050 | D9: =SUMIFS(Party_Ledger!$H:$H,Party_Ledger!$C:$C,$A9,Party_Ledger!$B:$B,">="&$B$4,Party_Ledger!$B:$B,"<="&$D$4) -> 17000 | E9: =C9-D9 -> 28050 | F9: =IF(ROUND(E9,0)=0,"Settled",IF(E9>0,"Receivable","Payable")) -> Receivable
A10: =Party_Master!$A5 -> AAMOSH KIRANA | B10: =Party_Master!$B5 -> Customer | C10: =SUMIFS(Party_Ledger!$G:$G,Party_Ledger!$C:$C,$A10,Party_Ledger!$B:$B,">="&$B$4,Party_Ledger!$B:$B,"<="&$D$4) -> 825393 | D10: =SUMIFS(Party_Ledger!$H:$H,Party_Ledger!$C:$C,$A10,Party_Ledger!$B:$B,">="&$B$4,Party_Ledger!$B:$B,"<="&$D$4) -> 511950 | E10: =C10-D10 -> 313443 | F10: =IF(ROUND(E10,0)=0,"Settled",IF(E10>0,"Receivable","Payable")) -> Receivable
A11: =Party_Master!$A6 -> AAYUSH AND AAYUSHMA | B11: =Party_Master!$B6 -> Customer | C11: =SUMIFS(Party_Ledger!$G:$G,Party_Ledger!$C:$C,$A11,Party_Ledger!$B:$B,">="&$B$4,Party_Ledger!$B:$B,"<="&$D$4) -> 22185 | D11: =SUMIFS(Party_Ledger!$H:$H,Party_Ledger!$C:$C,$A11,Party_Ledger!$B:$B,">="&$B$4,Party_Ledger!$B:$B,"<="&$D$4) -> 17485 | E11: =C11-D11 -> 4700 | F11: =IF(ROUND(E11,0)=0,"Settled",IF(E11>0,"Receivable","Payable")) -> Receivable
A12: =Party_Master!$A7 -> BAGESHWARI ICE CREAM | B12: =Party_Master!$B7 -> Customer | C12: =SUMIFS(Party_Ledger!$G:$G,Party_Ledger!$C:$C,$A12,Party_Ledger!$B:$B,">="&$B$4,Party_Ledger!$B:$B,"<="&$D$4) -> 11950 | D12: =SUMIFS(Party_Ledger!$H:$H,Party_Ledger!$C:$C,$A12,Party_Ledger!$B:$B,">="&$B$4,Party_Ledger!$B:$B,"<="&$D$4) -> 0 | E12: =C12-D12 -> 11950 | F12: =IF(ROUND(E12,0)=0,"Settled",IF(E12>0,"Receivable","Payable")) -> Receivable
A13: =Party_Master!$A8 -> BALKRISHNA GYAWALI | B13: =Party_Master!$B8 -> Customer | C13: =SUMIFS(Party_Ledger!$G:$G,Party_Ledger!$C:$C,$A13,Party_Ledger!$B:$B,">="&$B$4,Party_Ledger!$B:$B,"<="&$D$4) -> 4510 | D13: =SUMIFS(Party_Ledger!$H:$H,Party_Ledger!$C:$C,$A13,Party_Ledger!$B:$B,">="&$B$4,Party_Ledger!$B:$B,"<="&$D$4) -> 0 | E13: =C13-D13 -> 4510 | F13: =IF(ROUND(E13,0)=0,"Settled",IF(E13>0,"Receivable","Payable")) -> Receivable
A14: =Party_Master!$A9 -> BASUDEV DAIRY 316 | B14: =Party_Master!$B9 -> Supplier | C14: =SUMIFS(Party_Ledger!$G:$G,Party_Ledger!$C:$C,$A14,Party_Ledger!$B:$B,">="&$B$4,Party_Ledger!$B:$B,"<="&$D$4) -> 474131.13 | D14: =SUMIFS(Party_Ledger!$H:$H,Party_Ledger!$C:$C,$A14,Party_Ledger!$B:$B,">="&$B$4,Party_Ledger!$B:$B,"<="&$D$4) -> 693965.22 | E14: =C14-D14 -> -219834.09 | F14: =IF(ROUND(E14,0)=0,"Settled",IF(E14>0,"Receivable","Payable")) -> Payable
A15: =Party_Master!$A10 -> BHUSAL JANARAL STORE | B15: =Party_Master!$B10 -> Customer | C15: =SUMIFS(Party_Ledger!$G:$G,Party_Ledger!$C:$C,$A15,Party_Ledger!$B:$B,">="&$B$4,Party_Ledger!$B:$B,"<="&$D$4) -> 26410 | D15: =SUMIFS(Party_Ledger!$H:$H,Party_Ledger!$C:$C,$A15,Party_Ledger!$B:$B,">="&$B$4,Party_Ledger!$B:$B,"<="&$D$4) -> 16350 | E15: =C15-D15 -> 10060 | F15: =IF(ROUND(E15,0)=0,"Settled",IF(E15>0,"Receivable","Payable")) -> Receivable
A16: =Party_Master!$A11 -> BIKRAM DHUNGANA | B16: =Party_Master!$B11 -> Customer | C16: =SUMIFS(Party_Ledger!$G:$G,Party_Ledger!$C:$C,$A16,Party_Ledger!$B:$B,">="&$B$4,Party_Ledger!$B:$B,"<="&$D$4) -> 2200 | D16: =SUMIFS(Party_Ledger!$H:$H,Party_Ledger!$C:$C,$A16,Party_Ledger!$B:$B,">="&$B$4,Party_Ledger!$B:$B,"<="&$D$4) -> 2200 | E16: =C16-D16 -> 0 | F16: =IF(ROUND(E16,0)=0,"Settled",IF(E16>0,"Receivable","Payable")) -> Settled
A17: =Party_Master!$A12 -> BODESH 310 | B17: =Party_Master!$B12 -> Supplier | C17: =SUMIFS(Party_Ledger!$G:$G,Party_Ledger!$C:$C,$A17,Party_Ledger!$B:$B,">="&$B$4,Party_Ledger!$B:$B,"<="&$D$4) -> 310000 | D17: =SUMIFS(Party_Ledger!$H:$H,Party_Ledger!$C:$C,$A17,Party_Ledger!$B:$B,">="&$B$4,Party_Ledger!$B:$B,"<="&$D$4) -> 215600 | E17: =C17-D17 -> 94400 | F17: =IF(ROUND(E17,0)=0,"Settled",IF(E17>0,"Receivable","Payable")) -> Receivable
A18: =Party_Master!$A13 -> CHHATRABHUMI STORE | B18: =Party_Master!$B13 -> Customer | C18: =SUMIFS(Party_Ledger!$G:$G,Party_Ledger!$C:$C,$A18,Party_Ledger!$B:$B,">="&$B$4,Party_Ledger!$B:$B,"<="&$D$4) -> 223796 | D18: =SUMIFS(Party_Ledger!$H:$H,Party_Ledger!$C:$C,$A18,Party_Ledger!$B:$B,">="&$B$4,Party_Ledger!$B:$B,"<="&$D$4) -> 90000 | E18: =C18-D18 -> 133796 | F18: =IF(ROUND(E18,0)=0,"Settled",IF(E18>0,"Receivable","Payable")) -> Receivable
A19: =Party_Master!$A14 -> DANDA PANI ACHARYA | B19: =Party_Master!$B14 -> Customer | C19: =SUMIFS(Party_Ledger!$G:$G,Party_Ledger!$C:$C,$A19,Party_Ledger!$B:$B,">="&$B$4,Party_Ledger!$B:$B,"<="&$D$4) -> 1100 | D19: =SUMIFS(Party_Ledger!$H:$H,Party_Ledger!$C:$C,$A19,Party_Ledger!$B:$B,">="&$B$4,Party_Ledger!$B:$B,"<="&$D$4) -> 1100 | E19: =C19-D19 -> 0 | F19: =IF(ROUND(E19,0)=0,"Settled",IF(E19>0,"Receivable","Payable")) -> Settled
... A73: =Party_Master!$A68 -> YUBARAJ AND SAMRAT | B73: =Party_Master!$B68 -> Customer | C73: =SUMIFS(Party_Ledger!$G:$G,Party_Ledger!$C:$C,$A73,Party_Ledger!$B:$B,">="&$B$4,Party_Ledger!$B:$B,"<="&$D$4) -> 75650 | D73: =SUMIFS(Party_Ledger!$H:$H,Party_Ledger!$C:$C,$A73,Party_Ledger!$B:$B,">="&$B$4,Party_Ledger!$B:$B,"<="&$D$4) -> 66470 | E73: =C73-D73 -> 9180 | F73: =IF(ROUND(E73,0)=0,"Settled",IF(E73>0,"Receivable","Payable")) -> Receivable
A74: =Party_Master!$A69 -> 0
A77: TOTALS ► | C77: =SUM(C8:C76) -> 6244661.4 | D77: =SUM(D8:D76) -> 5645292.8 | E77: =SUM(E8:E76) -> 599368.62
A79: 💡 Change From/To Date — every party balance for that period recalculates. Positive = they owe you (Receivable). Negative = you owe them (Payable).
A80: 💡 Total Receivable / Total Payable shown at top-right.

Sheet Party_Statement
A1: =BizName -> PRARAMBHA DAIRY SUPPLIERS
A2: ="Phone: "&Settings!B9&" | PAN/VAT: "&Settings!B11 -> Phone: prarambhadairy@gmail.com | PAN/VAT: 152747352
A3: PARTY LEDGER STATEMENT | N3: One | O3: Twenty
N4: Two | O4: Thirty
A5: Select Party ► | C5: SAI KRIPA KSS LTD | F5: Opening (b/f): | G5: =SUMIFS(Party_Ledger!$G:$G,Party_Ledger!$C:$C,$C$5,Party_Ledger!$B:$B,"<"&$C$6)-SUMIFS(Party_Ledger!$H:$H,Party_Ledger!$C:$C,$C$5,Party_Ledger!$B:$B,"<"&$C$6) -> 0 | N5: Three | O5: Forty
A6: From Date ► | C6: =IFERROR(VLOOKUP(TEXT($C$7,"yyyy/mm/dd"),BSAD,2,FALSE),IFERROR(VLOOKUP($C$7,BSAD,2,FALSE),"")) -> 46202 | D6: To Date ► | E6: =IFERROR(VLOOKUP(TEXT($E$7,"yyyy/mm/dd"),BSAD,2,FALSE),IFERROR(VLOOKUP($E$7,BSAD,2,FALSE),"")) -> 46284 | F6: Period Debit: | G6: =SUMIFS(Party_Ledger!$G:$G,Party_Ledger!$C:$C,$C$5,Party_Ledger!$B:$B,">="&$C$6,Party_Ledger!$B:$B,"<="&$E$6) -> 370835 | N6: Four | O6: Fifty
A7: ="Period: "&TEXT($C$6,"dd-mmm-yyyy")&" to "&TEXT($E$6,"dd-mmm-yyyy") -> Period: 29-Jun-2026 to 19-Sep-2026 | C7: 66915 | E7: 66995 | F7: Period Credit: | G7: =SUMIFS(Party_Ledger!$H:$H,Party_Ledger!$C:$C,$C$5,Party_Ledger!$B:$B,">="&$C$6,Party_Ledger!$B:$B,"<="&$E$6) -> 106685 | N7: Five | O7: Sixty
F8: Closing Balance: | G8: =G5+G6-G7 -> 264150 | N8: Six | O8: Seventy
F9: Status: | G9: =IF(ROUND(G8,0)=0,"Settled",IF(G8>0,"Receivable","Payable/Advance")) -> Receivable | N9: Seven | O9: Eighty
N10: Eight | O10: Ninety
A11: Date | B11: AD Date | C11: Txn Type | D11: Reference | E11: Description | F11: Debit | G11: Credit | H11: Balance | N11: Nine
A12: =IFERROR(INDEX(Party_Ledger!$A$3:$A$100322, MATCH(ROWS($1:1), Party_Ledger!$K$3:$K$100322, 0)), "") -> 66915 | B12: =IF(A12="","",IF(ISNUMBER(A12),IFERROR(VLOOKUP(TEXT(A12,"yyyy/mm/dd"),BSAD,2,FALSE),""),IFERROR(VLOOKUP(A12,BSAD,2,FALSE),""))) -> 46202 | C12: =IFERROR(INDEX(Party_Ledger!$D$3:$D$100322,MATCH(ROWS($1:1),Party_Ledger!$K$3:$K$100322,0)),"") -> Purchase | D12: =IFERROR(INDEX(Party_Ledger!$E$3:$E$100322,MATCH(ROWS($1:1),Party_Ledger!$K$3:$K$100322,0)),"") -> S 5956 | E12: =IFERROR(INDEX(Party_Ledger!$F$3:$F$100322,MATCH(ROWS($1:1),Party_Ledger!$K$3:$K$100322,0)),"") -> Mix Milk | F12: =IFERROR(INDEX(Party_Ledger!$G$3:$G$100322,MATCH(ROWS($1:1),Party_Ledger!$K$3:$K$100322,0)),"") -> 0 | G12: =IFERROR(INDEX(Party_Ledger!$H$3:$H$100322,MATCH(ROWS($1:1),Party_Ledger!$K$3:$K$100322,0)),"") -> 16520 | H12: =IF($A12="","",N($F12)-N($G12)) -> -16520 | N12: Eleven
A13: =IFERROR(INDEX(Party_Ledger!$A$3:$A$100322, MATCH(ROWS($1:2), Party_Ledger!$K$3:$K$100322, 0)), "") -> 66915 | B13: =IF(A13="","",IF(ISNUMBER(A13),IFERROR(VLOOKUP(TEXT(A13,"yyyy/mm/dd"),BSAD,2,FALSE),""),IFERROR(VLOOKUP(A13,BSAD,2,FALSE),""))) -> 46202 | C13: =IFERROR(INDEX(Party_Ledger!$D$3:$D$100322,MATCH(ROWS($1:2),Party_Ledger!$K$3:$K$100322,0)),"") -> Purchase | D13: =IFERROR(INDEX(Party_Ledger!$E$3:$E$100322,MATCH(ROWS($1:2),Party_Ledger!$K$3:$K$100322,0)),"") -> S 5956 | E13: =IFERROR(INDEX(Party_Ledger!$F$3:$F$100322,MATCH(ROWS($1:2),Party_Ledger!$K$3:$K$100322,0)),"") -> NAUNI | F13: =IFERROR(INDEX(Party_Ledger!$G$3:$G$100322,MATCH(ROWS($1:2),Party_Ledger!$K$3:$K$100322,0)),"") -> 0 | G13: =IFERROR(INDEX(Party_Ledger!$H$3:$H$100322,MATCH(ROWS($1:2),Party_Ledger!$K$3:$K$100322,0)),"") -> 4550 | H13: =IF($A13="","",N($F13)-N($G13)) -> -4550 | N13: Thirteen
A14: =IFERROR(INDEX(Party_Ledger!$A$3:$A$100322, MATCH(ROWS($1:3), Party_Ledger!$K$3:$K$100322, 0)), "") -> 66915 | B14: =IF(A14="","",IF(ISNUMBER(A14),IFERROR(VLOOKUP(TEXT(A14,"yyyy/mm/dd"),BSAD,2,FALSE),""),IFERROR(VLOOKUP(A14,BSAD,2,FALSE),""))) -> 46202 | C14: =IFERROR(INDEX(Party_Ledger!$D$3:$D$100322,MATCH(ROWS($1:3),Party_Ledger!$K$3:$K$100322,0)),"") -> Purchase | D14: =IFERROR(INDEX(Party_Ledger!$E$3:$E$100322,MATCH(ROWS($1:3),Party_Ledger!$K$3:$K$100322,0)),"") -> S 5956 | E14: =IFERROR(INDEX(Party_Ledger!$F$3:$F$100322,MATCH(ROWS($1:3),Party_Ledger!$K$3:$K$100322,0)),"") -> Ghee | F14: =IFERROR(INDEX(Party_Ledger!$G$3:$G$100322,MATCH(ROWS($1:3),Party_Ledger!$K$3:$K$100322,0)),"") -> 0 | G14: =IFERROR(INDEX(Party_Ledger!$H$3:$H$100322,MATCH(ROWS($1:3),Party_Ledger!$K$3:$K$100322,0)),"") -> 17100 | H14: =IF($A14="","",N($F14)-N($G14)) -> -17100 | N14: Fourteen
A15: =IFERROR(INDEX(Party_Ledger!$A$3:$A$100322, MATCH(ROWS($1:4), Party_Ledger!$K$3:$K$100322, 0)), "") -> 66915 | B15: =IF(A15="","",IF(ISNUMBER(A15),IFERROR(VLOOKUP(TEXT(A15,"yyyy/mm/dd"),BSAD,2,FALSE),""),IFERROR(VLOOKUP(A15,BSAD,2,FALSE),""))) -> 46202 | C15: =IFERROR(INDEX(Party_Ledger!$D$3:$D$100322,MATCH(ROWS($1:4),Party_Ledger!$K$3:$K$100322,0)),"") -> Purchase | D15: =IFERROR(INDEX(Party_Ledger!$E$3:$E$100322,MATCH(ROWS($1:4),Party_Ledger!$K$3:$K$100322,0)),"") -> S 5956 | E15: =IFERROR(INDEX(Party_Ledger!$F$3:$F$100322,MATCH(ROWS($1:4),Party_Ledger!$K$3:$K$100322,0)),"") -> Paneer | F15: =IFERROR(INDEX(Party_Ledger!$G$3:$G$100322,MATCH(ROWS($1:4),Party_Ledger!$K$3:$K$100322,0)),"") -> 0 | G15: =IFERROR(INDEX(Party_Ledger!$H$3:$H$100322,MATCH(ROWS($1:4),Party_Ledger!$K$3:$K$100322,0)),"") -> 720 | H15: =IF($A15="","",N($F15)-N($G15)) -> -720 | N15: Fifteen
A16: =IFERROR(INDEX(Party_Ledger!$A$3:$A$100322, MATCH(ROWS($1:5), Party_Ledger!$K$3:$K$100322, 0)), "") -> 66915 | B16: =IF(A16="","",IF(ISNUMBER(A16),IFERROR(VLOOKUP(TEXT(A16,"yyyy/mm/dd"),BSAD,2,FALSE),""),IFERROR(VLOOKUP(A16,BSAD,2,FALSE),""))) -> 46202 | C16: =IFERROR(INDEX(Party_Ledger!$D$3:$D$100322,MATCH(ROWS($1:5),Party_Ledger!$K$3:$K$100322,0)),"") -> Purchase | D16: =IFERROR(INDEX(Party_Ledger!$E$3:$E$100322,MATCH(ROWS($1:5),Party_Ledger!$K$3:$K$100322,0)),"") -> S 5956 | E16: =IFERROR(INDEX(Party_Ledger!$F$3:$F$100322,MATCH(ROWS($1:5),Party_Ledger!$K$3:$K$100322,0)),"") -> Cream | F16: =IFERROR(INDEX(Party_Ledger!$G$3:$G$100322,MATCH(ROWS($1:5),Party_Ledger!$K$3:$K$100322,0)),"") -> 0 | G16: =IFERROR(INDEX(Party_Ledger!$H$3:$H$100322,MATCH(ROWS($1:5),Party_Ledger!$K$3:$K$100322,0)),"") -> 66150 | H16: =IF($A16="","",N($F16)-N($G16)) -> -66150 | N16: Sixteen
A17: =IFERROR(INDEX(Party_Ledger!$A$3:$A$100322, MATCH(ROWS($1:6), Party_Ledger!$K$3:$K$100322, 0)), "") -> 66915 | B17: =IF(A17="","",IF(ISNUMBER(A17),IFERROR(VLOOKUP(TEXT(A17,"yyyy/mm/dd"),BSAD,2,FALSE),""),IFERROR(VLOOKUP(A17,BSAD,2,FALSE),""))) -> 46202 | C17: =IFERROR(INDEX(Party_Ledger!$D$3:$D$100322,MATCH(ROWS($1:6),Party_Ledger!$K$3:$K$100322,0)),"") -> Purchase | D17: =IFERROR(INDEX(Party_Ledger!$E$3:$E$100322,MATCH(ROWS($1:6),Party_Ledger!$K$3:$K$100322,0)),"") -> S 5963 | E17: =IFERROR(INDEX(Party_Ledger!$F$3:$F$100322,MATCH(ROWS($1:6),Party_Ledger!$K$3:$K$100322,0)),"") -> Dana | F17: =IFERROR(INDEX(Party_Ledger!$G$3:$G$100322,MATCH(ROWS($1:6),Party_Ledger!$K$3:$K$100322,0)),"") -> 0 | G17: =IFERROR(INDEX(Party_Ledger!$H$3:$H$100322,MATCH(ROWS($1:6),Party_Ledger!$K$3:$K$100322,0)),"") -> 1645 | H17: =IF($A17="","",N($F17)-N($G17)) -> -1645 | N17: Seventeen
A18: =IFERROR(INDEX(Party_Ledger!$A$3:$A$100322, MATCH(ROWS($1:7), Party_Ledger!$K$3:$K$100322, 0)), "") -> 2083/03/16 | B18: =IF(A18="","",IF(ISNUMBER(A18),IFERROR(VLOOKUP(TEXT(A18,"yyyy/mm/dd"),BSAD,2,FALSE),""),IFERROR(VLOOKUP(A18,BSAD,2,FALSE),""))) -> 46203 | C18: =IFERROR(INDEX(Party_Ledger!$D$3:$D$100322,MATCH(ROWS($1:7),Party_Ledger!$K$3:$K$100322,0)),"") -> Advance | D18: =IFERROR(INDEX(Party_Ledger!$E$3:$E$100322,MATCH(ROWS($1:7),Party_Ledger!$K$3:$K$100322,0)),"") -> 0 | E18: =IFERROR(INDEX(Party_Ledger!$F$3:$F$100322,MATCH(ROWS($1:7),Party_Ledger!$K$3:$K$100322,0)),"") -> CASH | F18: =IFERROR(INDEX(Party_Ledger!$G$3:$G$100322,MATCH(ROWS($1:7),Party_Ledger!$K$3:$K$100322,0)),"") -> 190 | G18: =IFERROR(INDEX(Party_Ledger!$H$3:$H$100322,MATCH(ROWS($1:7),Party_Ledger!$K$3:$K$100322,0)),"") -> 0 | H18: =IF($A18="","",N($F18)-N($G18)) -> 190 | N18: Eighteen
A19: =IFERROR(INDEX(Party_Ledger!$A$3:$A$100322, MATCH(ROWS($1:8), Party_Ledger!$K$3:$K$100322, 0)), "") -> 66925 | B19: =IF(A19="","",IF(ISNUMBER(A19),IFERROR(VLOOKUP(TEXT(A19,"yyyy/mm/dd"),BSAD,2,FALSE),""),IFERROR(VLOOKUP(A19,BSAD,2,FALSE),""))) -> 46212 | C19: =IFERROR(INDEX(Party_Ledger!$D$3:$D$100322,MATCH(ROWS($1:8),Party_Ledger!$K$3:$K$100322,0)),"") -> Advance | D19: =IFERROR(INDEX(Party_Ledger!$E$3:$E$100322,MATCH(ROWS($1:8),Party_Ledger!$K$3:$K$100322,0)),"") -> 0 | E19: =IFERROR(INDEX(Party_Ledger!$F$3:$F$100322,MATCH(ROWS($1:8),Party_Ledger!$K$3:$K$100322,0)),"") -> SENSOE WIRE | F19: =IFERROR(INDEX(Party_Ledger!$G$3:$G$100322,MATCH(ROWS($1:8),Party_Ledger!$K$3:$K$100322,0)),"") -> 350 | G19: =IFERROR(INDEX(Party_Ledger!$H$3:$H$100322,MATCH(ROWS($1:8),Party_Ledger!$K$3:$K$100322,0)),"") -> 0 | H19: =IF($A19="","",N($F19)-N($G19)) -> 350 | N19: Nineteen
A20: =IFERROR(INDEX(Party_Ledger!$A$3:$A$100322, MATCH(ROWS($1:9), Party_Ledger!$K$3:$K$100322, 0)), "") -> 2083/04/07 | B20: =IF(A20="","",IF(ISNUMBER(A20),IFERROR(VLOOKUP(TEXT(A20,"yyyy/mm/dd"),BSAD,2,FALSE),""),IFERROR(VLOOKUP(A20,BSAD,2,FALSE),""))) -> 46226 | C20: =IFERROR(INDEX(Party_Ledger!$D$3:$D$100322,MATCH(ROWS($1:9),Party_Ledger!$K$3:$K$100322,0)),"") -> Advance | D20: =IFERROR(INDEX(Party_Ledger!$E$3:$E$100322,MATCH(ROWS($1:9),Party_Ledger!$K$3:$K$100322,0)),"") -> 0 | E20: =IFERROR(INDEX(Party_Ledger!$F$3:$F$100322,MATCH(ROWS($1:9),Party_Ledger!$K$3:$K$100322,0)),"") -> CASH | F20: =IFERROR(INDEX(Party_Ledger!$G$3:$G$100322,MATCH(ROWS($1:9),Party_Ledger!$K$3:$K$100322,0)),"") -> 3490 | G20: =IFERROR(INDEX(Party_Ledger!$H$3:$H$100322,MATCH(ROWS($1:9),Party_Ledger!$K$3:$K$100322,0)),"") -> 0 | H20: =IF($A20="","",N($F20)-N($G20)) -> 3490
A21: =IFERROR(INDEX(Party_Ledger!$A$3:$A$100322, MATCH(ROWS($1:10), Party_Ledger!$K$3:$K$100322, 0)), "") -> 2083/04/07 | B21: =IF(A21="","",IF(ISNUMBER(A21),IFERROR(VLOOKUP(TEXT(A21,"yyyy/mm/dd"),BSAD,2,FALSE),""),IFERROR(VLOOKUP(A21,BSAD,2,FALSE),""))) -> 46226 | C21: =IFERROR(INDEX(Party_Ledger!$D$3:$D$100322,MATCH(ROWS($1:10),Party_Ledger!$K$3:$K$100322,0)),"") -> Advance | D21: =IFERROR(INDEX(Party_Ledger!$E$3:$E$100322,MATCH(ROWS($1:10),Party_Ledger!$K$3:$K$100322,0)),"") -> 0 | E21: =IFERROR(INDEX(Party_Ledger!$F$3:$F$100322,MATCH(ROWS($1:10),Party_Ledger!$K$3:$K$100322,0)),"") -> CLEANING600 | F21: =IFERROR(INDEX(Party_Ledger!$G$3:$G$100322,MATCH(ROWS($1:10),Party_Ledger!$K$3:$K$100322,0)),"") -> 600 | G21: =IFERROR(INDEX(Party_Ledger!$H$3:$H$100322,MATCH(ROWS($1:10),Party_Ledger!$K$3:$K$100322,0)),"") -> 0 | H21: =IF($A21="","",N($F21)-N($G21)) -> 600
A22: =IFERROR(INDEX(Party_Ledger!$A$3:$A$100322, MATCH(ROWS($1:11), Party_Ledger!$K$3:$K$100322, 0)), "") -> 2083/04/08 | B22: =IF(A22="","",IF(ISNUMBER(A22),IFERROR(VLOOKUP(TEXT(A22,"yyyy/mm/dd"),BSAD,2,FALSE),""),IFERROR(VLOOKUP(A22,BSAD,2,FALSE),""))) -> 46227 | C22: =IFERROR(INDEX(Party_Ledger!$D$3:$D$100322,MATCH(ROWS($1:11),Party_Ledger!$K$3:$K$100322,0)),"") -> Advance | D22: =IFERROR(INDEX(Party_Ledger!$E$3:$E$100322,MATCH(ROWS($1:11),Party_Ledger!$K$3:$K$100322,0)),"") -> 0 | E22: =IFERROR(INDEX(Party_Ledger!$F$3:$F$100322,MATCH(ROWS($1:11),Party_Ledger!$K$3:$K$100322,0)),"") -> CASH | F22: =IFERROR(INDEX(Party_Ledger!$G$3:$G$100322,MATCH(ROWS($1:11),Party_Ledger!$K$3:$K$100322,0)),"") -> 3400 | G22: =IFERROR(INDEX(Party_Ledger!$H$3:$H$100322,MATCH(ROWS($1:11),Party_Ledger!$K$3:$K$100322,0)),"") -> 0 | H22: =IF($A22="","",N($F22)-N($G22)) -> 3400
A23: =IFERROR(INDEX(Party_Ledger!$A$3:$A$100322, MATCH(ROWS($1:12), Party_Ledger!$K$3:$K$100322, 0)), "") -> 2083/04/11 | B23: =IF(A23="","",IF(ISNUMBER(A23),IFERROR(VLOOKUP(TEXT(A23,"yyyy/mm/dd"),BSAD,2,FALSE),""),IFERROR(VLOOKUP(A23,BSAD,2,FALSE),""))) -> 46230 | C23: =IFERROR(INDEX(Party_Ledger!$D$3:$D$100322,MATCH(ROWS($1:12),Party_Ledger!$K$3:$K$100322,0)),"") -> Advance | D23: =IFERROR(INDEX(Party_Ledger!$E$3:$E$100322,MATCH(ROWS($1:12),Party_Ledger!$K$3:$K$100322,0)),"") -> 0 | E23: =IFERROR(INDEX(Party_Ledger!$F$3:$F$100322,MATCH(ROWS($1:12),Party_Ledger!$K$3:$K$100322,0)),"") -> SURYA KC FOR SENSOR | F23: =IFERROR(INDEX(Party_Ledger!$G$3:$G$100322,MATCH(ROWS($1:12),Party_Ledger!$K$3:$K$100322,0)),"") -> 2000 | G23: =IFERROR(INDEX(Party_Ledger!$H$3:$H$100322,MATCH(ROWS($1:12),Party_Ledger!$K$3:$K$100322,0)),"") -> 0 | H23: =IF($A23="","",N($F23)-N($G23)) -> 2000
A24: =IFERROR(INDEX(Party_Ledger!$A$3:$A$100322, MATCH(ROWS($1:13), Party_Ledger!$K$3:$K$100322, 0)), "") -> 2083/04/11 | B24: =IF(A24="","",IF(ISNUMBER(A24),IFERROR(VLOOKUP(TEXT(A24,"yyyy/mm/dd"),BSAD,2,FALSE),""),IFERROR(VLOOKUP(A24,BSAD,2,FALSE),""))) -> 46230 | C24: =IFERROR(INDEX(Party_Ledger!$D$3:$D$100322,MATCH(ROWS($1:13),Party_Ledger!$K$3:$K$100322,0)),"") -> Advance | D24: =IFERROR(INDEX(Party_Ledger!$E$3:$E$100322,MATCH(ROWS($1:13),Party_Ledger!$K$3:$K$100322,0)),"") -> 0 | E24: =IFERROR(INDEX(Party_Ledger!$F$3:$F$100322,MATCH(ROWS($1:13),Party_Ledger!$K$3:$K$100322,0)),"") -> SURYA KC FOR SENSOR | F24: =IFERROR(INDEX(Party_Ledger!$G$3:$G$100322,MATCH(ROWS($1:13),Party_Ledger!$K$3:$K$100322,0)),"") -> 5000 | G24: =IFERROR(INDEX(Party_Ledger!$H$3:$H$100322,MATCH(ROWS($1:13),Party_Ledger!$K$3:$K$100322,0)),"") -> 0 | H24: =IF($A24="","",N($F24)-N($G24)) -> 5000
A25: =IFERROR(INDEX(Party_Ledger!$A$3:$A$100322, MATCH(ROWS($1:14), Party_Ledger!$K$3:$K$100322, 0)), "") -> 2083/04/11 | B25: =IF(A25="","",IF(ISNUMBER(A25),IFERROR(VLOOKUP(TEXT(A25,"yyyy/mm/dd"),BSAD,2,FALSE),""),IFERROR(VLOOKUP(A25,BSAD,2,FALSE),""))) -> 46230 | C25: =IFERROR(INDEX(Party_Ledger!$D$3:$D$100322,MATCH(ROWS($1:14),Party_Ledger!$K$3:$K$100322,0)),"") -> Advance | D25: =IFERROR(INDEX(Party_Ledger!$E$3:$E$100322,MATCH(ROWS($1:14),Party_Ledger!$K$3:$K$100322,0)),"") -> 0 | E25: =IFERROR(INDEX(Party_Ledger!$F$3:$F$100322,MATCH(ROWS($1:14),Party_Ledger!$K$3:$K$100322,0)),"") -> WOOD | F25: =IFERROR(INDEX(Party_Ledger!$G$3:$G$100322,MATCH(ROWS($1:14),Party_Ledger!$K$3:$K$100322,0)),"") -> 900 | G25: =IFERROR(INDEX(Party_Ledger!$H$3:$H$100322,MATCH(ROWS($1:14),Party_Ledger!$K$3:$K$100322,0)),"") -> 0 | H25: =IF($A25="","",N($F25)-N($G25)) -> 900
A26: =IFERROR(INDEX(Party_Ledger!$A$3:$A$100322, MATCH(ROWS($1:15), Party_Ledger!$K$3:$K$100322, 0)), "") -> 2083/04/14 | B26: =IF(A26="","",IF(ISNUMBER(A26),IFERROR(VLOOKUP(TEXT(A26,"yyyy/mm/dd"),BSAD,2,FALSE),""),IFERROR(VLOOKUP(A26,BSAD,2,FALSE),""))) -> 46233 | C26: =IFERROR(INDEX(Party_Ledger!$D$3:$D$100322,MATCH(ROWS($1:15),Party_Ledger!$K$3:$K$100322,0)),"") -> Advance | D26: =IFERROR(INDEX(Party_Ledger!$E$3:$E$100322,MATCH(ROWS($1:15),Party_Ledger!$K$3:$K$100322,0)),"") -> 0 | E26: =IFERROR(INDEX(Party_Ledger!$F$3:$F$100322,MATCH(ROWS($1:15),Party_Ledger!$K$3:$K$100322,0)),"") -> WOOD | F26: =IFERROR(INDEX(Party_Ledger!$G$3:$G$100322,MATCH(ROWS($1:15),Party_Ledger!$K$3:$K$100322,0)),"") -> 1800 | G26: =IFERROR(INDEX(Party_Ledger!$H$3:$H$100322,MATCH(ROWS($1:15),Party_Ledger!$K$3:$K$100322,0)),"") -> 0 | H26: =IF($A26="","",N($F26)-N($G26)) -> 1800
A27: =IFERROR(INDEX(Party_Ledger!$A$3:$A$100322, MATCH(ROWS($1:16), Party_Ledger!$K$3:$K$100322, 0)), "") -> 2083/04/18 | B27: =IF(A27="","",IF(ISNUMBER(A27),IFERROR(VLOOKUP(TEXT(A27,"yyyy/mm/dd"),BSAD,2,FALSE),""),IFERROR(VLOOKUP(A27,BSAD,2,FALSE),""))) -> 46237 | C27: =IFERROR(INDEX(Party_Ledger!$D$3:$D$100322,MATCH(ROWS($1:16),Party_Ledger!$K$3:$K$100322,0)),"") -> Advance | D27: =IFERROR(INDEX(Party_Ledger!$E$3:$E$100322,MATCH(ROWS($1:16),Party_Ledger!$K$3:$K$100322,0)),"") -> 0 | E27: =IFERROR(INDEX(Party_Ledger!$F$3:$F$100322,MATCH(ROWS($1:16),Party_Ledger!$K$3:$K$100322,0)),"") -> WOOD | F27: =IFERROR(INDEX(Party_Ledger!$G$3:$G$100322,MATCH(ROWS($1:16),Party_Ledger!$K$3:$K$100322,0)),"") -> 2700 | G27: =IFERROR(INDEX(Party_Ledger!$H$3:$H$100322,MATCH(ROWS($1:16),Party_Ledger!$K$3:$K$100322,0)),"") -> 0 | H27: =IF($A27="","",N($F27)-N($G27)) -> 2700
A28: =IFERROR(INDEX(Party_Ledger!$A$3:$A$100322, MATCH(ROWS($1:17), Party_Ledger!$K$3:$K$100322, 0)), "") -> 2083/05/05 | B28: =IF(A28="","",IF(ISNUMBER(A28),IFERROR(VLOOKUP(TEXT(A28,"yyyy/mm/dd"),BSAD,2,FALSE),""),IFERROR(VLOOKUP(A28,BSAD,2,FALSE),""))) -> 46255 | C28: =IFERROR(INDEX(Party_Ledger!$D$3:$D$100322,MATCH(ROWS($1:17),Party_Ledger!$K$3:$K$100322,0)),"") -> Advance | D28: =IFERROR(INDEX(Party_Ledger!$E$3:$E$100322,MATCH(ROWS($1:17),Party_Ledger!$K$3:$K$100322,0)),"") -> 0 | E28: =IFERROR(INDEX(Party_Ledger!$F$3:$F$100322,MATCH(ROWS($1:17),Party_Ledger!$K$3:$K$100322,0)),"") -> CASH | F28: =IFERROR(INDEX(Party_Ledger!$G$3:$G$100322,MATCH(ROWS($1:17),Party_Ledger!$K$3:$K$100322,0)),"") -> 50000 | G28: =IFERROR(INDEX(Party_Ledger!$H$3:$H$100322,MATCH(ROWS($1:17),Party_Ledger!$K$3:$K$100322,0)),"") -> 0 | H28: =IF($A28="","",N($F28)-N($G28)) -> 50000
A29: =IFERROR(INDEX(Party_Ledger!$A$3:$A$100322, MATCH(ROWS($1:18), Party_Ledger!$K$3:$K$100322, 0)), "") -> 2083/05/05 | B29: =IF(A29="","",IF(ISNUMBER(A29),IFERROR(VLOOKUP(TEXT(A29,"yyyy/mm/dd"),BSAD,2,FALSE),""),IFERROR(VLOOKUP(A29,BSAD,2,FALSE),""))) -> 46255 | C29: =IFERROR(INDEX(Party_Ledger!$D$3:$D$100322,MATCH(ROWS($1:18),Party_Ledger!$K$3:$K$100322,0)),"") -> Advance | D29: =IFERROR(INDEX(Party_Ledger!$E$3:$E$100322,MATCH(ROWS($1:18),Party_Ledger!$K$3:$K$100322,0)),"") -> 0 | E29: =IFERROR(INDEX(Party_Ledger!$F$3:$F$100322,MATCH(ROWS($1:18),Party_Ledger!$K$3:$K$100322,0)),"") -> CASH | F29: =IFERROR(INDEX(Party_Ledger!$G$3:$G$100322,MATCH(ROWS($1:18),Party_Ledger!$K$3:$K$100322,0)),"") -> 139865 | G29: =IFERROR(INDEX(Party_Ledger!$H$3:$H$100322,MATCH(ROWS($1:18),Party_Ledger!$K$3:$K$100322,0)),"") -> 0 | H29: =IF($A29="","",N($F29)-N($G29)) -> 139865
A30: =IFERROR(INDEX(Party_Ledger!$A$3:$A$100322, MATCH(ROWS($1:19), Party_Ledger!$K$3:$K$100322, 0)), "") -> 2083/05/07 | B30: =IF(A30="","",IF(ISNUMBER(A30),IFERROR(VLOOKUP(TEXT(A30,"yyyy/mm/dd"),BSAD,2,FALSE),""),IFERROR(VLOOKUP(A30,BSAD,2,FALSE),""))) -> 46257 | C30: =IFERROR(INDEX(Party_Ledger!$D$3:$D$100322,MATCH(ROWS($1:19),Party_Ledger!$K$3:$K$100322,0)),"") -> Advance | D30: =IFERROR(INDEX(Party_Ledger!$E$3:$E$100322,MATCH(ROWS($1:19),Party_Ledger!$K$3:$K$100322,0)),"") -> 0 | E30: =IFERROR(INDEX(Party_Ledger!$F$3:$F$100322,MATCH(ROWS($1:19),Party_Ledger!$K$3:$K$100322,0)),"") -> FOOD FOR 4 | F30: =IFERROR(INDEX(Party_Ledger!$G$3:$G$100322,MATCH(ROWS($1:19),Party_Ledger!$K$3:$K$100322,0)),"") -> 840 | G30: =IFERROR(INDEX(Party_Ledger!$H$3:$H$100322,MATCH(ROWS($1:19),Party_Ledger!$K$3:$K$100322,0)),"") -> 0 | H30: =IF($A30="","",N($F30)-N($G30)) -> 840
A31: =IFERROR(INDEX(Party_Ledger!$A$3:$A$100322, MATCH(ROWS($1:20), Party_Ledger!$K$3:$K$100322, 0)), "") -> 2083/05/07 | B31: =IF(A31="","",IF(ISNUMBER(A31),IFERROR(VLOOKUP(TEXT(A31,"yyyy/mm/dd"),BSAD,2,FALSE),""),IFERROR(VLOOKUP(A31,BSAD,2,FALSE),""))) -> 46257 | C31: =IFERROR(INDEX(Party_Ledger!$D$3:$D$100322,MATCH(ROWS($1:20),Party_Ledger!$K$3:$K$100322,0)),"") -> Advance | D31: =IFERROR(INDEX(Party_Ledger!$E$3:$E$100322,MATCH(ROWS($1:20),Party_Ledger!$K$3:$K$100322,0)),"") -> 0 | E31: =IFERROR(INDEX(Party_Ledger!$F$3:$F$100322,MATCH(ROWS($1:20),Party_Ledger!$K$3:$K$100322,0)),"") -> ADVANCE | F31: =IFERROR(INDEX(Party_Ledger!$G$3:$G$100322,MATCH(ROWS($1:20),Party_Ledger!$K$3:$K$100322,0)),"") -> 500 | G31: =IFERROR(INDEX(Party_Ledger!$H$3:$H$100322,MATCH(ROWS($1:20),Party_Ledger!$K$3:$K$100322,0)),"") -> 0 | H31: =IF($A31="","",N($F31)-N($G31)) -> 500
A32: =IFERROR(INDEX(Party_Ledger!$A$3:$A$100322, MATCH(ROWS($1:21), Party_Ledger!$K$3:$K$100322, 0)), "") -> 2083/05/08 | B32: =IF(A32="","",IF(ISNUMBER(A32),IFERROR(VLOOKUP(TEXT(A32,"yyyy/mm/dd"),BSAD,2,FALSE),""),IFERROR(VLOOKUP(A32,BSAD,2,FALSE),""))) -> 46258 | C32: =IFERROR(INDEX(Party_Ledger!$D$3:$D$100322,MATCH(ROWS($1:21),Party_Ledger!$K$3:$K$100322,0)),"") -> Advance | D32: =IFERROR(INDEX(Party_Ledger!$E$3:$E$100322,MATCH(ROWS($1:21),Party_Ledger!$K$3:$K$100322,0)),"") -> 0 | E32: =IFERROR(INDEX(Party_Ledger!$F$3:$F$100322,MATCH(ROWS($1:21),Party_Ledger!$K$3:$K$100322,0)),"") -> CLAMP FOR VEHICLE | F32: =IFERROR(INDEX(Party_Ledger!$G$3:$G$100322,MATCH(ROWS($1:21),Party_Ledger!$K$3:$K$100322,0)),"") -> 500 | G32: =IFERROR(INDEX(Party_Ledger!$H$3:$H$100322,MATCH(ROWS($1:21),Party_Ledger!$K$3:$K$100322,0)),"") -> 0 | H32: =IF($A32="","",N($F32)-N($G32)) -> 500
A33: =IFERROR(INDEX(Party_Ledger!$A$3:$A$100322, MATCH(ROWS($1:22), Party_Ledger!$K$3:$K$100322, 0)), "") -> 2083/05/08 | B33: =IF(A33="","",IF(ISNUMBER(A33),IFERROR(VLOOKUP(TEXT(A33,"yyyy/mm/dd"),BSAD,2,FALSE),""),IFERROR(VLOOKUP(A33,BSAD,2,FALSE),""))) -> 46258 | C33: =IFERROR(INDEX(Party_Ledger!$D$3:$D$100322,MATCH(ROWS($1:22),Party_Ledger!$K$3:$K$100322,0)),"") -> Advance | D33: =IFERROR(INDEX(Party_Ledger!$E$3:$E$100322,MATCH(ROWS($1:22),Party_Ledger!$K$3:$K$100322,0)),"") -> 0 | E33: =IFERROR(INDEX(Party_Ledger!$F$3:$F$100322,MATCH(ROWS($1:22),Party_Ledger!$K$3:$K$100322,0)),"") -> CHI. KHANA 2, WATER | F33: =IFERROR(INDEX(Party_Ledger!$G$3:$G$100322,MATCH(ROWS($1:22),Party_Ledger!$K$3:$K$100322,0)),"") -> 680 | G33: =IFERROR(INDEX(Party_Ledger!$H$3:$H$100322,MATCH(ROWS($1:22),Party_Ledger!$K$3:$K$100322,0)),"") -> 0 | H33: =IF($A33="","",N($F33)-N($G33)) -> 680
A34: =IFERROR(INDEX(Party_Ledger!$A$3:$A$100322, MATCH(ROWS($1:23), Party_Ledger!$K$3:$K$100322, 0)), "") -> 2083/05/10 | B34: =IF(A34="","",IF(ISNUMBER(A34),IFERROR(VLOOKUP(TEXT(A34,"yyyy/mm/dd"),BSAD,2,FALSE),""),IFERROR(VLOOKUP(A34,BSAD,2,FALSE),""))) -> 46260 | C34: =IFERROR(INDEX(Party_Ledger!$D$3:$D$100322,MATCH(ROWS($1:23),Party_Ledger!$K$3:$K$100322,0)),"") -> Advance | D34: =IFERROR(INDEX(Party_Ledger!$E$3:$E$100322,MATCH(ROWS($1:23),Party_Ledger!$K$3:$K$100322,0)),"") -> 0 | E34: =IFERROR(INDEX(Party_Ledger!$F$3:$F$100322,MATCH(ROWS($1:23),Party_Ledger!$K$3:$K$100322,0)),"") -> ADVANCE | F34: =IFERROR(INDEX(Party_Ledger!$G$3:$G$100322,MATCH(ROWS($1:23),Party_Ledger!$K$3:$K$100322,0)),"") -> 7000 | G34: =IFERROR(INDEX(Party_Ledger!$H$3:$H$100322,MATCH(ROWS($1:23),Party_Ledger!$K$3:$K$100322,0)),"") -> 0 | H34: =IF($A34="","",N($F34)-N($G34)) -> 7000
A35: =IFERROR(INDEX(Party_Ledger!$A$3:$A$100322, MATCH(ROWS($1:24), Party_Ledger!$K$3:$K$100322, 0)), "") -> 2083/05/11 | B35: =IF(A35="","",IF(ISNUMBER(A35),IFERROR(VLOOKUP(TEXT(A35,"yyyy/mm/dd"),BSAD,2,FALSE),""),IFERROR(VLOOKUP(A35,BSAD,2,FALSE),""))) -> 46261 | C35: =IFERROR(INDEX(Party_Ledger!$D$3:$D$100322,MATCH(ROWS($1:24),Party_Ledger!$K$3:$K$100322,0)),"") -> Advance | D35: =IFERROR(INDEX(Party_Ledger!$E$3:$E$100322,MATCH(ROWS($1:24),Party_Ledger!$K$3:$K$100322,0)),"") -> 0 | E35: =IFERROR(INDEX(Party_Ledger!$F$3:$F$100322,MATCH(ROWS($1:24),Party_Ledger!$K$3:$K$100322,0)),"") -> WOOD | F35: =IFERROR(INDEX(Party_Ledger!$G$3:$G$100322,MATCH(ROWS($1:24),Party_Ledger!$K$3:$K$100322,0)),"") -> 900 | G35: =IFERROR(INDEX(Party_Ledger!$H$3:$H$100322,MATCH(ROWS($1:24),Party_Ledger!$K$3:$K$100322,0)),"") -> 0 | H35: =IF($A35="","",N($F35)-N($G35)) -> 900
A36: =IFERROR(INDEX(Party_Ledger!$A$3:$A$100322, MATCH(ROWS($1:25), Party_Ledger!$K$3:$K$100322, 0)), "") -> 2083/05/15 | B36: =IF(A36="","",IF(ISNUMBER(A36),IFERROR(VLOOKUP(TEXT(A36,"yyyy/mm/dd"),BSAD,2,FALSE),""),IFERROR(VLOOKUP(A36,BSAD,2,FALSE),""))) -> 46265 | C36: =IFERROR(INDEX(Party_Ledger!$D$3:$D$100322,MATCH(ROWS($1:25),Party_Ledger!$K$3:$K$100322,0)),"") -> Advance | D36: =IFERROR(INDEX(Party_Ledger!$E$3:$E$100322,MATCH(ROWS($1:25),Party_Ledger!$K$3:$K$100322,0)),"") -> 0 | E36: =IFERROR(INDEX(Party_Ledger!$F$3:$F$100322,MATCH(ROWS($1:25),Party_Ledger!$K$3:$K$100322,0)),"") -> ELECTRICITY MAINTINANCE SAIKRIKPA | F36: =IFERROR(INDEX(Party_Ledger!$G$3:$G$100322,MATCH(ROWS($1:25),Party_Ledger!$K$3:$K$100322,0)),"") -> 5500 | G36: =IFERROR(INDEX(Party_Ledger!$H$3:$H$100322,MATCH(ROWS($1:25),Party_Ledger!$K$3:$K$100322,0)),"") -> 0 | H36: =IF($A36="","",N($F36)-N($G36)) -> 5500
A37: =IFERROR(INDEX(Party_Ledger!$A$3:$A$100322, MATCH(ROWS($1:26), Party_Ledger!$K$3:$K$100322, 0)), "") -> 2083/05/17 | B37: =IF(A37="","",IF(ISNUMBER(A37),IFERROR(VLOOKUP(TEXT(A37,"yyyy/mm/dd"),BSAD,2,FALSE),""),IFERROR(VLOOKUP(A37,BSAD,2,FALSE),""))) -> 46267 | C37: =IFERROR(INDEX(Party_Ledger!$D$3:$D$100322,MATCH(ROWS($1:26),Party_Ledger!$K$3:$K$100322,0)),"") -> Advance | D37: =IFERROR(INDEX(Party_Ledger!$E$3:$E$100322,MATCH(ROWS($1:26),Party_Ledger!$K$3:$K$100322,0)),"") -> 0 | E37: =IFERROR(INDEX(Party_Ledger!$F$3:$F$100322,MATCH(ROWS($1:26),Party_Ledger!$K$3:$K$100322,0)),"") -> WOOD | F37: =IFERROR(INDEX(Party_Ledger!$G$3:$G$100322,MATCH(ROWS($1:26),Party_Ledger!$K$3:$K$100322,0)),"") -> 1800 | G37: =IFERROR(INDEX(Party_Ledger!$H$3:$H$100322,MATCH(ROWS($1:26),Party_Ledger!$K$3:$K$100322,0)),"") -> 0 | H37: =IF($A37="","",N($F37)-N($G37)) -> 1800
A38: =IFERROR(INDEX(Party_Ledger!$A$3:$A$100322, MATCH(ROWS($1:27), Party_Ledger!$K$3:$K$100322, 0)), "") -> 2083/05/17 | B38: =IF(A38="","",IF(ISNUMBER(A38),IFERROR(VLOOKUP(TEXT(A38,"yyyy/mm/dd"),BSAD,2,FALSE),""),IFERROR(VLOOKUP(A38,BSAD,2,FALSE),""))) -> 46267 | C38: =IFERROR(INDEX(Party_Ledger!$D$3:$D$100322,MATCH(ROWS($1:27),Party_Ledger!$K$3:$K$100322,0)),"") -> Advance | D38: =IFERROR(INDEX(Party_Ledger!$E$3:$E$100322,MATCH(ROWS($1:27),Party_Ledger!$K$3:$K$100322,0)),"") -> 0 | E38: =IFERROR(INDEX(Party_Ledger!$F$3:$F$100322,MATCH(ROWS($1:27),Party_Ledger!$K$3:$K$100322,0)),"") -> SENSOR MAINTINANCE SAIKRIPA | F38: =IFERROR(INDEX(Party_Ledger!$G$3:$G$100322,MATCH(ROWS($1:27),Party_Ledger!$K$3:$K$100322,0)),"") -> 1500 | G38: =IFERROR(INDEX(Party_Ledger!$H$3:$H$100322,MATCH(ROWS($1:27),Party_Ledger!$K$3:$K$100322,0)),"") -> 0 | H38: =IF($A38="","",N($F38)-N($G38)) -> 1500
A39: =IFERROR(INDEX(Party_Ledger!$A$3:$A$100322, MATCH(ROWS($1:28), Party_Ledger!$K$3:$K$100322, 0)), "") -> 2083/05/17 | B39: =IF(A39="","",IF(ISNUMBER(A39),IFERROR(VLOOKUP(TEXT(A39,"yyyy/mm/dd"),BSAD,2,FALSE),""),IFERROR(VLOOKUP(A39,BSAD,2,FALSE),""))) -> 46267 | C39: =IFERROR(INDEX(Party_Ledger!$D$3:$D$100322,MATCH(ROWS($1:28),Party_Ledger!$K$3:$K$100322,0)),"") -> Advance | D39: =IFERROR(INDEX(Party_Ledger!$E$3:$E$100322,MATCH(ROWS($1:28),Party_Ledger!$K$3:$K$100322,0)),"") -> 0 | E39: =IFERROR(INDEX(Party_Ledger!$F$3:$F$100322,MATCH(ROWS($1:28),Party_Ledger!$K$3:$K$100322,0)),"") -> TRANSPORTATION FOR PIPE WELDING LABOUR | F39: =IFERROR(INDEX(Party_Ledger!$G$3:$G$100322,MATCH(ROWS($1:28),Party_Ledger!$K$3:$K$100322,0)),"") -> 400 | G39: =IFERROR(INDEX(Party_Ledger!$H$3:$H$100322,MATCH(ROWS($1:28),Party_Ledger!$K$3:$K$100322,0)),"") -> 0 | H39: =IF($A39="","",N($F39)-N($G39)) -> 400
A40: =IFERROR(INDEX(Party_Ledger!$A$3:$A$100322, MATCH(ROWS($1:29), Party_Ledger!$K$3:$K$100322, 0)), "") -> 2083/05/17 | B40: =IF(A40="","",IF(ISNUMBER(A40),IFERROR(VLOOKUP(TEXT(A40,"yyyy/mm/dd"),BSAD,2,FALSE),""),IFERROR(VLOOKUP(A40,BSAD,2,FALSE),""))) -> 46267 | C40: =IFERROR(INDEX(Party_Ledger!$D$3:$D$100322,MATCH(ROWS($1:29),Party_Ledger!$K$3:$K$100322,0)),"") -> Advance | D40: =IFERROR(INDEX(Party_Ledger!$E$3:$E$100322,MATCH(ROWS($1:29),Party_Ledger!$K$3:$K$100322,0)),"") -> 0 | E40: =IFERROR(INDEX(Party_Ledger!$F$3:$F$100322,MATCH(ROWS($1:29),Party_Ledger!$K$3:$K$100322,0)),"") -> OIL FOR VEHICLE TO BHAIRAHAWA WELDING | F40: =IFERROR(INDEX(Party_Ledger!$G$3:$G$100322,MATCH(ROWS($1:29),Party_Ledger!$K$3:$K$100322,0)),"") -> 2000 | G40: =IFERROR(INDEX(Party_Ledger!$H$3:$H$100322,MATCH(ROWS($1:29),Party_Ledger!$K$3:$K$100322,0)),"") -> 0 | H40: =IF($A40="","",N($F40)-N($G40)) -> 2000
A41: =IFERROR(INDEX(Party_Ledger!$A$3:$A$100322, MATCH(ROWS($1:30), Party_Ledger!$K$3:$K$100322, 0)), "") -> 2083/05/27 | B41: =IF(A41="","",IF(ISNUMBER(A41),IFERROR(VLOOKUP(TEXT(A41,"yyyy/mm/dd"),BSAD,2,FALSE),""),IFERROR(VLOOKUP(A41,BSAD,2,FALSE),""))) -> 46277 | C41: =IFERROR(INDEX(Party_Ledger!$D$3:$D$100322,MATCH(ROWS($1:30),Party_Ledger!$K$3:$K$100322,0)),"") -> Advance | D41: =IFERROR(INDEX(Party_Ledger!$E$3:$E$100322,MATCH(ROWS($1:30),Party_Ledger!$K$3:$K$100322,0)),"") -> 0 | E41: =IFERROR(INDEX(Party_Ledger!$F$3:$F$100322,MATCH(ROWS($1:30),Party_Ledger!$K$3:$K$100322,0)),"") -> TEEN AND DOOR MAINTINANCE | F41: =IFERROR(INDEX(Party_Ledger!$G$3:$G$100322,MATCH(ROWS($1:30),Party_Ledger!$K$3:$K$100322,0)),"") -> 11300 | G41: =IFERROR(INDEX(Party_Ledger!$H$3:$H$100322,MATCH(ROWS($1:30),Party_Ledger!$K$3:$K$100322,0)),"") -> 0 | H41: =IF($A41="","",N($F41)-N($G41)) -> 11300
A42: =IFERROR(INDEX(Party_Ledger!$A$3:$A$100322, MATCH(ROWS($1:31), Party_Ledger!$K$3:$K$100322, 0)), "") -> 2083/05/15 | B42: =IF(A42="","",IF(ISNUMBER(A42),IFERROR(VLOOKUP(TEXT(A42,"yyyy/mm/dd"),BSAD,2,FALSE),""),IFERROR(VLOOKUP(A42,BSAD,2,FALSE),""))) -> 46265 | C42: =IFERROR(INDEX(Party_Ledger!$D$3:$D$100322,MATCH(ROWS($1:31),Party_Ledger!$K$3:$K$100322,0)),"") -> Advance | D42: =IFERROR(INDEX(Party_Ledger!$E$3:$E$100322,MATCH(ROWS($1:31),Party_Ledger!$K$3:$K$100322,0)),"") -> 0 | E42: =IFERROR(INDEX(Party_Ledger!$F$3:$F$100322,MATCH(ROWS($1:31),Party_Ledger!$K$3:$K$100322,0)),"") -> CREAM SEPERATOR MAINTINANCE | F42: =IFERROR(INDEX(Party_Ledger!$G$3:$G$100322,MATCH(ROWS($1:31),Party_Ledger!$K$3:$K$100322,0)),"") -> 1800 | G42: =IFERROR(INDEX(Party_Ledger!$H$3:$H$100322,MATCH(ROWS($1:31),Party_Ledger!$K$3:$K$100322,0)),"") -> 0 | H42: =IF($A42="","",N($F42)-N($G42)) -> 1800
A43: =IFERROR(INDEX(Party_Ledger!$A$3:$A$100322, MATCH(ROWS($1:32), Party_Ledger!$K$3:$K$100322, 0)), "") -> 2083/06/03 | B43: =IF(A43="","",IF(ISNUMBER(A43),IFERROR(VLOOKUP(TEXT(A43,"yyyy/mm/dd"),BSAD,2,FALSE),""),IFERROR(VLOOKUP(A43,BSAD,2,FALSE),""))) -> 46284 | C43: =IFERROR(INDEX(Party_Ledger!$D$3:$D$100322,MATCH(ROWS($1:32),Party_Ledger!$K$3:$K$100322,0)),"") -> Payment | D43: =IFERROR(INDEX(Party_Ledger!$E$3:$E$100322,MATCH(ROWS($1:32),Party_Ledger!$K$3:$K$100322,0)),"") -> 0 | E43: =IFERROR(INDEX(Party_Ledger!$F$3:$F$100322,MATCH(ROWS($1:32),Party_Ledger!$K$3:$K$100322,0)),"") -> SRAWAN ELECTRICITY BILL | F43: =IFERROR(INDEX(Party_Ledger!$G$3:$G$100322,MATCH(ROWS($1:32),Party_Ledger!$K$3:$K$100322,0)),"") -> 10000 | G43: =IFERROR(INDEX(Party_Ledger!$H$3:$H$100322,MATCH(ROWS($1:32),Party_Ledger!$K$3:$K$100322,0)),"") -> 0 | H43: =IF($A43="","",N($F43)-N($G43)) -> 10000
A44: =IFERROR(INDEX(Party_Ledger!$A$3:$A$100322, MATCH(ROWS($1:33), Party_Ledger!$K$3:$K$100322, 0)), "") -> 66929 | B44: =IF(A44="","",IF(ISNUMBER(A44),IFERROR(VLOOKUP(TEXT(A44,"yyyy/mm/dd"),BSAD,2,FALSE),""),IFERROR(VLOOKUP(A44,BSAD,2,FALSE),""))) -> 46216 | C44: =IFERROR(INDEX(Party_Ledger!$D$3:$D$100322,MATCH(ROWS($1:33),Party_Ledger!$K$3:$K$100322,0)),"") -> SAI KRIPA KSS LTD | D44: =IFERROR(INDEX(Party_Ledger!$E$3:$E$100322,MATCH(ROWS($1:33),Party_Ledger!$K$3:$K$100322,0)),"") -> QR-002 | E44: =IFERROR(INDEX(Party_Ledger!$F$3:$F$100322,MATCH(ROWS($1:33),Party_Ledger!$K$3:$K$100322,0)),"") -> ONLINE TRANSFERRED TO MODERN AGRO | F44: =IFERROR(INDEX(Party_Ledger!$G$3:$G$100322,MATCH(ROWS($1:33),Party_Ledger!$K$3:$K$100322,0)),"") -> 100000 | G44: =IFERROR(INDEX(Party_Ledger!$H$3:$H$100322,MATCH(ROWS($1:33),Party_Ledger!$K$3:$K$100322,0)),"") -> 0 | H44: =IF($A44="","",N($F44)-N($G44)) -> 100000
A45: =IFERROR(INDEX(Party_Ledger!$A$3:$A$100322, MATCH(ROWS($1:34), Party_Ledger!$K$3:$K$100322, 0)), "") -> 66979 | B45: =IF(A45="","",IF(ISNUMBER(A45),IFERROR(VLOOKUP(TEXT(A45,"yyyy/mm/dd"),BSAD,2,FALSE),""),IFERROR(VLOOKUP(A45,BSAD,2,FALSE),""))) -> 46268 | C45: =IFERROR(INDEX(Party_Ledger!$D$3:$D$100322,MATCH(ROWS($1:34),Party_Ledger!$K$3:$K$100322,0)),"") -> SAI KRIPA KSS LTD | D45: =IFERROR(INDEX(Party_Ledger!$E$3:$E$100322,MATCH(ROWS($1:34),Party_Ledger!$K$3:$K$100322,0)),"") -> QR-054 | E45: =IFERROR(INDEX(Party_Ledger!$F$3:$F$100322,MATCH(ROWS($1:34),Party_Ledger!$K$3:$K$100322,0)),"") -> ONLINE PAID TO NEW GODAR FOR SS PIPE WELDING | F45: =IFERROR(INDEX(Party_Ledger!$G$3:$G$100322,MATCH(ROWS($1:34),Party_Ledger!$K$3:$K$100322,0)),"") -> 15820 | G45: =IFERROR(INDEX(Party_Ledger!$H$3:$H$100322,MATCH(ROWS($1:34),Party_Ledger!$K$3:$K$100322,0)),"") -> 0 | H45: =IF($A45="","",N($F45)-N($G45)) -> 15820
A46: =IFERROR(INDEX(Party_Ledger!$A$3:$A$100322, MATCH(ROWS($1:35), Party_Ledger!$K$3:$K$100322, 0)), "") | B46: =IF(A46="","",IF(ISNUMBER(A46),IFERROR(VLOOKUP(TEXT(A46,"yyyy/mm/dd"),BSAD,2,FALSE),""),IFERROR(VLOOKUP(A46,BSAD,2,FALSE),""))) | C46: =IFERROR(INDEX(Party_Ledger!$D$3:$D$100322,MATCH(ROWS($1:35),Party_Ledger!$K$3:$K$100322,0)),"") | D46: =IFERROR(INDEX(Party_Ledger!$E$3:$E$100322,MATCH(ROWS($1:35),Party_Ledger!$K$3:$K$100322,0)),"") | E46: =IFERROR(INDEX(Party_Ledger!$F$3:$F$100322,MATCH(ROWS($1:35),Party_Ledger!$K$3:$K$100322,0)),"") | F46: =IFERROR(INDEX(Party_Ledger!$G$3:$G$100322,MATCH(ROWS($1:35),Party_Ledger!$K$3:$K$100322,0)),"") | G46: =IFERROR(INDEX(Party_Ledger!$H$3:$H$100322,MATCH(ROWS($1:35),Party_Ledger!$K$3:$K$100322,0)),"") | H46: =IF($A46="","",N($F46)-N($G46))
A47: =IFERROR(INDEX(Party_Ledger!$A$3:$A$100322, MATCH(ROWS($1:36), Party_Ledger!$K$3:$K$100322, 0)), "") | B47: =IF(A47="","",IF(ISNUMBER(A47),IFERROR(VLOOKUP(TEXT(A47,"yyyy/mm/dd"),BSAD,2,FALSE),""),IFERROR(VLOOKUP(A47,BSAD,2,FALSE),""))) | C47: =IFERROR(INDEX(Party_Ledger!$D$3:$D$100322,MATCH(ROWS($1:36),Party_Ledger!$K$3:$K$100322,0)),"") | D47: =IFERROR(INDEX(Party_Ledger!$E$3:$E$100322,MATCH(ROWS($1:36),Party_Ledger!$K$3:$K$100322,0)),"") | E47: =IFERROR(INDEX(Party_Ledger!$F$3:$F$100322,MATCH(ROWS($1:36),Party_Ledger!$K$3:$K$100322,0)),"") | F47: =IFERROR(INDEX(Party_Ledger!$G$3:$G$100322,MATCH(ROWS($1:36),Party_Ledger!$K$3:$K$100322,0)),"") | G47: =IFERROR(INDEX(Party_Ledger!$H$3:$H$100322,MATCH(ROWS($1:36),Party_Ledger!$K$3:$K$100322,0)),"") | H47: =IF($A47="","",N($F47)-N($G47))
A48: =IFERROR(INDEX(Party_Ledger!$A$3:$A$100322, MATCH(ROWS($1:37), Party_Ledger!$K$3:$K$100322, 0)), "") | B48: =IF(A48="","",IF(ISNUMBER(A48),IFERROR(VLOOKUP(TEXT(A48,"yyyy/mm/dd"),BSAD,2,FALSE),""),IFERROR(VLOOKUP(A48,BSAD,2,FALSE),""))) | C48: =IFERROR(INDEX(Party_Ledger!$D$3:$D$100322,MATCH(ROWS($1:37),Party_Ledger!$K$3:$K$100322,0)),"") | D48: =IFERROR(INDEX(Party_Ledger!$E$3:$E$100322,MATCH(ROWS($1:37),Party_Ledger!$K$3:$K$100322,0)),"") | E48: =IFERROR(INDEX(Party_Ledger!$F$3:$F$100322,MATCH(ROWS($1:37),Party_Ledger!$K$3:$K$100322,0)),"") | F48: =IFERROR(INDEX(Party_Ledger!$G$3:$G$100322,MATCH(ROWS($1:37),Party_Ledger!$K$3:$K$100322,0)),"") | G48: =IFERROR(INDEX(Party_Ledger!$H$3:$H$100322,MATCH(ROWS($1:37),Party_Ledger!$K$3:$K$100322,0)),"") | H48: =IF($A48="","",N($F48)-N($G48))
A49: =IFERROR(INDEX(Party_Ledger!$A$3:$A$100322, MATCH(ROWS($1:38), Party_Ledger!$K$3:$K$100322, 0)), "") | B49: =IF(A49="","",IF(ISNUMBER(A49),IFERROR(VLOOKUP(TEXT(A49,"yyyy/mm/dd"),BSAD,2,FALSE),""),IFERROR(VLOOKUP(A49,BSAD,2,FALSE),""))) | C49: =IFERROR(INDEX(Party_Ledger!$D$3:$D$100322,MATCH(ROWS($1:38),Party_Ledger!$K$3:$K$100322,0)),"") | D49: =IFERROR(INDEX(Party_Ledger!$E$3:$E$100322,MATCH(ROWS($1:38),Party_Ledger!$K$3:$K$100322,0)),"") | E49: =IFERROR(INDEX(Party_Ledger!$F$3:$F$100322,MATCH(ROWS($1:38),Party_Ledger!$K$3:$K$100322,0)),"") | F49: =IFERROR(INDEX(Party_Ledger!$G$3:$G$100322,MATCH(ROWS($1:38),Party_Ledger!$K$3:$K$100322,0)),"") | G49: =IFERROR(INDEX(Party_Ledger!$H$3:$H$100322,MATCH(ROWS($1:38),Party_Ledger!$K$3:$K$100322,0)),"") | H49: =IF($A49="","",N($F49)-N($G49))
A50: =IFERROR(INDEX(Party_Ledger!$A$3:$A$100322, MATCH(ROWS($1:39), Party_Ledger!$K$3:$K$100322, 0)), "") | B50: =IF(A50="","",IF(ISNUMBER(A50),IFERROR(VLOOKUP(TEXT(A50,"yyyy/mm/dd"),BSAD,2,FALSE),""),IFERROR(VLOOKUP(A50,BSAD,2,FALSE),""))) | C50: =IFERROR(INDEX(Party_Ledger!$D$3:$D$100322,MATCH(ROWS($1:39),Party_Ledger!$K$3:$K$100322,0)),"") | D50: =IFERROR(INDEX(Party_Ledger!$E$3:$E$100322,MATCH(ROWS($1:39),Party_Ledger!$K$3:$K$100322,0)),"") | E50: =IFERROR(INDEX(Party_Ledger!$F$3:$F$100322,MATCH(ROWS($1:39),Party_Ledger!$K$3:$K$100322,0)),"") | F50: =IFERROR(INDEX(Party_Ledger!$G$3:$G$100322,MATCH(ROWS($1:39),Party_Ledger!$K$3:$K$100322,0)),"") | G50: =IFERROR(INDEX(Party_Ledger!$H$3:$H$100322,MATCH(ROWS($1:39),Party_Ledger!$K$3:$K$100322,0)),"") | H50: =IF($A50="","",N($F50)-N($G50))
A51: =IFERROR(INDEX(Party_Ledger!$A$3:$A$100322, MATCH(ROWS($1:40), Party_Ledger!$K$3:$K$100322, 0)), "") | B51: =IF(A51="","",IF(ISNUMBER(A51),IFERROR(VLOOKUP(TEXT(A51,"yyyy/mm/dd"),BSAD,2,FALSE),""),IFERROR(VLOOKUP(A51,BSAD,2,FALSE),""))) | C51: =IFERROR(INDEX(Party_Ledger!$D$3:$D$100322,MATCH(ROWS($1:40),Party_Ledger!$K$3:$K$100322,0)),"") | D51: =IFERROR(INDEX(Party_Ledger!$E$3:$E$100322,MATCH(ROWS($1:40),Party_Ledger!$K$3:$K$100322,0)),"") | E51: =IFERROR(INDEX(Party_Ledger!$F$3:$F$100322,MATCH(ROWS($1:40),Party_Ledger!$K$3:$K$100322,0)),"") | F51: =IFERROR(INDEX(Party_Ledger!$G$3:$G$100322,MATCH(ROWS($1:40),Party_Ledger!$K$3:$K$100322,0)),"") | G51: =IFERROR(INDEX(Party_Ledger!$H$3:$H$100322,MATCH(ROWS($1:40),Party_Ledger!$K$3:$K$100322,0)),"") | H51: =IF($A51="","",N($F51)-N($G51))
A52: =IFERROR(INDEX(Party_Ledger!$A$3:$A$100322, MATCH(ROWS($1:41), Party_Ledger!$K$3:$K$100322, 0)), "") | B52: =IF(A52="","",IF(ISNUMBER(A52),IFERROR(VLOOKUP(TEXT(A52,"yyyy/mm/dd"),BSAD,2,FALSE),""),IFERROR(VLOOKUP(A52,BSAD,2,FALSE),""))) | C52: =IFERROR(INDEX(Party_Ledger!$D$3:$D$100322,MATCH(ROWS($1:41),Party_Ledger!$K$3:$K$100322,0)),"") | D52: =IFERROR(INDEX(Party_Ledger!$E$3:$E$100322,MATCH(ROWS($1:41),Party_Ledger!$K$3:$K$100322,0)),"") | E52: =IFERROR(INDEX(Party_Ledger!$F$3:$F$100322,MATCH(ROWS($1:41),Party_Ledger!$K$3:$K$100322,0)),"") | F52: =IFERROR(INDEX(Party_Ledger!$G$3:$G$100322,MATCH(ROWS($1:41),Party_Ledger!$K$3:$K$100322,0)),"") | G52: =IFERROR(INDEX(Party_Ledger!$H$3:$H$100322,MATCH(ROWS($1:41),Party_Ledger!$K$3:$K$100322,0)),"") | H52: =IF($A52="","",N($F52)-N($G52))
A53: =IFERROR(INDEX(Party_Ledger!$A$3:$A$100322, MATCH(ROWS($1:42), Party_Ledger!$K$3:$K$100322, 0)), "") | B53: =IF(A53="","",IF(ISNUMBER(A53),IFERROR(VLOOKUP(TEXT(A53,"yyyy/mm/dd"),BSAD,2,FALSE),""),IFERROR(VLOOKUP(A53,BSAD,2,FALSE),""))) | C53: =IFERROR(INDEX(Party_Ledger!$D$3:$D$100322,MATCH(ROWS($1:42),Party_Ledger!$K$3:$K$100322,0)),"") | D53: =IFERROR(INDEX(Party_Ledger!$E$3:$E$100322,MATCH(ROWS($1:42),Party_Ledger!$K$3:$K$100322,0)),"") | E53: =IFERROR(INDEX(Party_Ledger!$F$3:$F$100322,MATCH(ROWS($1:42),Party_Ledger!$K$3:$K$100322,0)),"") | F53: =IFERROR(INDEX(Party_Ledger!$G$3:$G$100322,MATCH(ROWS($1:42),Party_Ledger!$K$3:$K$100322,0)),"") | G53: =IFERROR(INDEX(Party_Ledger!$H$3:$H$100322,MATCH(ROWS($1:42),Party_Ledger!$K$3:$K$100322,0)),"") | H53: =IF($A53="","",N($F53)-N($G53))
A54: =IFERROR(INDEX(Party_Ledger!$A$3:$A$100322, MATCH(ROWS($1:43), Party_Ledger!$K$3:$K$100322, 0)), "") | B54: =IF(A54="","",IF(ISNUMBER(A54),IFERROR(VLOOKUP(TEXT(A54,"yyyy/mm/dd"),BSAD,2,FALSE),""),IFERROR(VLOOKUP(A54,BSAD,2,FALSE),""))) | C54: =IFERROR(INDEX(Party_Ledger!$D$3:$D$100322,MATCH(ROWS($1:43),Party_Ledger!$K$3:$K$100322,0)),"") | D54: =IFERROR(INDEX(Party_Ledger!$E$3:$E$100322,MATCH(ROWS($1:43),Party_Ledger!$K$3:$K$100322,0)),"") | E54: =IFERROR(INDEX(Party_Ledger!$F$3:$F$100322,MATCH(ROWS($1:43),Party_Ledger!$K$3:$K$100322,0)),"") | F54: =IFERROR(INDEX(Party_Ledger!$G$3:$G$100322,MATCH(ROWS($1:43),Party_Ledger!$K$3:$K$100322,0)),"") | G54: =IFERROR(INDEX(Party_Ledger!$H$3:$H$100322,MATCH(ROWS($1:43),Party_Ledger!$K$3:$K$100322,0)),"") | H54: =IF($A54="","",N($F54)-N($G54))
A55: =IFERROR(INDEX(Party_Ledger!$A$3:$A$100322, MATCH(ROWS($1:44), Party_Ledger!$K$3:$K$100322, 0)), "") | B55: =IF(A55="","",IF(ISNUMBER(A55),IFERROR(VLOOKUP(TEXT(A55,"yyyy/mm/dd"),BSAD,2,FALSE),""),IFERROR(VLOOKUP(A55,BSAD,2,FALSE),""))) | C55: =IFERROR(INDEX(Party_Ledger!$D$3:$D$100322,MATCH(ROWS($1:44),Party_Ledger!$K$3:$K$100322,0)),"") | D55: =IFERROR(INDEX(Party_Ledger!$E$3:$E$100322,MATCH(ROWS($1:44),Party_Ledger!$K$3:$K$100322,0)),"") | E55: =IFERROR(INDEX(Party_Ledger!$F$3:$F$100322,MATCH(ROWS($1:44),Party_Ledger!$K$3:$K$100322,0)),"") | F55: =IFERROR(INDEX(Party_Ledger!$G$3:$G$100322,MATCH(ROWS($1:44),Party_Ledger!$K$3:$K$100322,0)),"") | G55: =IFERROR(INDEX(Party_Ledger!$H$3:$H$100322,MATCH(ROWS($1:44),Party_Ledger!$K$3:$K$100322,0)),"") | H55: =IF($A55="","",N($F55)-N($G55))
A56: =IFERROR(INDEX(Party_Ledger!$A$3:$A$100322, MATCH(ROWS($1:45), Party_Ledger!$K$3:$K$100322, 0)), "") | B56: =IF(A56="","",IF(ISNUMBER(A56),IFERROR(VLOOKUP(TEXT(A56,"yyyy/mm/dd"),BSAD,2,FALSE),""),IFERROR(VLOOKUP(A56,BSAD,2,FALSE),""))) | C56: =IFERROR(INDEX(Party_Ledger!$D$3:$D$100322,MATCH(ROWS($1:45),Party_Ledger!$K$3:$K$100322,0)),"") | D56: =IFERROR(INDEX(Party_Ledger!$E$3:$E$100322,MATCH(ROWS($1:45),Party_Ledger!$K$3:$K$100322,0)),"") | E56: =IFERROR(INDEX(Party_Ledger!$F$3:$F$100322,MATCH(ROWS($1:45),Party_Ledger!$K$3:$K$100322,0)),"") | F56: =IFERROR(INDEX(Party_Ledger!$G$3:$G$100322,MATCH(ROWS($1:45),Party_Ledger!$K$3:$K$100322,0)),"") | G56: =IFERROR(INDEX(Party_Ledger!$H$3:$H$100322,MATCH(ROWS($1:45),Party_Ledger!$K$3:$K$100322,0)),"") | H56: =IF($A56="","",N($F56)-N($G56))
A57: =IFERROR(INDEX(Party_Ledger!$A$3:$A$100322, MATCH(ROWS($1:46), Party_Ledger!$K$3:$K$100322, 0)), "") | B57: =IF(A57="","",IF(ISNUMBER(A57),IFERROR(VLOOKUP(TEXT(A57,"yyyy/mm/dd"),BSAD,2,FALSE),""),IFERROR(VLOOKUP(A57,BSAD,2,FALSE),""))) | C57: =IFERROR(INDEX(Party_Ledger!$D$3:$D$100322,MATCH(ROWS($1:46),Party_Ledger!$K$3:$K$100322,0)),"") | D57: =IFERROR(INDEX(Party_Ledger!$E$3:$E$100322,MATCH(ROWS($1:46),Party_Ledger!$K$3:$K$100322,0)),"") | E57: =IFERROR(INDEX(Party_Ledger!$F$3:$F$100322,MATCH(ROWS($1:46),Party_Ledger!$K$3:$K$100322,0)),"") | F57: =IFERROR(INDEX(Party_Ledger!$G$3:$G$100322,MATCH(ROWS($1:46),Party_Ledger!$K$3:$K$100322,0)),"") | G57: =IFERROR(INDEX(Party_Ledger!$H$3:$H$100322,MATCH(ROWS($1:46),Party_Ledger!$K$3:$K$100322,0)),"") | H57: =IF($A57="","",N($F57)-N($G57))
A58: =IFERROR(INDEX(Party_Ledger!$A$3:$A$100322, MATCH(ROWS($1:47), Party_Ledger!$K$3:$K$100322, 0)), "") | B58: =IF(A58="","",IF(ISNUMBER(A58),IFERROR(VLOOKUP(TEXT(A58,"yyyy/mm/dd"),BSAD,2,FALSE),""),IFERROR(VLOOKUP(A58,BSAD,2,FALSE),""))) | C58: =IFERROR(INDEX(Party_Ledger!$D$3:$D$100322,MATCH(ROWS($1:47),Party_Ledger!$K$3:$K$100322,0)),"") | D58: =IFERROR(INDEX(Party_Ledger!$E$3:$E$100322,MATCH(ROWS($1:47),Party_Ledger!$K$3:$K$100322,0)),"") | E58: =IFERROR(INDEX(Party_Ledger!$F$3:$F$100322,MATCH(ROWS($1:47),Party_Ledger!$K$3:$K$100322,0)),"") | F58: =IFERROR(INDEX(Party_Ledger!$G$3:$G$100322,MATCH(ROWS($1:47),Party_Ledger!$K$3:$K$100322,0)),"") | G58: =IFERROR(INDEX(Party_Ledger!$H$3:$H$100322,MATCH(ROWS($1:47),Party_Ledger!$K$3:$K$100322,0)),"") | H58: =IF($A58="","",N($F58)-N($G58))
A59: =IFERROR(INDEX(Party_Ledger!$A$3:$A$100322, MATCH(ROWS($1:48), Party_Ledger!$K$3:$K$100322, 0)), "") | B59: =IF(A59="","",IF(ISNUMBER(A59),IFERROR(VLOOKUP(TEXT(A59,"yyyy/mm/dd"),BSAD,2,FALSE),""),IFERROR(VLOOKUP(A59,BSAD,2,FALSE),""))) | C59: =IFERROR(INDEX(Party_Ledger!$D$3:$D$100322,MATCH(ROWS($1:48),Party_Ledger!$K$3:$K$100322,0)),"") | D59: =IFERROR(INDEX(Party_Ledger!$E$3:$E$100322,MATCH(ROWS($1:48),Party_Ledger!$K$3:$K$100322,0)),"") | E59: =IFERROR(INDEX(Party_Ledger!$F$3:$F$100322,MATCH(ROWS($1:48),Party_Ledger!$K$3:$K$100322,0)),"") | F59: =IFERROR(INDEX(Party_Ledger!$G$3:$G$100322,MATCH(ROWS($1:48),Party_Ledger!$K$3:$K$100322,0)),"") | G59: =IFERROR(INDEX(Party_Ledger!$H$3:$H$100322,MATCH(ROWS($1:48),Party_Ledger!$K$3:$K$100322,0)),"") | H59: =IF($A59="","",N($F59)-N($G59))
A60: =IFERROR(INDEX(Party_Ledger!$A$3:$A$100322, MATCH(ROWS($1:49), Party_Ledger!$K$3:$K$100322, 0)), "") | B60: =IF(A60="","",IF(ISNUMBER(A60),IFERROR(VLOOKUP(TEXT(A60,"yyyy/mm/dd"),BSAD,2,FALSE),""),IFERROR(VLOOKUP(A60,BSAD,2,FALSE),""))) | C60: =IFERROR(INDEX(Party_Ledger!$D$3:$D$100322,MATCH(ROWS($1:49),Party_Ledger!$K$3:$K$100322,0)),"") | D60: =IFERROR(INDEX(Party_Ledger!$E$3:$E$100322,MATCH(ROWS($1:49),Party_Ledger!$K$3:$K$100322,0)),"") | E60: =IFERROR(INDEX(Party_Ledger!$F$3:$F$100322,MATCH(ROWS($1:49),Party_Ledger!$K$3:$K$100322,0)),"") | F60: =IFERROR(INDEX(Party_Ledger!$G$3:$G$100322,MATCH(ROWS($1:49),Party_Ledger!$K$3:$K$100322,0)),"") | G60: =IFERROR(INDEX(Party_Ledger!$H$3:$H$100322,MATCH(ROWS($1:49),Party_Ledger!$K$3:$K$100322,0)),"") | H60: =IF($A60="","",N($F60)-N($G60))
A61: =IFERROR(INDEX(Party_Ledger!$A$3:$A$100322, MATCH(ROWS($1:50), Party_Ledger!$K$3:$K$100322, 0)), "") | B61: =IF(A61="","",IF(ISNUMBER(A61),IFERROR(VLOOKUP(TEXT(A61,"yyyy/mm/dd"),BSAD,2,FALSE),""),IFERROR(VLOOKUP(A61,BSAD,2,FALSE),""))) | C61: =IFERROR(INDEX(Party_Ledger!$D$3:$D$100322,MATCH(ROWS($1:50),Party_Ledger!$K$3:$K$100322,0)),"") | D61: =IFERROR(INDEX(Party_Ledger!$E$3:$E$100322,MATCH(ROWS($1:50),Party_Ledger!$K$3:$K$100322,0)),"") | E61: =IFERROR(INDEX(Party_Ledger!$F$3:$F$100322,MATCH(ROWS($1:50),Party_Ledger!$K$3:$K$100322,0)),"") | F61: =IFERROR(INDEX(Party_Ledger!$G$3:$G$100322,MATCH(ROWS($1:50),Party_Ledger!$K$3:$K$100322,0)),"") | G61: =IFERROR(INDEX(Party_Ledger!$H$3:$H$100322,MATCH(ROWS($1:50),Party_Ledger!$K$3:$K$100322,0)),"") | H61: =IF($A61="","",N($F61)-N($G61))
A62: =IFERROR(INDEX(Party_Ledger!$A$3:$A$100322, MATCH(ROWS($1:51), Party_Ledger!$K$3:$K$100322, 0)), "") | B62: =IF(A62="","",IF(ISNUMBER(A62),IFERROR(VLOOKUP(TEXT(A62,"yyyy/mm/dd"),BSAD,2,FALSE),""),IFERROR(VLOOKUP(A62,BSAD,2,FALSE),""))) | C62: =IFERROR(INDEX(Party_Ledger!$D$3:$D$100322,MATCH(ROWS($1:51),Party_Ledger!$K$3:$K$100322,0)),"") | D62: =IFERROR(INDEX(Party_Ledger!$E$3:$E$100322,MATCH(ROWS($1:51),Party_Ledger!$K$3:$K$100322,0)),"") | E62: =IFERROR(INDEX(Party_Ledger!$F$3:$F$100322,MATCH(ROWS($1:51),Party_Ledger!$K$3:$K$100322,0)),"") | F62: =IFERROR(INDEX(Party_Ledger!$G$3:$G$100322,MATCH(ROWS($1:51),Party_Ledger!$K$3:$K$100322,0)),"") | G62: =IFERROR(INDEX(Party_Ledger!$H$3:$H$100322,MATCH(ROWS($1:51),Party_Ledger!$K$3:$K$100322,0)),"") | H62: =IF($A62="","",N($F62)-N($G62))
A63: =IFERROR(INDEX(Party_Ledger!$A$3:$A$100322, MATCH(ROWS($1:52), Party_Ledger!$K$3:$K$100322, 0)), "") | B63: =IF(A63="","",IF(ISNUMBER(A63),IFERROR(VLOOKUP(TEXT(A63,"yyyy/mm/dd"),BSAD,2,FALSE),""),IFERROR(VLOOKUP(A63,BSAD,2,FALSE),""))) | C63: =IFERROR(INDEX(Party_Ledger!$D$3:$D$100322,MATCH(ROWS($1:52),Party_Ledger!$K$3:$K$100322,0)),"") | D63: =IFERROR(INDEX(Party_Ledger!$E$3:$E$100322,MATCH(ROWS($1:52),Party_Ledger!$K$3:$K$100322,0)),"") | E63: =IFERROR(INDEX(Party_Ledger!$F$3:$F$100322,MATCH(ROWS($1:52),Party_Ledger!$K$3:$K$100322,0)),"") | F63: =IFERROR(INDEX(Party_Ledger!$G$3:$G$100322,MATCH(ROWS($1:52),Party_Ledger!$K$3:$K$100322,0)),"") | G63: =IFERROR(INDEX(Party_Ledger!$H$3:$H$100322,MATCH(ROWS($1:52),Party_Ledger!$K$3:$K$100322,0)),"") | H63: =IF($A63="","",N($F63)-N($G63))
A64: =IFERROR(INDEX(Party_Ledger!$A$3:$A$100322, MATCH(ROWS($1:53), Party_Ledger!$K$3:$K$100322, 0)), "") | B64: =IF(A64="","",IF(ISNUMBER(A64),IFERROR(VLOOKUP(TEXT(A64,"yyyy/mm/dd"),BSAD,2,FALSE),""),IFERROR(VLOOKUP(A64,BSAD,2,FALSE),""))) | C64: =IFERROR(INDEX(Party_Ledger!$D$3:$D$100322,MATCH(ROWS($1:53),Party_Ledger!$K$3:$K$100322,0)),"") | D64: =IFERROR(INDEX(Party_Ledger!$E$3:$E$100322,MATCH(ROWS($1:53),Party_Ledger!$K$3:$K$100322,0)),"") | E64: =IFERROR(INDEX(Party_Ledger!$F$3:$F$100322,MATCH(ROWS($1:53),Party_Ledger!$K$3:$K$100322,0)),"") | F64: =IFERROR(INDEX(Party_Ledger!$G$3:$G$100322,MATCH(ROWS($1:53),Party_Ledger!$K$3:$K$100322,0)),"") | G64: =IFERROR(INDEX(Party_Ledger!$H$3:$H$100322,MATCH(ROWS($1:53),Party_Ledger!$K$3:$K$100322,0)),"") | H64: =IF($A64="","",N($F64)-N($G64))
A65: =IFERROR(INDEX(Party_Ledger!$A$3:$A$100322, MATCH(ROWS($1:54), Party_Ledger!$K$3:$K$100322, 0)), "") | B65: =IF(A65="","",IF(ISNUMBER(A65),IFERROR(VLOOKUP(TEXT(A65,"yyyy/mm/dd"),BSAD,2,FALSE),""),IFERROR(VLOOKUP(A65,BSAD,2,FALSE),""))) | C65: =IFERROR(INDEX(Party_Ledger!$D$3:$D$100322,MATCH(ROWS($1:54),Party_Ledger!$K$3:$K$100322,0)),"") | D65: =IFERROR(INDEX(Party_Ledger!$E$3:$E$100322,MATCH(ROWS($1:54),Party_Ledger!$K$3:$K$100322,0)),"") | E65: =IFERROR(INDEX(Party_Ledger!$F$3:$F$100322,MATCH(ROWS($1:54),Party_Ledger!$K$3:$K$100322,0)),"") | F65: =IFERROR(INDEX(Party_Ledger!$G$3:$G$100322,MATCH(ROWS($1:54),Party_Ledger!$K$3:$K$100322,0)),"") | G65: =IFERROR(INDEX(Party_Ledger!$H$3:$H$100322,MATCH(ROWS($1:54),Party_Ledger!$K$3:$K$100322,0)),"") | H65: =IF($A65="","",N($F65)-N($G65))
A66: =IFERROR(INDEX(Party_Ledger!$A$3:$A$100322, MATCH(ROWS($1:55), Party_Ledger!$K$3:$K$100322, 0)), "") | B66: =IF(A66="","",IF(ISNUMBER(A66),IFERROR(VLOOKUP(TEXT(A66,"yyyy/mm/dd"),BSAD,2,FALSE),""),IFERROR(VLOOKUP(A66,BSAD,2,FALSE),""))) | C66: =IFERROR(INDEX(Party_Ledger!$D$3:$D$100322,MATCH(ROWS($1:55),Party_Ledger!$K$3:$K$100322,0)),"") | D66: =IFERROR(INDEX(Party_Ledger!$E$3:$E$100322,MATCH(ROWS($1:55),Party_Ledger!$K$3:$K$100322,0)),"") | E66: =IFERROR(INDEX(Party_Ledger!$F$3:$F$100322,MATCH(ROWS($1:55),Party_Ledger!$K$3:$K$100322,0)),"") | F66: =IFERROR(INDEX(Party_Ledger!$G$3:$G$100322,MATCH(ROWS($1:55),Party_Ledger!$K$3:$K$100322,0)),"") | G66: =IFERROR(INDEX(Party_Ledger!$H$3:$H$100322,MATCH(ROWS($1:55),Party_Ledger!$K$3:$K$100322,0)),"") | H66: =IF($A66="","",N($F66)-N($G66))
A67: =IFERROR(INDEX(Party_Ledger!$A$3:$A$100322, MATCH(ROWS($1:56), Party_Ledger!$K$3:$K$100322, 0)), "") | B67: =IF(A67="","",IF(ISNUMBER(A67),IFERROR(VLOOKUP(TEXT(A67,"yyyy/mm/dd"),BSAD,2,FALSE),""),IFERROR(VLOOKUP(A67,BSAD,2,FALSE),""))) | C67: =IFERROR(INDEX(Party_Ledger!$D$3:$D$100322,MATCH(ROWS($1:56),Party_Ledger!$K$3:$K$100322,0)),"") | D67: =IFERROR(INDEX(Party_Ledger!$E$3:$E$100322,MATCH(ROWS($1:56),Party_Ledger!$K$3:$K$100322,0)),"") | E67: =IFERROR(INDEX(Party_Ledger!$F$3:$F$100322,MATCH(ROWS($1:56),Party_Ledger!$K$3:$K$100322,0)),"") | F67: =IFERROR(INDEX(Party_Ledger!$G$3:$G$100322,MATCH(ROWS($1:56),Party_Ledger!$K$3:$K$100322,0)),"") | G67: =IFERROR(INDEX(Party_Ledger!$H$3:$H$100322,MATCH(ROWS($1:56),Party_Ledger!$K$3:$K$100322,0)),"") | H67: =IF($A67="","",N($F67)-N($G67))
A68: =IFERROR(INDEX(Party_Ledger!$A$3:$A$100322, MATCH(ROWS($1:57), Party_Ledger!$K$3:$K$100322, 0)), "") | B68: =IF(A68="","",IF(ISNUMBER(A68),IFERROR(VLOOKUP(TEXT(A68,"yyyy/mm/dd"),BSAD,2,FALSE),""),IFERROR(VLOOKUP(A68,BSAD,2,FALSE),""))) | C68: =IFERROR(INDEX(Party_Ledger!$D$3:$D$100322,MATCH(ROWS($1:57),Party_Ledger!$K$3:$K$100322,0)),"") | D68: =IFERROR(INDEX(Party_Ledger!$E$3:$E$100322,MATCH(ROWS($1:57),Party_Ledger!$K$3:$K$100322,0)),"") | E68: =IFERROR(INDEX(Party_Ledger!$F$3:$F$100322,MATCH(ROWS($1:57),Party_Ledger!$K$3:$K$100322,0)),"") | F68: =IFERROR(INDEX(Party_Ledger!$G$3:$G$100322,MATCH(ROWS($1:57),Party_Ledger!$K$3:$K$100322,0)),"") | G68: =IFERROR(INDEX(Party_Ledger!$H$3:$H$100322,MATCH(ROWS($1:57),Party_Ledger!$K$3:$K$100322,0)),"") | H68: =IF($A68="","",N($F68)-N($G68))
A69: =IFERROR(INDEX(Party_Ledger!$A$3:$A$100322, MATCH(ROWS($1:58), Party_Ledger!$K$3:$K$100322, 0)), "") | B69: =IF(A69="","",IF(ISNUMBER(A69),IFERROR(VLOOKUP(TEXT(A69,"yyyy/mm/dd"),BSAD,2,FALSE),""),IFERROR(VLOOKUP(A69,BSAD,2,FALSE),""))) | C69: =IFERROR(INDEX(Party_Ledger!$D$3:$D$100322,MATCH(ROWS($1:58),Party_Ledger!$K$3:$K$100322,0)),"") | D69: =IFERROR(INDEX(Party_Ledger!$E$3:$E$100322,MATCH(ROWS($1:58),Party_Ledger!$K$3:$K$100322,0)),"") | E69: =IFERROR(INDEX(Party_Ledger!$F$3:$F$100322,MATCH(ROWS($1:58),Party_Ledger!$K$3:$K$100322,0)),"") | F69: =IFERROR(INDEX(Party_Ledger!$G$3:$G$100322,MATCH(ROWS($1:58),Party_Ledger!$K$3:$K$100322,0)),"") | G69: =IFERROR(INDEX(Party_Ledger!$H$3:$H$100322,MATCH(ROWS($1:58),Party_Ledger!$K$3:$K$100322,0)),"") | H69: =IF($A69="","",N($F69)-N($G69))
A70: =IFERROR(INDEX(Party_Ledger!$A$3:$A$100322, MATCH(ROWS($1:59), Party_Ledger!$K$3:$K$100322, 0)), "") | B70: =IF(A70="","",IF(ISNUMBER(A70),IFERROR(VLOOKUP(TEXT(A70,"yyyy/mm/dd"),BSAD,2,FALSE),""),IFERROR(VLOOKUP(A70,BSAD,2,FALSE),""))) | C70: =IFERROR(INDEX(Party_Ledger!$D$3:$D$100322,MATCH(ROWS($1:59),Party_Ledger!$K$3:$K$100322,0)),"") | D70: =IFERROR(INDEX(Party_Ledger!$E$3:$E$100322,MATCH(ROWS($1:59),Party_Ledger!$K$3:$K$100322,0)),"") | E70: =IFERROR(INDEX(Party_Ledger!$F$3:$F$100322,MATCH(ROWS($1:59),Party_Ledger!$K$3:$K$100322,0)),"") | F70: =IFERROR(INDEX(Party_Ledger!$G$3:$G$100322,MATCH(ROWS($1:59),Party_Ledger!$K$3:$K$100322,0)),"") | G70: =IFERROR(INDEX(Party_Ledger!$H$3:$H$100322,MATCH(ROWS($1:59),Party_Ledger!$K$3:$K$100322,0)),"") | H70: =IF($A70="","",N($F70)-N($G70))
A71: =IFERROR(INDEX(Party_Ledger!$A$3:$A$100322, MATCH(ROWS($1:60), Party_Ledger!$K$3:$K$100322, 0)), "") | B71: =IF(A71="","",IF(ISNUMBER(A71),IFERROR(VLOOKUP(TEXT(A71,"yyyy/mm/dd"),BSAD,2,FALSE),""),IFERROR(VLOOKUP(A71,BSAD,2,FALSE),""))) | C71: =IFERROR(INDEX(Party_Ledger!$D$3:$D$100322,MATCH(ROWS($1:60),Party_Ledger!$K$3:$K$100322,0)),"") | D71: =IFERROR(INDEX(Party_Ledger!$E$3:$E$100322,MATCH(ROWS($1:60),Party_Ledger!$K$3:$K$100322,0)),"") | E71: =IFERROR(INDEX(Party_Ledger!$F$3:$F$100322,MATCH(ROWS($1:60),Party_Ledger!$K$3:$K$100322,0)),"") | F71: =IFERROR(INDEX(Party_Ledger!$G$3:$G$100322,MATCH(ROWS($1:60),Party_Ledger!$K$3:$K$100322,0)),"") | G71: =IFERROR(INDEX(Party_Ledger!$H$3:$H$100322,MATCH(ROWS($1:60),Party_Ledger!$K$3:$K$100322,0)),"") | H71: =IF($A71="","",N($F71)-N($G71))
A72: =IFERROR(INDEX(Party_Ledger!$A$3:$A$100322, MATCH(ROWS($1:61), Party_Ledger!$K$3:$K$100322, 0)), "") | B72: =IF(A72="","",IF(ISNUMBER(A72),IFERROR(VLOOKUP(TEXT(A72,"yyyy/mm/dd"),BSAD,2,FALSE),""),IFERROR(VLOOKUP(A72,BSAD,2,FALSE),""))) | C72: =IFERROR(INDEX(Party_Ledger!$D$3:$D$100322,MATCH(ROWS($1:61),Party_Ledger!$K$3:$K$100322,0)),"") | D72: =IFERROR(INDEX(Party_Ledger!$E$3:$E$100322,MATCH(ROWS($1:61),Party_Ledger!$K$3:$K$100322,0)),"") | E72: =IFERROR(INDEX(Party_Ledger!$F$3:$F$100322,MATCH(ROWS($1:61),Party_Ledger!$K$3:$K$100322,0)),"") | F72: =IFERROR(INDEX(Party_Ledger!$G$3:$G$100322,MATCH(ROWS($1:61),Party_Ledger!$K$3:$K$100322,0)),"") | G72: =IFERROR(INDEX(Party_Ledger!$H$3:$H$100322,MATCH(ROWS($1:61),Party_Ledger!$K$3:$K$100322,0)),"") | H72: =IF($A72="","",N($F72)-N($G72))
A73: =IFERROR(INDEX(Party_Ledger!$A$3:$A$100322, MATCH(ROWS($1:62), Party_Ledger!$K$3:$K$100322, 0)), "") | B73: =IF(A73="","",IF(ISNUMBER(A73),IFERROR(VLOOKUP(TEXT(A73,"yyyy/mm/dd"),BSAD,2,FALSE),""),IFERROR(VLOOKUP(A73,BSAD,2,FALSE),""))) | C73: =IFERROR(INDEX(Party_Ledger!$D$3:$D$100322,MATCH(ROWS($1:62),Party_Ledger!$K$3:$K$100322,0)),"") | D73: =IFERROR(INDEX(Party_Ledger!$E$3:$E$100322,MATCH(ROWS($1:62),Party_Ledger!$K$3:$K$100322,0)),"") | E73: =IFERROR(INDEX(Party_Ledger!$F$3:$F$100322,MATCH(ROWS($1:62),Party_Ledger!$K$3:$K$100322,0)),"") | F73: =IFERROR(INDEX(Party_Ledger!$G$3:$G$100322,MATCH(ROWS($1:62),Party_Ledger!$K$3:$K$100322,0)),"") | G73: =IFERROR(INDEX(Party_Ledger!$H$3:$H$100322,MATCH(ROWS($1:62),Party_Ledger!$K$3:$K$100322,0)),"") | H73: =IF($A73="","",N($F73)-N($G73))
A74: =IFERROR(INDEX(Party_Ledger!$A$3:$A$100322, MATCH(ROWS($1:63), Party_Ledger!$K$3:$K$100322, 0)), "") | B74: =IF(A74="","",IF(ISNUMBER(A74),IFERROR(VLOOKUP(TEXT(A74,"yyyy/mm/dd"),BSAD,2,FALSE),""),IFERROR(VLOOKUP(A74,BSAD,2,FALSE),""))) | C74: =IFERROR(INDEX(Party_Ledger!$D$3:$D$100322,MATCH(ROWS($1:63),Party_Ledger!$K$3:$K$100322,0)),"") | D74: =IFERROR(INDEX(Party_Ledger!$E$3:$E$100322,MATCH(ROWS($1:63),Party_Ledger!$K$3:$K$100322,0)),"") | E74: =IFERROR(INDEX(Party_Ledger!$F$3:$F$100322,MATCH(ROWS($1:63),Party_Ledger!$K$3:$K$100322,0)),"") | F74: =IFERROR(INDEX(Party_Ledger!$G$3:$G$100322,MATCH(ROWS($1:63),Party_Ledger!$K$3:$K$100322,0)),"") | G74: =IFERROR(INDEX(Party_Ledger!$H$3:$H$100322,MATCH(ROWS($1:63),Party_Ledger!$K$3:$K$100322,0)),"") | H74: =IF($A74="","",N($F74)-N($G74))
A75: =IFERROR(INDEX(Party_Ledger!$A$3:$A$100322, MATCH(ROWS($1:64), Party_Ledger!$K$3:$K$100322, 0)), "") | B75: =IF(A75="","",IF(ISNUMBER(A75),IFERROR(VLOOKUP(TEXT(A75,"yyyy/mm/dd"),BSAD,2,FALSE),""),IFERROR(VLOOKUP(A75,BSAD,2,FALSE),""))) | C75: =IFERROR(INDEX(Party_Ledger!$D$3:$D$100322,MATCH(ROWS($1:64),Party_Ledger!$K$3:$K$100322,0)),"") | D75: =IFERROR(INDEX(Party_Ledger!$E$3:$E$100322,MATCH(ROWS($1:64),Party_Ledger!$K$3:$K$100322,0)),"") | E75: =IFERROR(INDEX(Party_Ledger!$F$3:$F$100322,MATCH(ROWS($1:64),Party_Ledger!$K$3:$K$100322,0)),"") | F75: =IFERROR(INDEX(Party_Ledger!$G$3:$G$100322,MATCH(ROWS($1:64),Party_Ledger!$K$3:$K$100322,0)),"") | G75: =IFERROR(INDEX(Party_Ledger!$H$3:$H$100322,MATCH(ROWS($1:64),Party_Ledger!$K$3:$K$100322,0)),"") | H75: =IF($A75="","",N($F75)-N($G75))
A76: =IFERROR(INDEX(Party_Ledger!$A$3:$A$100322, MATCH(ROWS($1:65), Party_Ledger!$K$3:$K$100322, 0)), "") | B76: =IF(A76="","",IF(ISNUMBER(A76),IFERROR(VLOOKUP(TEXT(A76,"yyyy/mm/dd"),BSAD,2,FALSE),""),IFERROR(VLOOKUP(A76,BSAD,2,FALSE),""))) | C76: =IFERROR(INDEX(Party_Ledger!$D$3:$D$100322,MATCH(ROWS($1:65),Party_Ledger!$K$3:$K$100322,0)),"") | D76: =IFERROR(INDEX(Party_Ledger!$E$3:$E$100322,MATCH(ROWS($1:65),Party_Ledger!$K$3:$K$100322,0)),"") | E76: =IFERROR(INDEX(Party_Ledger!$F$3:$F$100322,MATCH(ROWS($1:65),Party_Ledger!$K$3:$K$100322,0)),"") | F76: =IFERROR(INDEX(Party_Ledger!$G$3:$G$100322,MATCH(ROWS($1:65),Party_Ledger!$K$3:$K$100322,0)),"") | G76: =IFERROR(INDEX(Party_Ledger!$H$3:$H$100322,MATCH(ROWS($1:65),Party_Ledger!$K$3:$K$100322,0)),"") | H76: =IF($A76="","",N($F76)-N($G76))
A77: =IFERROR(INDEX(Party_Ledger!$A$3:$A$100322, MATCH(ROWS($1:66), Party_Ledger!$K$3:$K$100322, 0)), "") | B77: =IF(A77="","",IF(ISNUMBER(A77),IFERROR(VLOOKUP(TEXT(A77,"yyyy/mm/dd"),BSAD,2,FALSE),""),IFERROR(VLOOKUP(A77,BSAD,2,FALSE),""))) | C77: =IFERROR(INDEX(Party_Ledger!$D$3:$D$100322,MATCH(ROWS($1:66),Party_Ledger!$K$3:$K$100322,0)),"") | D77: =IFERROR(INDEX(Party_Ledger!$E$3:$E$100322,MATCH(ROWS($1:66),Party_Ledger!$K$3:$K$100322,0)),"") | E77: =IFERROR(INDEX(Party_Ledger!$F$3:$F$100322,MATCH(ROWS($1:66),Party_Ledger!$K$3:$K$100322,0)),"") | F77: =IFERROR(INDEX(Party_Ledger!$G$3:$G$100322,MATCH(ROWS($1:66),Party_Ledger!$K$3:$K$100322,0)),"") | G77: =IFERROR(INDEX(Party_Ledger!$H$3:$H$100322,MATCH(ROWS($1:66),Party_Ledger!$K$3:$K$100322,0)),"") | H77: =IF($A77="","",N($F77)-N($G77))
A78: =IFERROR(INDEX(Party_Ledger!$A$3:$A$100322, MATCH(ROWS($1:67), Party_Ledger!$K$3:$K$100322, 0)), "") | B78: =IF(A78="","",IF(ISNUMBER(A78),IFERROR(VLOOKUP(TEXT(A78,"yyyy/mm/dd"),BSAD,2,FALSE),""),IFERROR(VLOOKUP(A78,BSAD,2,FALSE),""))) | C78: =IFERROR(INDEX(Party_Ledger!$D$3:$D$100322,MATCH(ROWS($1:67),Party_Ledger!$K$3:$K$100322,0)),"") | D78: =IFERROR(INDEX(Party_Ledger!$E$3:$E$100322,MATCH(ROWS($1:67),Party_Ledger!$K$3:$K$100322,0)),"") | E78: =IFERROR(INDEX(Party_Ledger!$F$3:$F$100322,MATCH(ROWS($1:67),Party_Ledger!$K$3:$K$100322,0)),"") | F78: =IFERROR(INDEX(Party_Ledger!$G$3:$G$100322,MATCH(ROWS($1:67),Party_Ledger!$K$3:$K$100322,0)),"") | G78: =IFERROR(INDEX(Party_Ledger!$H$3:$H$100322,MATCH(ROWS($1:67),Party_Ledger!$K$3:$K$100322,0)),"") | H78: =IF($A78="","",N($F78)-N($G78))
A79: =IFERROR(INDEX(Party_Ledger!$A$3:$A$100322, MATCH(ROWS($1:68), Party_Ledger!$K$3:$K$100322, 0)), "") | B79: =IF(A79="","",IF(ISNUMBER(A79),IFERROR(VLOOKUP(TEXT(A79,"yyyy/mm/dd"),BSAD,2,FALSE),""),IFERROR(VLOOKUP(A79,BSAD,2,FALSE),""))) | C79: =IFERROR(INDEX(Party_Ledger!$D$3:$D$100322,MATCH(ROWS($1:68),Party_Ledger!$K$3:$K$100322,0)),"") | D79: =IFERROR(INDEX(Party_Ledger!$E$3:$E$100322,MATCH(ROWS($1:68),Party_Ledger!$K$3:$K$100322,0)),"") | E79: =IFERROR(INDEX(Party_Ledger!$F$3:$F$100322,MATCH(ROWS($1:68),Party_Ledger!$K$3:$K$100322,0)),"") | F79: =IFERROR(INDEX(Party_Ledger!$G$3:$G$100322,MATCH(ROWS($1:68),Party_Ledger!$K$3:$K$100322,0)),"") | G79: =IFERROR(INDEX(Party_Ledger!$H$3:$H$100322,MATCH(ROWS($1:68),Party_Ledger!$K$3:$K$100322,0)),"") | H79: =IF($A79="","",N($F79)-N($G79))
A80: =IFERROR(INDEX(Party_Ledger!$A$3:$A$100322, MATCH(ROWS($1:69), Party_Ledger!$K$3:$K$100322, 0)), "") | B80: =IF(A80="","",IF(ISNUMBER(A80),IFERROR(VLOOKUP(TEXT(A80,"yyyy/mm/dd"),BSAD,2,FALSE),""),IFERROR(VLOOKUP(A80,BSAD,2,FALSE),""))) | C80: =IFERROR(INDEX(Party_Ledger!$D$3:$D$100322,MATCH(ROWS($1:69),Party_Ledger!$K$3:$K$100322,0)),"") | D80: =IFERROR(INDEX(Party_Ledger!$E$3:$E$100322,MATCH(ROWS($1:69),Party_Ledger!$K$3:$K$100322,0)),"") | E80: =IFERROR(INDEX(Party_Ledger!$F$3:$F$100322,MATCH(ROWS($1:69),Party_Ledger!$K$3:$K$100322,0)),"") | F80: =IFERROR(INDEX(Party_Ledger!$G$3:$G$100322,MATCH(ROWS($1:69),Party_Ledger!$K$3:$K$100322,0)),"") | G80: =IFERROR(INDEX(Party_Ledger!$H$3:$H$100322,MATCH(ROWS($1:69),Party_Ledger!$K$3:$K$100322,0)),"") | H80: =IF($A80="","",N($F80)-N($G80))
A81: =IFERROR(INDEX(Party_Ledger!$A$3:$A$100322, MATCH(ROWS($1:70), Party_Ledger!$K$3:$K$100322, 0)), "") | B81: =IF(A81="","",IF(ISNUMBER(A81),IFERROR(VLOOKUP(TEXT(A81,"yyyy/mm/dd"),BSAD,2,FALSE),""),IFERROR(VLOOKUP(A81,BSAD,2,FALSE),""))) | C81: =IFERROR(INDEX(Party_Ledger!$D$3:$D$100322,MATCH(ROWS($1:70),Party_Ledger!$K$3:$K$100322,0)),"") | D81: =IFERROR(INDEX(Party_Ledger!$E$3:$E$100322,MATCH(ROWS($1:70),Party_Ledger!$K$3:$K$100322,0)),"") | E81: =IFERROR(INDEX(Party_Ledger!$F$3:$F$100322,MATCH(ROWS($1:70),Party_Ledger!$K$3:$K$100322,0)),"") | F81: =IFERROR(INDEX(Party_Ledger!$G$3:$G$100322,MATCH(ROWS($1:70),Party_Ledger!$K$3:$K$100322,0)),"") | G81: =IFERROR(INDEX(Party_Ledger!$H$3:$H$100322,MATCH(ROWS($1:70),Party_Ledger!$K$3:$K$100322,0)),"") | H81: =IF($A81="","",N($F81)-N($G81))
A82: =IFERROR(INDEX(Party_Ledger!$A$3:$A$100322, MATCH(ROWS($1:71), Party_Ledger!$K$3:$K$100322, 0)), "") | B82: =IF(A82="","",IF(ISNUMBER(A82),IFERROR(VLOOKUP(TEXT(A82,"yyyy/mm/dd"),BSAD,2,FALSE),""),IFERROR(VLOOKUP(A82,BSAD,2,FALSE),""))) | C82: =IFERROR(INDEX(Party_Ledger!$D$3:$D$100322,MATCH(ROWS($1:71),Party_Ledger!$K$3:$K$100322,0)),"") | D82: =IFERROR(INDEX(Party_Ledger!$E$3:$E$100322,MATCH(ROWS($1:71),Party_Ledger!$K$3:$K$100322,0)),"") | E82: =IFERROR(INDEX(Party_Ledger!$F$3:$F$100322,MATCH(ROWS($1:71),Party_Ledger!$K$3:$K$100322,0)),"") | F82: =IFERROR(INDEX(Party_Ledger!$G$3:$G$100322,MATCH(ROWS($1:71),Party_Ledger!$K$3:$K$100322,0)),"") | G82: =IFERROR(INDEX(Party_Ledger!$H$3:$H$100322,MATCH(ROWS($1:71),Party_Ledger!$K$3:$K$100322,0)),"") | H82: =IF($A82="","",N($F82)-N($G82))
A83: =IFERROR(INDEX(Party_Ledger!$A$3:$A$100322, MATCH(ROWS($1:72), Party_Ledger!$K$3:$K$100322, 0)), "") | B83: =IF(A83="","",IF(ISNUMBER(A83),IFERROR(VLOOKUP(TEXT(A83,"yyyy/mm/dd"),BSAD,2,FALSE),""),IFERROR(VLOOKUP(A83,BSAD,2,FALSE),""))) | C83: =IFERROR(INDEX(Party_Ledger!$D$3:$D$100322,MATCH(ROWS($1:72),Party_Ledger!$K$3:$K$100322,0)),"") | D83: =IFERROR(INDEX(Party_Ledger!$E$3:$E$100322,MATCH(ROWS($1:72),Party_Ledger!$K$3:$K$100322,0)),"") | E83: =IFERROR(INDEX(Party_Ledger!$F$3:$F$100322,MATCH(ROWS($1:72),Party_Ledger!$K$3:$K$100322,0)),"") | F83: =IFERROR(INDEX(Party_Ledger!$G$3:$G$100322,MATCH(ROWS($1:72),Party_Ledger!$K$3:$K$100322,0)),"") | G83: =IFERROR(INDEX(Party_Ledger!$H$3:$H$100322,MATCH(ROWS($1:72),Party_Ledger!$K$3:$K$100322,0)),"") | H83: =IF($A83="","",N($F83)-N($G83))
A84: =IFERROR(INDEX(Party_Ledger!$A$3:$A$100322, MATCH(ROWS($1:73), Party_Ledger!$K$3:$K$100322, 0)), "") | B84: =IF(A84="","",IF(ISNUMBER(A84),IFERROR(VLOOKUP(TEXT(A84,"yyyy/mm/dd"),BSAD,2,FALSE),""),IFERROR(VLOOKUP(A84,BSAD,2,FALSE),""))) | C84: =IFERROR(INDEX(Party_Ledger!$D$3:$D$100322,MATCH(ROWS($1:73),Party_Ledger!$K$3:$K$100322,0)),"") | D84: =IFERROR(INDEX(Party_Ledger!$E$3:$E$100322,MATCH(ROWS($1:73),Party_Ledger!$K$3:$K$100322,0)),"") | E84: =IFERROR(INDEX(Party_Ledger!$F$3:$F$100322,MATCH(ROWS($1:73),Party_Ledger!$K$3:$K$100322,0)),"") | F84: =IFERROR(INDEX(Party_Ledger!$G$3:$G$100322,MATCH(ROWS($1:73),Party_Ledger!$K$3:$K$100322,0)),"") | G84: =IFERROR(INDEX(Party_Ledger!$H$3:$H$100322,MATCH(ROWS($1:73),Party_Ledger!$K$3:$K$100322,0)),"") | H84: =IF($A84="","",N($F84)-N($G84))
A85: =IFERROR(INDEX(Party_Ledger!$A$3:$A$100322, MATCH(ROWS($1:74), Party_Ledger!$K$3:$K$100322, 0)), "") | B85: =IF(A85="","",IF(ISNUMBER(A85),IFERROR(VLOOKUP(TEXT(A85,"yyyy/mm/dd"),BSAD,2,FALSE),""),IFERROR(VLOOKUP(A85,BSAD,2,FALSE),""))) | C85: =IFERROR(INDEX(Party_Ledger!$D$3:$D$100322,MATCH(ROWS($1:74),Party_Ledger!$K$3:$K$100322,0)),"") | D85: =IFERROR(INDEX(Party_Ledger!$E$3:$E$100322,MATCH(ROWS($1:74),Party_Ledger!$K$3:$K$100322,0)),"") | E85: =IFERROR(INDEX(Party_Ledger!$F$3:$F$100322,MATCH(ROWS($1:74),Party_Ledger!$K$3:$K$100322,0)),"") | F85: =IFERROR(INDEX(Party_Ledger!$G$3:$G$100322,MATCH(ROWS($1:74),Party_Ledger!$K$3:$K$100322,0)),"") | G85: =IFERROR(INDEX(Party_Ledger!$H$3:$H$100322,MATCH(ROWS($1:74),Party_Ledger!$K$3:$K$100322,0)),"") | H85: =IF($A85="","",N($F85)-N($G85))
A86: =IFERROR(INDEX(Party_Ledger!$A$3:$A$100322, MATCH(ROWS($1:75), Party_Ledger!$K$3:$K$100322, 0)), "") | B86: =IF(A86="","",IF(ISNUMBER(A86),IFERROR(VLOOKUP(TEXT(A86,"yyyy/mm/dd"),BSAD,2,FALSE),""),IFERROR(VLOOKUP(A86,BSAD,2,FALSE),""))) | C86: =IFERROR(INDEX(Party_Ledger!$D$3:$D$100322,MATCH(ROWS($1:75),Party_Ledger!$K$3:$K$100322,0)),"") | D86: =IFERROR(INDEX(Party_Ledger!$E$3:$E$100322,MATCH(ROWS($1:75),Party_Ledger!$K$3:$K$100322,0)),"") | E86: =IFERROR(INDEX(Party_Ledger!$F$3:$F$100322,MATCH(ROWS($1:75),Party_Ledger!$K$3:$K$100322,0)),"") | F86: =IFERROR(INDEX(Party_Ledger!$G$3:$G$100322,MATCH(ROWS($1:75),Party_Ledger!$K$3:$K$100322,0)),"") | G86: =IFERROR(INDEX(Party_Ledger!$H$3:$H$100322,MATCH(ROWS($1:75),Party_Ledger!$K$3:$K$100322,0)),"") | H86: =IF($A86="","",N($F86)-N($G86))
A87: =IFERROR(INDEX(Party_Ledger!$A$3:$A$100322, MATCH(ROWS($1:76), Party_Ledger!$K$3:$K$100322, 0)), "") | B87: =IF(A87="","",IF(ISNUMBER(A87),IFERROR(VLOOKUP(TEXT(A87,"yyyy/mm/dd"),BSAD,2,FALSE),""),IFERROR(VLOOKUP(A87,BSAD,2,FALSE),""))) | C87: =IFERROR(INDEX(Party_Ledger!$D$3:$D$100322,MATCH(ROWS($1:76),Party_Ledger!$K$3:$K$100322,0)),"") | D87: =IFERROR(INDEX(Party_Ledger!$E$3:$E$100322,MATCH(ROWS($1:76),Party_Ledger!$K$3:$K$100322,0)),"") | E87: =IFERROR(INDEX(Party_Ledger!$F$3:$F$100322,MATCH(ROWS($1:76),Party_Ledger!$K$3:$K$100322,0)),"") | F87: =IFERROR(INDEX(Party_Ledger!$G$3:$G$100322,MATCH(ROWS($1:76),Party_Ledger!$K$3:$K$100322,0)),"") | G87: =IFERROR(INDEX(Party_Ledger!$H$3:$H$100322,MATCH(ROWS($1:76),Party_Ledger!$K$3:$K$100322,0)),"") | H87: =IF($A87="","",N($F87)-N($G87))
A88: =IFERROR(INDEX(Party_Ledger!$A$3:$A$100322, MATCH(ROWS($1:77), Party_Ledger!$K$3:$K$100322, 0)), "") | B88: =IF(A88="","",IF(ISNUMBER(A88),IFERROR(VLOOKUP(TEXT(A88,"yyyy/mm/dd"),BSAD,2,FALSE),""),IFERROR(VLOOKUP(A88,BSAD,2,FALSE),""))) | C88: =IFERROR(INDEX(Party_Ledger!$D$3:$D$100322,MATCH(ROWS($1:77),Party_Ledger!$K$3:$K$100322,0)),"") | D88: =IFERROR(INDEX(Party_Ledger!$E$3:$E$100322,MATCH(ROWS($1:77),Party_Ledger!$K$3:$K$100322,0)),"") | E88: =IFERROR(INDEX(Party_Ledger!$F$3:$F$100322,MATCH(ROWS($1:77),Party_Ledger!$K$3:$K$100322,0)),"") | F88: =IFERROR(INDEX(Party_Ledger!$G$3:$G$100322,MATCH(ROWS($1:77),Party_Ledger!$K$3:$K$100322,0)),"") | G88: =IFERROR(INDEX(Party_Ledger!$H$3:$H$100322,MATCH(ROWS($1:77),Party_Ledger!$K$3:$K$100322,0)),"") | H88: =IF($A88="","",N($F88)-N($G88))
A89: =IFERROR(INDEX(Party_Ledger!$A$3:$A$100322, MATCH(ROWS($1:78), Party_Ledger!$K$3:$K$100322, 0)), "") | B89: =IF(A89="","",IF(ISNUMBER(A89),IFERROR(VLOOKUP(TEXT(A89,"yyyy/mm/dd"),BSAD,2,FALSE),""),IFERROR(VLOOKUP(A89,BSAD,2,FALSE),""))) | C89: =IFERROR(INDEX(Party_Ledger!$D$3:$D$100322,MATCH(ROWS($1:78),Party_Ledger!$K$3:$K$100322,0)),"") | D89: =IFERROR(INDEX(Party_Ledger!$E$3:$E$100322,MATCH(ROWS($1:78),Party_Ledger!$K$3:$K$100322,0)),"") | E89: =IFERROR(INDEX(Party_Ledger!$F$3:$F$100322,MATCH(ROWS($1:78),Party_Ledger!$K$3:$K$100322,0)),"") | F89: =IFERROR(INDEX(Party_Ledger!$G$3:$G$100322,MATCH(ROWS($1:78),Party_Ledger!$K$3:$K$100322,0)),"") | G89: =IFERROR(INDEX(Party_Ledger!$H$3:$H$100322,MATCH(ROWS($1:78),Party_Ledger!$K$3:$K$100322,0)),"") | H89: =IF($A89="","",N($F89)-N($G89))
A90: =IFERROR(INDEX(Party_Ledger!$A$3:$A$100322, MATCH(ROWS($1:79), Party_Ledger!$K$3:$K$100322, 0)), "") | B90: =IF(A90="","",IF(ISNUMBER(A90),IFERROR(VLOOKUP(TEXT(A90,"yyyy/mm/dd"),BSAD,2,FALSE),""),IFERROR(VLOOKUP(A90,BSAD,2,FALSE),""))) | C90: =IFERROR(INDEX(Party_Ledger!$D$3:$D$100322,MATCH(ROWS($1:79),Party_Ledger!$K$3:$K$100322,0)),"") | D90: =IFERROR(INDEX(Party_Ledger!$E$3:$E$100322,MATCH(ROWS($1:79),Party_Ledger!$K$3:$K$100322,0)),"") | E90: =IFERROR(INDEX(Party_Ledger!$F$3:$F$100322,MATCH(ROWS($1:79),Party_Ledger!$K$3:$K$100322,0)),"") | F90: =IFERROR(INDEX(Party_Ledger!$G$3:$G$100322,MATCH(ROWS($1:79),Party_Ledger!$K$3:$K$100322,0)),"") | G90: =IFERROR(INDEX(Party_Ledger!$H$3:$H$100322,MATCH(ROWS($1:79),Party_Ledger!$K$3:$K$100322,0)),"") | H90: =IF($A90="","",N($F90)-N($G90))
A91: =IFERROR(INDEX(Party_Ledger!$A$3:$A$100322, MATCH(ROWS($1:80), Party_Ledger!$K$3:$K$100322, 0)), "") | B91: =IF(A91="","",IF(ISNUMBER(A91),IFERROR(VLOOKUP(TEXT(A91,"yyyy/mm/dd"),BSAD,2,FALSE),""),IFERROR(VLOOKUP(A91,BSAD,2,FALSE),""))) | C91: =IFERROR(INDEX(Party_Ledger!$D$3:$D$100322,MATCH(ROWS($1:80),Party_Ledger!$K$3:$K$100322,0)),"") | D91: =IFERROR(INDEX(Party_Ledger!$E$3:$E$100322,MATCH(ROWS($1:80),Party_Ledger!$K$3:$K$100322,0)),"") | E91: =IFERROR(INDEX(Party_Ledger!$F$3:$F$100322,MATCH(ROWS($1:80),Party_Ledger!$K$3:$K$100322,0)),"") | F91: =IFERROR(INDEX(Party_Ledger!$G$3:$G$100322,MATCH(ROWS($1:80),Party_Ledger!$K$3:$K$100322,0)),"") | G91: =IFERROR(INDEX(Party_Ledger!$H$3:$H$100322,MATCH(ROWS($1:80),Party_Ledger!$K$3:$K$100322,0)),"") | H91: =IF($A91="","",N($F91)-N($G91))
A92: =IFERROR(INDEX(Party_Ledger!$A$3:$A$100322, MATCH(ROWS($1:81), Party_Ledger!$K$3:$K$100322, 0)), "") | B92: =IF(A92="","",IF(ISNUMBER(A92),IFERROR(VLOOKUP(TEXT(A92,"yyyy/mm/dd"),BSAD,2,FALSE),""),IFERROR(VLOOKUP(A92,BSAD,2,FALSE),""))) | C92: =IFERROR(INDEX(Party_Ledger!$D$3:$D$100322,MATCH(ROWS($1:81),Party_Ledger!$K$3:$K$100322,0)),"") | D92: =IFERROR(INDEX(Party_Ledger!$E$3:$E$100322,MATCH(ROWS($1:81),Party_Ledger!$K$3:$K$100322,0)),"") | E92: =IFERROR(INDEX(Party_Ledger!$F$3:$F$100322,MATCH(ROWS($1:81),Party_Ledger!$K$3:$K$100322,0)),"") | F92: =IFERROR(INDEX(Party_Ledger!$G$3:$G$100322,MATCH(ROWS($1:81),Party_Ledger!$K$3:$K$100322,0)),"") | G92: =IFERROR(INDEX(Party_Ledger!$H$3:$H$100322,MATCH(ROWS($1:81),Party_Ledger!$K$3:$K$100322,0)),"") | H92: =IF($A92="","",N($F92)-N($G92))
A93: =IFERROR(INDEX(Party_Ledger!$A$3:$A$100322, MATCH(ROWS($1:82), Party_Ledger!$K$3:$K$100322, 0)), "") | B93: =IF(A93="","",IF(ISNUMBER(A93),IFERROR(VLOOKUP(TEXT(A93,"yyyy/mm/dd"),BSAD,2,FALSE),""),IFERROR(VLOOKUP(A93,BSAD,2,FALSE),""))) | C93: =IFERROR(INDEX(Party_Ledger!$D$3:$D$100322,MATCH(ROWS($1:82),Party_Ledger!$K$3:$K$100322,0)),"") | D93: =IFERROR(INDEX(Party_Ledger!$E$3:$E$100322,MATCH(ROWS($1:82),Party_Ledger!$K$3:$K$100322,0)),"") | E93: =IFERROR(INDEX(Party_Ledger!$F$3:$F$100322,MATCH(ROWS($1:82),Party_Ledger!$K$3:$K$100322,0)),"") | F93: =IFERROR(INDEX(Party_Ledger!$G$3:$G$100322,MATCH(ROWS($1:82),Party_Ledger!$K$3:$K$100322,0)),"") | G93: =IFERROR(INDEX(Party_Ledger!$H$3:$H$100322,MATCH(ROWS($1:82),Party_Ledger!$K$3:$K$100322,0)),"") | H93: =IF($A93="","",N($F93)-N($G93))
A94: =IFERROR(INDEX(Party_Ledger!$A$3:$A$100322, MATCH(ROWS($1:83), Party_Ledger!$K$3:$K$100322, 0)), "") | B94: =IF(A94="","",IF(ISNUMBER(A94),IFERROR(VLOOKUP(TEXT(A94,"yyyy/mm/dd"),BSAD,2,FALSE),""),IFERROR(VLOOKUP(A94,BSAD,2,FALSE),""))) | C94: =IFERROR(INDEX(Party_Ledger!$D$3:$D$100322,MATCH(ROWS($1:83),Party_Ledger!$K$3:$K$100322,0)),"") | D94: =IFERROR(INDEX(Party_Ledger!$E$3:$E$100322,MATCH(ROWS($1:83),Party_Ledger!$K$3:$K$100322,0)),"") | E94: =IFERROR(INDEX(Party_Ledger!$F$3:$F$100322,MATCH(ROWS($1:83),Party_Ledger!$K$3:$K$100322,0)),"") | F94: =IFERROR(INDEX(Party_Ledger!$G$3:$G$100322,MATCH(ROWS($1:83),Party_Ledger!$K$3:$K$100322,0)),"") | G94: =IFERROR(INDEX(Party_Ledger!$H$3:$H$100322,MATCH(ROWS($1:83),Party_Ledger!$K$3:$K$100322,0)),"") | H94: =IF($A94="","",N($F94)-N($G94))
A95: =IFERROR(INDEX(Party_Ledger!$A$3:$A$100322, MATCH(ROWS($1:84), Party_Ledger!$K$3:$K$100322, 0)), "") | B95: =IF(A95="","",IF(ISNUMBER(A95),IFERROR(VLOOKUP(TEXT(A95,"yyyy/mm/dd"),BSAD,2,FALSE),""),IFERROR(VLOOKUP(A95,BSAD,2,FALSE),""))) | C95: =IFERROR(INDEX(Party_Ledger!$D$3:$D$100322,MATCH(ROWS($1:84),Party_Ledger!$K$3:$K$100322,0)),"") | D95: =IFERROR(INDEX(Party_Ledger!$E$3:$E$100322,MATCH(ROWS($1:84),Party_Ledger!$K$3:$K$100322,0)),"") | E95: =IFERROR(INDEX(Party_Ledger!$F$3:$F$100322,MATCH(ROWS($1:84),Party_Ledger!$K$3:$K$100322,0)),"") | F95: =IFERROR(INDEX(Party_Ledger!$G$3:$G$100322,MATCH(ROWS($1:84),Party_Ledger!$K$3:$K$100322,0)),"") | G95: =IFERROR(INDEX(Party_Ledger!$H$3:$H$100322,MATCH(ROWS($1:84),Party_Ledger!$K$3:$K$100322,0)),"") | H95: =IF($A95="","",N($F95)-N($G95))
A96: =IFERROR(INDEX(Party_Ledger!$A$3:$A$100322, MATCH(ROWS($1:85), Party_Ledger!$K$3:$K$100322, 0)), "") | B96: =IF(A96="","",IF(ISNUMBER(A96),IFERROR(VLOOKUP(TEXT(A96,"yyyy/mm/dd"),BSAD,2,FALSE),""),IFERROR(VLOOKUP(A96,BSAD,2,FALSE),""))) | C96: =IFERROR(INDEX(Party_Ledger!$D$3:$D$100322,MATCH(ROWS($1:85),Party_Ledger!$K$3:$K$100322,0)),"") | D96: =IFERROR(INDEX(Party_Ledger!$E$3:$E$100322,MATCH(ROWS($1:85),Party_Ledger!$K$3:$K$100322,0)),"") | E96: =IFERROR(INDEX(Party_Ledger!$F$3:$F$100322,MATCH(ROWS($1:85),Party_Ledger!$K$3:$K$100322,0)),"") | F96: =IFERROR(INDEX(Party_Ledger!$G$3:$G$100322,MATCH(ROWS($1:85),Party_Ledger!$K$3:$K$100322,0)),"") | G96: =IFERROR(INDEX(Party_Ledger!$H$3:$H$100322,MATCH(ROWS($1:85),Party_Ledger!$K$3:$K$100322,0)),"") | H96: =IF($A96="","",N($F96)-N($G96))
A97: =IFERROR(INDEX(Party_Ledger!$A$3:$A$100322, MATCH(ROWS($1:86), Party_Ledger!$K$3:$K$100322, 0)), "") | B97: =IF(A97="","",IF(ISNUMBER(A97),IFERROR(VLOOKUP(TEXT(A97,"yyyy/mm/dd"),BSAD,2,FALSE),""),IFERROR(VLOOKUP(A97,BSAD,2,FALSE),""))) | C97: =IFERROR(INDEX(Party_Ledger!$D$3:$D$100322,MATCH(ROWS($1:86),Party_Ledger!$K$3:$K$100322,0)),"") | D97: =IFERROR(INDEX(Party_Ledger!$E$3:$E$100322,MATCH(ROWS($1:86),Party_Ledger!$K$3:$K$100322,0)),"") | E97: =IFERROR(INDEX(Party_Ledger!$F$3:$F$100322,MATCH(ROWS($1:86),Party_Ledger!$K$3:$K$100322,0)),"") | F97: =IFERROR(INDEX(Party_Ledger!$G$3:$G$100322,MATCH(ROWS($1:86),Party_Ledger!$K$3:$K$100322,0)),"") | G97: =IFERROR(INDEX(Party_Ledger!$H$3:$H$100322,MATCH(ROWS($1:86),Party_Ledger!$K$3:$K$100322,0)),"") | H97: =IF($A97="","",N($F97)-N($G97))
A98: =IFERROR(INDEX(Party_Ledger!$A$3:$A$100322, MATCH(ROWS($1:87), Party_Ledger!$K$3:$K$100322, 0)), "") | B98: =IF(A98="","",IF(ISNUMBER(A98),IFERROR(VLOOKUP(TEXT(A98,"yyyy/mm/dd"),BSAD,2,FALSE),""),IFERROR(VLOOKUP(A98,BSAD,2,FALSE),""))) | C98: =IFERROR(INDEX(Party_Ledger!$D$3:$D$100322,MATCH(ROWS($1:87),Party_Ledger!$K$3:$K$100322,0)),"") | D98: =IFERROR(INDEX(Party_Ledger!$E$3:$E$100322,MATCH(ROWS($1:87),Party_Ledger!$K$3:$K$100322,0)),"") | E98: =IFERROR(INDEX(Party_Ledger!$F$3:$F$100322,MATCH(ROWS($1:87),Party_Ledger!$K$3:$K$100322,0)),"") | F98: =IFERROR(INDEX(Party_Ledger!$G$3:$G$100322,MATCH(ROWS($1:87),Party_Ledger!$K$3:$K$100322,0)),"") | G98: =IFERROR(INDEX(Party_Ledger!$H$3:$H$100322,MATCH(ROWS($1:87),Party_Ledger!$K$3:$K$100322,0)),"") | H98: =IF($A98="","",N($F98)-N($G98))
A99: =IFERROR(INDEX(Party_Ledger!$A$3:$A$100322, MATCH(ROWS($1:88), Party_Ledger!$K$3:$K$100322, 0)), "") | B99: =IF(A99="","",IF(ISNUMBER(A99),IFERROR(VLOOKUP(TEXT(A99,"yyyy/mm/dd"),BSAD,2,FALSE),""),IFERROR(VLOOKUP(A99,BSAD,2,FALSE),""))) | C99: =IFERROR(INDEX(Party_Ledger!$D$3:$D$100322,MATCH(ROWS($1:88),Party_Ledger!$K$3:$K$100322,0)),"") | D99: =IFERROR(INDEX(Party_Ledger!$E$3:$E$100322,MATCH(ROWS($1:88),Party_Ledger!$K$3:$K$100322,0)),"") | E99: =IFERROR(INDEX(Party_Ledger!$F$3:$F$100322,MATCH(ROWS($1:88),Party_Ledger!$K$3:$K$100322,0)),"") | F99: =IFERROR(INDEX(Party_Ledger!$G$3:$G$100322,MATCH(ROWS($1:88),Party_Ledger!$K$3:$K$100322,0)),"") | G99: =IFERROR(INDEX(Party_Ledger!$H$3:$H$100322,MATCH(ROWS($1:88),Party_Ledger!$K$3:$K$100322,0)),"") | H99: =IF($A99="","",N($F99)-N($G99))
A100: =IFERROR(INDEX(Party_Ledger!$A$3:$A$100322, MATCH(ROWS($1:89), Party_Ledger!$K$3:$K$100322, 0)), "") | B100: =IF(A100="","",IF(ISNUMBER(A100),IFERROR(VLOOKUP(TEXT(A100,"yyyy/mm/dd"),BSAD,2,FALSE),""),IFERROR(VLOOKUP(A100,BSAD,2,FALSE),""))) | C100: =IFERROR(INDEX(Party_Ledger!$D$3:$D$100322,MATCH(ROWS($1:89),Party_Ledger!$K$3:$K$100322,0)),"") | D100: =IFERROR(INDEX(Party_Ledger!$E$3:$E$100322,MATCH(ROWS($1:89),Party_Ledger!$K$3:$K$100322,0)),"") | E100: =IFERROR(INDEX(Party_Ledger!$F$3:$F$100322,MATCH(ROWS($1:89),Party_Ledger!$K$3:$K$100322,0)),"") | F100: =IFERROR(INDEX(Party_Ledger!$G$3:$G$100322,MATCH(ROWS($1:89),Party_Ledger!$K$3:$K$100322,0)),"") | G100: =IFERROR(INDEX(Party_Ledger!$H$3:$H$100322,MATCH(ROWS($1:89),Party_Ledger!$K$3:$K$100322,0)),"") | H100: =IF($A100="","",N($F100)-N($G100))
...

Sheet Party_Ledger
A1: =C7 -> CHHATRABHUMI STORE
A2: Date | B2: AD Date | C2: Party Name | D2: Txn Type | E2: Reference | F2: Description | G2: Debit | H2: Credit | I2: Balance | J2: Remarks | K2: MatchIdx
A3: =Sales_Entry!A3 -> 66915 | B3: =Sales_Entry!B3 -> 46202 | C3: =Sales_Entry!D3 -> NAWA DURGA -317 | D3: Sale | E3: =Sales_Entry!C3 -> OPN-1001 | F3: =Sales_Entry!E3 -> OPENING | G3: =N(Sales_Entry!J3) -> 81953 | H3: 0 | I3: =IF($C3="","",$G3-$H3) -> 81953 | K3: {=IF($C3="","",IF(AND($C3=Party_Statement!$C$5,$B3>=Party_Statement!$C$6,$B3<=Party_Statement!$E$6),SUMPRODUCT(($C$3:$C3=Party_Statement!$C$5)*($B$3:$B3>=Party_Statement!$C$6)*($B$3:$B3<=Party_Statement!$E$6)),""))}
A4: =Sales_Entry!A4 -> 66915 | B4: =Sales_Entry!B4 -> 46202 | C4: =Sales_Entry!D4 -> THE DARBAR PARTY PALACE | D4: Sale | E4: =Sales_Entry!C4 -> OPN-1002 | F4: =Sales_Entry!E4 -> OPENING | G4: =N(Sales_Entry!J4) -> 28322 | H4: 0 | I4: =IF($C4="","",$G4-$H4) -> 28322 | K4: {=IF($C4="","",IF(AND($C4=Party_Statement!$C$5,$B4>=Party_Statement!$C$6,$B4<=Party_Statement!$E$6),SUMPRODUCT(($C$3:$C4=Party_Statement!$C$5)*($B$3:$B4>=Party_Statement!$C$6)*($B$3:$B4<=Party_Statement!$E$6)),""))}
A5: =Sales_Entry!A5 -> 66915 | B5: =Sales_Entry!B5 -> 46202 | C5: =Sales_Entry!D5 -> SRIJANA DAIRY | D5: Sale | E5: =Sales_Entry!C5 -> OPN-1003 | F5: =Sales_Entry!E5 -> OPENING | G5: =N(Sales_Entry!J5) -> 6950 | H5: 0 | I5: =IF($C5="","",$G5-$H5) -> 6950 | K5: {=IF($C5="","",IF(AND($C5=Party_Statement!$C$5,$B5>=Party_Statement!$C$6,$B5<=Party_Statement!$E$6),SUMPRODUCT(($C$3:$C5=Party_Statement!$C$5)*($B$3:$B5>=Party_Statement!$C$6)*($B$3:$B5<=Party_Statement!$E$6)),""))}
A6: =Sales_Entry!A6 -> 66915 | B6: =Sales_Entry!B6 -> 46202 | C6: =Sales_Entry!D6 -> SOBHA BHATTARAI | D6: Sale | E6: =Sales_Entry!C6 -> OPN-1004 | F6: =Sales_Entry!E6 -> OPENING | G6: =N(Sales_Entry!J6) -> 3400 | H6: 0 | I6: =IF($C6="","",$G6-$H6) -> 3400 | K6: {=IF($C6="","",IF(AND($C6=Party_Statement!$C$5,$B6>=Party_Statement!$C$6,$B6<=Party_Statement!$E$6),SUMPRODUCT(($C$3:$C6=Party_Statement!$C$5)*($B$3:$B6>=Party_Statement!$C$6)*($B$3:$B6<=Party_Statement!$E$6)),""))}
A7: =Sales_Entry!A7 -> 66915 | B7: =Sales_Entry!B7 -> 46202 | C7: =Sales_Entry!D7 -> CHHATRABHUMI STORE | D7: Sale | E7: =Sales_Entry!C7 -> OPN-1005 | F7: =Sales_Entry!E7 -> OPENING | G7: =N(Sales_Entry!J7) -> 44495 | H7: 0 | I7: =IF($C7="","",$G7-$H7) -> 44495 | K7: {=IF($C7="","",IF(AND($C7=Party_Statement!$C$5,$B7>=Party_Statement!$C$6,$B7<=Party_Statement!$E$6),SUMPRODUCT(($C$3:$C7=Party_Statement!$C$5)*($B$3:$B7>=Party_Statement!$C$6)*($B$3:$B7<=Party_Statement!$E$6)),""))}
A8: =Sales_Entry!A8 -> 66915 | B8: =Sales_Entry!B8 -> 46202 | C8: =Sales_Entry!D8 -> AAMOSH KIRANA | D8: Sale | E8: =Sales_Entry!C8 -> OPN-1006 | F8: =Sales_Entry!E8 -> OPENING | G8: =N(Sales_Entry!J8) -> 208022 | H8: 0 | I8: =IF($C8="","",$G8-$H8) -> 208022 | K8: {=IF($C8="","",IF(AND($C8=Party_Statement!$C$5,$B8>=Party_Statement!$C$6,$B8<=Party_Statement!$E$6),SUMPRODUCT(($C$3:$C8=Party_Statement!$C$5)*($B$3:$B8>=Party_Statement!$C$6)*($B$3:$B8<=Party_Statement!$E$6)),""))}
A9: =Sales_Entry!A9 -> 66915 | B9: =Sales_Entry!B9 -> 46202 | C9: =Sales_Entry!D9 -> ORGANIC TARKALI | D9: Sale | E9: =Sales_Entry!C9 -> OPN-1007 | F9: =Sales_Entry!E9 -> OPENING | G9: =N(Sales_Entry!J9) -> 9310 | H9: 0 | I9: =IF($C9="","",$G9-$H9) -> 9310 | K9: {=IF($C9="","",IF(AND($C9=Party_Statement!$C$5,$B9>=Party_Statement!$C$6,$B9<=Party_Statement!$E$6),SUMPRODUCT(($C$3:$C9=Party_Statement!$C$5)*($B$3:$B9>=Party_Statement!$C$6)*($B$3:$B9<=Party_Statement!$E$6)),""))}
A10: =Sales_Entry!A10 -> 66915 | B10: =Sales_Entry!B10 -> 46202 | C10: =Sales_Entry!D10 -> SHARMA DAI | D10: Sale | E10: =Sales_Entry!C10 -> OPN-1008 | F10: =Sales_Entry!E10 -> OPENING | G10: =N(Sales_Entry!J10) -> 39602 | H10: 0 | I10: =IF($C10="","",$G10-$H10) -> 39602 | K10: {=IF($C10="","",IF(AND($C10=Party_Statement!$C$5,$B10>=Party_Statement!$C$6,$B10<=Party_Statement!$E$6),SUMPRODUCT(($C$3:$C10=Party_Statement!$C$5)*($B$3:$B10>=Party_Statement!$C$6)*($B$3:$B10<=Party_Statement!$E$6)),""))}
A11: =Sales_Entry!A11 -> 66915 | B11: =Sales_Entry!B11 -> 46202 | C11: =Sales_Entry!D11 -> GANGA NEUPANE | D11: Sale | E11: =Sales_Entry!C11 -> OPN-1009 | F11: =Sales_Entry!E11 -> OPENING | G11: =N(Sales_Entry!J11) -> 14507 | H11: 0 | I11: =IF($C11="","",$G11-$H11) -> 14507 | K11: {=IF($C11="","",IF(AND($C11=Party_Statement!$C$5,$B11>=Party_Statement!$C$6,$B11<=Party_Statement!$E$6),SUMPRODUCT(($C$3:$C11=Party_Statement!$C$5)*($B$3:$B11>=Party_Statement!$C$6)*($B$3:$B11<=Party_Statement!$E$6)),""))}
A12: =Sales_Entry!A12 -> 66915 | B12: =Sales_Entry!B12 -> 46202 | C12: =Sales_Entry!D12 -> GIRI KIRANA | D12: Sale | E12: =Sales_Entry!C12 -> OPN-1010 | F12: =Sales_Entry!E12 -> OPENING | G12: =N(Sales_Entry!J12) -> 2550 | H12: 0 | I12: =IF($C12="","",$G12-$H12) -> 2550 | K12: {=IF($C12="","",IF(AND($C12=Party_Statement!$C$5,$B12>=Party_Statement!$C$6,$B12<=Party_Statement!$E$6),SUMPRODUCT(($C$3:$C12=Party_Statement!$C$5)*($B$3:$B12>=Party_Statement!$C$6)*($B$3:$B12<=Party_Statement!$E$6)),""))}
A13: =Sales_Entry!A13 -> 66915 | B13: =Sales_Entry!B13 -> 46202 | C13: =Sales_Entry!D13 -> NAR BAHADUR RANA | D13: Sale | E13: =Sales_Entry!C13 -> OPN-1011 | F13: =Sales_Entry!E13 -> OPENING | G13: =N(Sales_Entry!J13) -> 8117.5 | H13: 0 | I13: =IF($C13="","",$G13-$H13) -> 8117.5 | K13: {=IF($C13="","",IF(AND($C13=Party_Statement!$C$5,$B13>=Party_Statement!$C$6,$B13<=Party_Statement!$E$6),SUMPRODUCT(($C$3:$C13=Party_Statement!$C$5)*($B$3:$B13>=Party_Statement!$C$6)*($B$3:$B13<=Party_Statement!$E$6)),""))}
A14: =Sales_Entry!A14 -> 66915 | B14: =Sales_Entry!B14 -> 46202 | C14: =Sales_Entry!D14 -> DIPAK NEPAL | D14: Sale | E14: =Sales_Entry!C14 -> OPN-1012 | F14: =Sales_Entry!E14 -> OPENING | G14: =N(Sales_Entry!J14) -> 2750 | H14: 0 | I14: =IF($C14="","",$G14-$H14) -> 2750 | K14: {=IF($C14="","",IF(AND($C14=Party_Statement!$C$5,$B14>=Party_Statement!$C$6,$B14<=Party_Statement!$E$6),SUMPRODUCT(($C$3:$C14=Party_Statement!$C$5)*($B$3:$B14>=Party_Statement!$C$6)*($B$3:$B14<=Party_Statement!$E$6)),""))}
... A1853: =Sales_Entry!A1853 -> 0 | B1853: =Sales_Entry!B1853 | C1853: =Sales_Entry!D1853 -> 0 | D1853: Sale | E1853: =Sales_Entry!C1853 -> 0 | F1853: =Sales_Entry!E1853 -> 0 | G1853: =N(Sales_Entry!J1853) -> 0 | H1853: 0 | I1853: =IF($C1853="","",$G1853-$H1853) -> 0 | K1853: {=IF($C1853="","",IF(AND($C1853=Party_Statement!$C$5,$B1853>=Party_Statement!$C$6,$B1853<=Party_Statement!$E$6),SUMPRODUCT(($C$3:$C1853=Party_Statement!$C$5)*($B$3:$B1853>=Party_Statement!$C$6)*($B$3:$B1853<=Party_Statement!$E$6)),""))}
K1854: {=IF($C1854="","",IF(AND($C1854=Party_Statement!$C$5,$B1854>=Party_Statement!$C$6,$B1854<=Party_Statement!$E$6),SUMPRODUCT(($C$3:$C1854=Party_Statement!$C$5)*($B$3:$B1854>=Party_Statement!$C$6)*($B$3:$B1854<=Party_Statement!$E$6)),""))}
K1855: {=IF($C1855="","",IF(AND($C1855=Party_Statement!$C$5,$B1855>=Party_Statement!$C$6,$B1855<=Party_Statement!$E$6),SUMPRODUCT(($C$3:$C1855=Party_Statement!$C$5)*($B$3:$B1855>=Party_Statement!$C$6)*($B$3:$B1855<=Party_Statement!$E$6)),""))}
A1856: # | B1856: # | C1856: # | D1856: # | E1856: # | F1856: # | G1856: # | H1856: # | I1856: # | J1856: # | K1856: {=IF($C1856="","",IF(AND($C1856=Party_Statement!$C$5,$B1856>=Party_Statement!$C$6,$B1856<=Party_Statement!$E$6),SUMPRODUCT(($C$3:$C1856=Party_Statement!$C$5)*($B$3:$B1856>=Party_Statement!$C$6)*($B$3:$B1856<=Party_Statement!$E$6)),""))}
K1857: {=IF($C1857="","",IF(AND($C1857=Party_Statement!$C$5,$B1857>=Party_Statement!$C$6,$B1857<=Party_Statement!$E$6),SUMPRODUCT(($C$3:$C1857=Party_Statement!$C$5)*($B$3:$B1857>=Party_Statement!$C$6)*($B$3:$B1857<=Party_Statement!$E$6)),""))}
A1858: =Purchase_Entry!A3 -> 2083/03/15 | B1858: =Purchase_Entry!B3 -> 46202 | C1858: =Purchase_Entry!D3 -> MUKTESHWOR ENTERPRISES | D1858: Purchase | E1858: =Purchase_Entry!C3 -> OPN2001 | F1858: =Purchase_Entry!F3 -> OPENING | G1858: 0 | H1858: =N(Purchase_Entry!P3) -> 69018 | I1858: =IF($C1858="","",IF($C1858=$C589,$I589+$G1858-$H1858,$G1858-$H1858)) -> -69018 | K1858: {=IF($C1858="","",IF(AND($C1858=Party_Statement!$C$5,$B1858>=Party_Statement!$C$6,$B1858<=Party_Statement!$E$6),SUMPRODUCT(($C$3:$C1858=Party_Statement!$C$5)*($B$3:$B1858>=Party_Statement!$C$6)*($B$3:$B1858<=Party_Statement!$E$6)),""))}
A1859: =Purchase_Entry!A4 -> 2083/03/32 | B1859: =Purchase_Entry!B4 -> 46219 | C1859: =Purchase_Entry!D4 -> MUKTESHWOR ENTERPRISES | D1859: Purchase | E1859: =Purchase_Entry!C4 -> BILL-0809 | F1859: =Purchase_Entry!F4 -> DISSEL | G1859: 0 | H1859: =N(Purchase_Entry!P4) -> 23295 | I1859: =IF($C1859="","",IF($C1859=$C590,$I590+$G1859-$H1859,$G1859-$H1859)) -> -23295 | K1859: {=IF($C1859="","",IF(AND($C1859=Party_Statement!$C$5,$B1859>=Party_Statement!$C$6,$B1859<=Party_Statement!$E$6),SUMPRODUCT(($C$3:$C1859=Party_Statement!$C$5)*($B$3:$B1859>=Party_Statement!$C$6)*($B$3:$B1859<=Party_Statement!$E$6)),""))}
A1860: =Purchase_Entry!A5 -> 2083/04/31 | B1860: =Purchase_Entry!B5 -> 46250 | C1860: =Purchase_Entry!D5 -> MUKTESHWOR ENTERPRISES | D1860: Purchase | E1860: =Purchase_Entry!C5 -> BILL-0079 | F1860: =Purchase_Entry!F5 -> DISSEL | G1860: 0 | H1860: =N(Purchase_Entry!P5) -> 50715 | I1860: =IF($C1860="","",IF($C1860=$C591,$I591+$G1860-$H1860,$G1860-$H1860)) -> -50715 | K1860: {=IF($C1860="","",IF(AND($C1860=Party_Statement!$C$5,$B1860>=Party_Statement!$C$6,$B1860<=Party_Statement!$E$6),SUMPRODUCT(($C$3:$C1860=Party_Statement!$C$5)*($B$3:$B1860>=Party_Statement!$C$6)*($B$3:$B1860<=Party_Statement!$E$6)),""))}
A1861: =Purchase_Entry!A6 -> 2083/03/15 | B1861: =Purchase_Entry!B6 -> 46202 | C1861: =Purchase_Entry!D6 -> MODERN AGRO -315 | D1861: Purchase | E1861: =Purchase_Entry!C6 -> OPN2002 | F1861: =Purchase_Entry!F6 -> OPENING | G1861: 0 | H1861: =N(Purchase_Entry!P6) -> 172184 | I1861: =IF($C1861="","",IF($C1861=$C592,$I592+$G1861-$H1861,$G1861-$H1861)) -> -172184 | K1861: {=IF($C1861="","",IF(AND($C1861=Party_Statement!$C$5,$B1861>=Party_Statement!$C$6,$B1861<=Party_Statement!$E$6),SUMPRODUCT(($C$3:$C1861=Party_Statement!$C$5)*($B$3:$B1861>=Party_Statement!$C$6)*($B$3:$B1861<=Party_Statement!$E$6)),""))}
A1862: =Purchase_Entry!A7 -> 2083/03/15 | B1862: =Purchase_Entry!B7 -> 46202 | C1862: =Purchase_Entry!D7 -> LUSCAN | D1862: Purchase | E1862: =Purchase_Entry!C7 -> OPN2003 | F1862: =Purchase_Entry!F7 -> OPENING | G1862: 0 | H1862: =N(Purchase_Entry!P7) -> 278851 | I1862: =IF($C1862="","",IF($C1862=$C593,$I593+$G1862-$H1862,$G1862-$H1862)) -> -278851 | K1862: {=IF($C1862="","",IF(AND($C1862=Party_Statement!$C$5,$B1862>=Party_Statement!$C$6,$B1862<=Party_Statement!$E$6),SUMPRODUCT(($C$3:$C1862=Party_Statement!$C$5)*($B$3:$B1862>=Party_Statement!$C$6)*($B$3:$B1862<=Party_Statement!$E$6)),""))}
A1863: =Purchase_Entry!A8 -> 2083/03/15 | B1863: =Purchase_Entry!B8 -> 46202 | C1863: =Purchase_Entry!D8 -> PRARAMBHA DAIRY SUPPLIERS | D1863: Purchase | E1863: =Purchase_Entry!C8 -> OPN2004 | F1863: =Purchase_Entry!F8 -> OPENING | G1863: 0 | H1863: =N(Purchase_Entry!P8) -> 11932 | I1863: =IF($C1863="","",IF($C1863=$C594,$I594+$G1863-$H1863,$G1863-$H1863)) -> -11932 | K1863: {=IF($C1863="","",IF(AND($C1863=Party_Statement!$C$5,$B1863>=Party_Statement!$C$6,$B1863<=Party_Statement!$E$6),SUMPRODUCT(($C$3:$C1863=Party_Statement!$C$5)*($B$3:$B1863>=Party_Statement!$C$6)*($B$3:$B1863<=Party_Statement!$E$6)),""))}
A1864: =Purchase_Entry!A9 -> 66916 | B1864: =Purchase_Entry!B9 -> 46203 | C1864: =Purchase_Entry!D9 -> BASUDEV DAIRY 316 | D1864: Purchase | E1864: =Purchase_Entry!C9 -> BILL-5006 | F1864: =Purchase_Entry!F9 -> Buffalo Milk | G1864: 0 | H1864: =N(Purchase_Entry!P9) -> 21948 | I1864: =IF($C1864="","",IF($C1864=$C595,$I595+$G1864-$H1864,$G1864-$H1864)) -> -21948 | K1864: {=IF($C1864="","",IF(AND($C1864=Party_Statement!$C$5,$B1864>=Party_Statement!$C$6,$B1864<=Party_Statement!$E$6),SUMPRODUCT(($C$3:$C1864=Party_Statement!$C$5)*($B$3:$B1864>=Party_Statement!$C$6)*($B$3:$B1864<=Party_Statement!$E$6)),""))}
A1865: =Purchase_Entry!A10 -> 66918 | B1865: =Purchase_Entry!B10 -> 46205 | C1865: =Purchase_Entry!D10 -> BASUDEV DAIRY 316 | D1865: Purchase | E1865: =Purchase_Entry!C10 -> BILL-5020 | F1865: =Purchase_Entry!F10 -> Buffalo Milk | G1865: 0 | H1865: =N(Purchase_Entry!P10) -> 23436 | I1865: =IF($C1865="","",IF($C1865=$C596,$I596+$G1865-$H1865,$G1865-$H1865)) -> -23436 | K1865: {=IF($C1865="","",IF(AND($C1865=Party_Statement!$C$5,$B1865>=Party_Statement!$C$6,$B1865<=Party_Statement!$E$6),SUMPRODUCT(($C$3:$C1865=Party_Statement!$C$5)*($B$3:$B1865>=Party_Statement!$C$6)*($B$3:$B1865<=Party_Statement!$E$6)),""))}
A1866: =Purchase_Entry!A11 -> 66920 | B1866: =Purchase_Entry!B11 -> 46207 | C1866: =Purchase_Entry!D11 -> BASUDEV DAIRY 316 | D1866: Purchase | E1866: =Purchase_Entry!C11 -> BILL-5034 | F1866: =Purchase_Entry!F11 -> Buffalo Milk | G1866: 0 | H1866: =N(Purchase_Entry!P11) -> 24180 | I1866: =IF($C1866="","",IF($C1866=$C597,$I597+$G1866-$H1866,$G1866-$H1866)) -> -24180 | K1866: {=IF($C1866="","",IF(AND($C1866=Party_Statement!$C$5,$B1866>=Party_Statement!$C$6,$B1866<=Party_Statement!$E$6),SUMPRODUCT(($C$3:$C1866=Party_Statement!$C$5)*($B$3:$B1866>=Party_Statement!$C$6)*($B$3:$B1866<=Party_Statement!$E$6)),""))}
A1867: =Purchase_Entry!A12 -> 66922 | B1867: =Purchase_Entry!B12 -> 46209 | C1867: =Purchase_Entry!D12 -> BASUDEV DAIRY 316 | D1867: Purchase | E1867: =Purchase_Entry!C12 -> BILL-5048 | F1867: =Purchase_Entry!F12 -> Buffalo Milk | G1867: 0 | H1867: =N(Purchase_Entry!P12) -> 23064 | I1867: =IF($C1867="","",IF($C1867=$C598,$I598+$G1867-$H1867,$G1867-$H1867)) -> -23064 | K1867: {=IF($C1867="","",IF(AND($C1867=Party_Statement!$C$5,$B1867>=Party_Statement!$C$6,$B1867<=Party_Statement!$E$6),SUMPRODUCT(($C$3:$C1867=Party_Statement!$C$5)*($B$3:$B1867>=Party_Statement!$C$6)*($B$3:$B1867<=Party_Statement!$E$6)),""))}
A1868: =Purchase_Entry!A13 -> 66924 | B1868: =Purchase_Entry!B13 -> 46211 | C1868: =Purchase_Entry!D13 -> BASUDEV DAIRY 316 | D1868: Purchase | E1868: =Purchase_Entry!C13 -> BILL-5062 | F1868: =Purchase_Entry!F13 -> Buffalo Milk | G1868: 0 | H1868: =N(Purchase_Entry!P13) -> 23436 | I1868: =IF($C1868="","",IF($C1868=$C599,$I599+$G1868-$H1868,$G1868-$H1868)) -> -23436 | K1868: {=IF($C1868="","",IF(AND($C1868=Party_Statement!$C$5,$B1868>=Party_Statement!$C$6,$B1868<=Party_Statement!$E$6),SUMPRODUCT(($C$3:$C1868=Party_Statement!$C$5)*($B$3:$B1868>=Party_Statement!$C$6)*($B$3:$B1868<=Party_Statement!$E$6)),""))}
A1869: =Purchase_Entry!A14 -> 66926 | B1869: =Purchase_Entry!B14 -> 46213 | C1869: =Purchase_Entry!D14 -> BASUDEV DAIRY 316 | D1869: Purchase | E1869: =Purchase_Entry!C14 -> BILL-5076 | F1869: =Purchase_Entry!F14 -> Buffalo Milk | G1869: 0 | H1869: =N(Purchase_Entry!P14) -> 23436 | I1869: =IF($C1869="","",IF($C1869=$C600,$I600+$G1869-$H1869,$G1869-$H1869)) -> -23436 | K1869: {=IF($C1869="","",IF(AND($C1869=Party_Statement!$C$5,$B1869>=Party_Statement!$C$6,$B1869<=Party_Statement!$E$6),SUMPRODUCT(($C$3:$C1869=Party_Statement!$C$5)*($B$3:$B1869>=Party_Statement!$C$6)*($B$3:$B1869<=Party_Statement!$E$6)),""))}
... A1898: =Purchase_Entry!A43 -> 66982 | B1898: =Purchase_Entry!B43 -> 46271 | C1898: =Purchase_Entry!D43 -> BASUDEV DAIRY 316 | D1898: Purchase | E1898: =Purchase_Entry!C43 -> BILL-5152 | F1898: =Purchase_Entry!F43 -> Buffalo Milk | G1898: 0 | H1898: =N(Purchase_Entry!P43) -> 31806 | I1898: =IF($C1898="","",IF($C1898=$C629,$I629+$G1898-$H1898,$G1898-$H1898)) -> -31806 | K1898: {=IF($C1898="","",IF(AND($C1898=Party_Statement!$C$5,$B1898>=Party_Statement!$C$6,$B1898<=Party_Statement!$E$6),SUMPRODUCT(($C$3:$C1898=Party_Statement!$C$5)*($B$3:$B1898>=Party_Statement!$C$6)*($B$3:$B1898<=Party_Statement!$E$6)),""))}
A1899: =Purchase_Entry!A49 -> 66926 | B1899: =Purchase_Entry!B49 -> 46213 | C1899: =Purchase_Entry!D49 -> BODESH 310 | D1899: Purchase | E1899: =Purchase_Entry!C49 -> BILL-5078 | F1899: =Purchase_Entry!F49 -> Buffalo Milk | G1899: 0 | H1899: =N(Purchase_Entry!P49) -> 3000 | I1899: =IF($C1899="","",IF($C1899=$C630,$I630+$G1899-$H1899,$G1899-$H1899)) -> -3000 | K1899: {=IF($C1899="","",IF(AND($C1899=Party_Statement!$C$5,$B1899>=Party_Statement!$C$6,$B1899<=Party_Statement!$E$6),SUMPRODUCT(($C$3:$C1899=Party_Statement!$C$5)*($B$3:$B1899>=Party_Statement!$C$6)*($B$3:$B1899<=Party_Statement!$E$6)),""))}
A1900: =Purchase_Entry!A50 -> 66927 | B1900: =Purchase_Entry!B50 -> 46214 | C1900: =Purchase_Entry!D50 -> BODESH 310 | D1900: Purchase | E1900: =Purchase_Entry!C50 -> BILL-5086 | F1900: =Purchase_Entry!F50 -> Buffalo Milk | G1900: 0 | H1900: =N(Purchase_Entry!P50) -> 9000 | I1900: =IF($C1900="","",IF($C1900=$C631,$I631+$G1900-$H1900,$G1900-$H1900)) -> -9000 | K1900: {=IF($C1900="","",IF(AND($C1900=Party_Statement!$C$5,$B1900>=Party_Statement!$C$6,$B1900<=Party_Statement!$E$6),SUMPRODUCT(($C$3:$C1900=Party_Statement!$C$5)*($B$3:$B1900>=Party_Statement!$C$6)*($B$3:$B1900<=Party_Statement!$E$6)),""))}
A1901: =Purchase_Entry!A51 -> 66928 | B1901: =Purchase_Entry!B51 -> 46215 | C1901: =Purchase_Entry!D51 -> BODESH 310 | D1901: Purchase | E1901: =Purchase_Entry!C51 -> BILL-5094 | F1901: =Purchase_Entry!F51 -> Buffalo Milk | G1901: 0 | H1901: =N(Purchase_Entry!P51) -> 9000 | I1901: =IF($C1901="","",IF($C1901=$C632,$I632+$G1901-$H1901,$G1901-$H1901)) -> -9000 | K1901: {=IF($C1901="","",IF(AND($C1901=Party_Statement!$C$5,$B1901>=Party_Statement!$C$6,$B1901<=Party_Statement!$E$6),SUMPRODUCT(($C$3:$C1901=Party_Statement!$C$5)*($B$3:$B1901>=Party_Statement!$C$6)*($B$3:$B1901<=Party_Statement!$E$6)),""))}
A1902: =Purchase_Entry!A52 -> 66929 | B1902: =Purchase_Entry!B52 -> 46216 | C1902: =Purchase_Entry!D52 -> BODESH 310 | D1902: Purchase | E1902: =Purchase_Entry!C52 -> BILL-5102 | F1902: =Purchase_Entry!F52 -> Buffalo Milk | G1902: 0 | H1902: =N(Purchase_Entry!P52) -> 11250 | I1902: =IF($C1902="","",IF($C1902=$C633,$I633+$G1902-$H1902,$G1902-$H1902)) -> -11250 | K1902: {=IF($C1902="","",IF(AND($C1902=Party_Statement!$C$5,$B1902>=Party_Statement!$C$6,$B1902<=Party_Statement!$E$6),SUMPRODUCT(($C$3:$C1902=Party_Statement!$C$5)*($B$3:$B1902>=Party_Statement!$C$6)*($B$3:$B1902<=Party_Statement!$E$6)),""))}
A1903: =Purchase_Entry!A53 -> 66930 | B1903: =Purchase_Entry!B53 -> 46217 | C1903: =Purchase_Entry!D53 -> BODESH 310 | D1903: Purchase | E1903: =Purchase_Entry!C53 -> BILL-5110 | F1903: =Purchase_Entry!F53 -> Buffalo Milk | G1903: 0 | H1903: =N(Purchase_Entry!P53) -> 8250 | I1903: =IF($C1903="","",IF($C1903=$C634,$I634+$G1903-$H1903,$G1903-$H1903)) -> -8250 | K1903: {=IF($C1903="","",IF(AND($C1903=Party_Statement!$C$5,$B1903>=Party_Statement!$C$6,$B1903<=Party_Statement!$E$6),SUMPRODUCT(($C$3:$C1903=Party_Statement!$C$5)*($B$3:$B1903>=Party_Statement!$C$6)*($B$3:$B1903<=Party_Statement!$E$6)),""))}
A1904: =Purchase_Entry!A54 -> 66931 | B1904: =Purchase_Entry!B54 -> 46218 | C1904: =Purchase_Entry!D54 -> BODESH 310 | D1904: Purchase | E1904: =Purchase_Entry!C54 -> BILL-5118 | F1904: =Purchase_Entry!F54 -> Buffalo Milk | G1904: 0 | H1904: =N(Purchase_Entry!P54) -> 3000 | I1904: =IF($C1904="","",IF($C1904=$C635,$I635+$G1904-$H1904,$G1904-$H1904)) -> -3000 | K1904: {=IF($C1904="","",IF(AND($C1904=Party_Statement!$C$5,$B1904>=Party_Statement!$C$6,$B1904<=Party_Statement!$E$6),SUMPRODUCT(($C$3:$C1904=Party_Statement!$C$5)*($B$3:$B1904>=Party_Statement!$C$6)*($B$3:$B1904<=Party_Statement!$E$6)),""))}
A1905: =Purchase_Entry!A55 -> 2083/03/32 | B1905: =Purchase_Entry!B55 -> 46219 | C1905: =Purchase_Entry!D55 -> BODESH 310 | D1905: Purchase | E1905: =Purchase_Entry!C55 -> BILL-5126 | F1905: =Purchase_Entry!F55 -> Buffalo Milk | G1905: 0 | H1905: =N(Purchase_Entry!P55) -> 5250 | I1905: =IF($C1905="","",IF($C1905=$C636,$I636+$G1905-$H1905,$G1905-$H1905)) -> -5250 | K1905: {=IF($C1905="","",IF(AND($C1905=Party_Statement!$C$5,$B1905>=Party_Statement!$C$6,$B1905<=Party_Statement!$E$6),SUMPRODUCT(($C$3:$C1905=Party_Statement!$C$5)*($B$3:$B1905>=Party_Statement!$C$6)*($B$3:$B1905<=Party_Statement!$E$6)),""))}
A1906: =Purchase_Entry!A56 -> 66933 | B1906: =Purchase_Entry!B56 -> 46221 | C1906: =Purchase_Entry!D56 -> BODESH 310 | D1906: Purchase | E1906: =Purchase_Entry!C56 -> BILL-5140 | F1906: =Purchase_Entry!F56 -> Buffalo Milk | G1906: 0 | H1906: =N(Purchase_Entry!P56) -> 5250 | I1906: =IF($C1906="","",IF($C1906=$C637,$I637+$G1906-$H1906,$G1906-$H1906)) -> -5250 | K1906: {=IF($C1906="","",IF(AND($C1906=Party_Statement!$C$5,$B1906>=Party_Statement!$C$6,$B1906<=Party_Statement!$E$6),SUMPRODUCT(($C$3:$C1906=Party_Statement!$C$5)*($B$3:$B1906>=Party_Statement!$C$6)*($B$3:$B1906<=Party_Statement!$E$6)),""))}
A1907: =Purchase_Entry!A57 -> 66949 | B1907: =Purchase_Entry!B57 -> 46237 | C1907: =Purchase_Entry!D57 -> BODESH 310 | D1907: Purchase | E1907: =Purchase_Entry!C57 -> BILL-5154 | F1907: =Purchase_Entry!F57 -> Buffalo Milk | G1907: 0 | H1907: =N(Purchase_Entry!P57) -> 6400 | I1907: =IF($C1907="","",IF($C1907=$C638,$I638+$G1907-$H1907,$G1907-$H1907)) -> -6400 | K1907: {=IF($C1907="","",IF(AND($C1907=Party_Statement!$C$5,$B1907>=Party_Statement!$C$6,$B1907<=Party_Statement!$E$6),SUMPRODUCT(($C$3:$C1907=Party_Statement!$C$5)*($B$3:$B1907>=Party_Statement!$C$6)*($B$3:$B1907<=Party_Statement!$E$6)),""))}
A1908: =Purchase_Entry!A58 -> 66950 | B1908: =Purchase_Entry!B58 -> 46238 | C1908: =Purchase_Entry!D58 -> BODESH 310 | D1908: Purchase | E1908: =Purchase_Entry!C58 -> BILL-5154 | F1908: =Purchase_Entry!F58 -> Buffalo Milk | G1908: 0 | H1908: =N(Purchase_Entry!P58) -> 4800 | I1908: =IF($C1908="","",IF($C1908=$C639,$I639+$G1908-$H1908,$G1908-$H1908)) -> -4800 | K1908: {=IF($C1908="","",IF(AND($C1908=Party_Statement!$C$5,$B1908>=Party_Statement!$C$6,$B1908<=Party_Statement!$E$6),SUMPRODUCT(($C$3:$C1908=Party_Statement!$C$5)*($B$3:$B1908>=Party_Statement!$C$6)*($B$3:$B1908<=Party_Statement!$E$6)),""))}
A1909: =Purchase_Entry!A59 -> 66951 | B1909: =Purchase_Entry!B59 -> 46239 | C1909: =Purchase_Entry!D59 -> BODESH 310 | D1909: Purchase | E1909: =Purchase_Entry!C59 -> BILL-5154 | F1909: =Purchase_Entry!F59 -> Buffalo Milk | G1909: 0 | H1909: =N(Purchase_Entry!P59) -> 9600 | I1909: =IF($C1909="","",IF($C1909=$C640,$I640+$G1909-$H1909,$G1909-$H1909)) -> -9600 | K1909: {=IF($C1909="","",IF(AND($C1909=Party_Statement!$C$5,$B1909>=Party_Statement!$C$6,$B1909<=Party_Statement!$E$6),SUMPRODUCT(($C$3:$C1909=Party_Statement!$C$5)*($B$3:$B1909>=Party_Statement!$C$6)*($B$3:$B1909<=Party_Statement!$E$6)),""))}
A1910: =Purchase_Entry!A60 -> 66952 | B1910: =Purchase_Entry!B60 -> 46240 | C1910: =Purchase_Entry!D60 -> BODESH 310 | D1910: Purchase | E1910: =Purchase_Entry!C60 -> BILL-5154 | F1910: =Purchase_Entry!F60 -> Buffalo Milk | G1910: 0 | H1910: =N(Purchase_Entry!P60) -> 9600 | I1910: =IF($C1910="","",IF($C1910=$C641,$I641+$G1910-$H1910,$G1910-$H1910)) -> -9600 | K1910: {=IF($C1910="","",IF(AND($C1910=Party_Statement!$C$5,$B1910>=Party_Statement!$C$6,$B1910<=Party_Statement!$E$6),SUMPRODUCT(($C$3:$C1910=Party_Statement!$C$5)*($B$3:$B1910>=Party_Statement!$C$6)*($B$3:$B1910<=Party_Statement!$E$6)),""))}
... A1929: =Purchase_Entry!A79 -> 66974 | B1929: =Purchase_Entry!B79 -> 46263 | C1929: =Purchase_Entry!D79 -> BODESH 310 | D1929: Purchase | E1929: =Purchase_Entry!C79 -> BILL-5154 | F1929: =Purchase_Entry!F79 -> Buffalo Milk | G1929: 0 | H1929: =N(Purchase_Entry!P79) -> 0 | I1929: =IF($C1929="","",IF($C1929=$C660,$I660+$G1929-$H1929,$G1929-$H1929)) -> 0 | K1929: {=IF($C1929="","",IF(AND($C1929=Party_Statement!$C$5,$B1929>=Party_Statement!$C$6,$B1929<=Party_Statement!$E$6),SUMPRODUCT(($C$3:$C1929=Party_Statement!$C$5)*($B$3:$B1929>=Party_Statement!$C$6)*($B$3:$B1929<=Party_Statement!$E$6)),""))}
A1930: =Purchase_Entry!A81 -> 66992 | B1930: =Purchase_Entry!B81 -> 46281 | C1930: =Purchase_Entry!D81 -> BODESH 310 | D1930: Purchase | E1930: =Purchase_Entry!C81 -> BILL-5154 | F1930: =Purchase_Entry!F81 -> Buffalo Milk | G1930: 0 | H1930: =N(Purchase_Entry!P81) -> 3200 | I1930: =IF($C1930="","",IF($C1930=$C661,$I661+$G1930-$H1930,$G1930-$H1930)) -> -3200 | K1930: {=IF($C1930="","",IF(AND($C1930=Party_Statement!$C$5,$B1930>=Party_Statement!$C$6,$B1930<=Party_Statement!$E$6),SUMPRODUCT(($C$3:$C1930=Party_Statement!$C$5)*($B$3:$B1930>=Party_Statement!$C$6)*($B$3:$B1930<=Party_Statement!$E$6)),""))}
A1931: =Purchase_Entry!A82 -> 66916 | B1931: =Purchase_Entry!B82 -> 46203 | C1931: =Purchase_Entry!D82 -> MINA LAMICHHANE 322 | D1931: Purchase | E1931: =Purchase_Entry!C82 -> BILL-5005 | F1931: =Purchase_Entry!F82 -> Cow Milk | G1931: 0 | H1931: =N(Purchase_Entry!P82) -> 481.7367 | I1931: =IF($C1931="","",IF($C1931=$C662,$I662+$G1931-$H1931,$G1931-$H1931)) -> -481.7367 | K1931: {=IF($C1931="","",IF(AND($C1931=Party_Statement!$C$5,$B1931>=Party_Statement!$C$6,$B1931<=Party_Statement!$E$6),SUMPRODUCT(($C$3:$C1931=Party_Statement!$C$5)*($B$3:$B1931>=Party_Statement!$C$6)*($B$3:$B1931<=Party_Statement!$E$6)),""))}
A1932: =Purchase_Entry!A83 -> 66917 | B1932: =Purchase_Entry!B83 -> 46204 | C1932: =Purchase_Entry!D83 -> MINA LAMICHHANE 322 | D1932: Purchase | E1932: =Purchase_Entry!C83 -> BILL-5012 | F1932: =Purchase_Entry!F83 -> Cow Milk | G1932: 0 | H1932: =N(Purchase_Entry!P83) -> 193.0095 | I1932: =IF($C1932="","",IF($C1932=$C663,$I663+$G1932-$H1932,$G1932-$H1932)) -> -193.0095 | K1932: {=IF($C1932="","",IF(AND($C1932=Party_Statement!$C$5,$B1932>=Party_Statement!$C$6,$B1932<=Party_Statement!$E$6),SUMPRODUCT(($C$3:$C1932=Party_Statement!$C$5)*($B$3:$B1932>=Party_Statement!$C$6)*($B$3:$B1932<=Party_Statement!$E$6)),""))}
A1933: =Purchase_Entry!A84 -> 66918 | B1933: =Purchase_Entry!B84 -> 46205 | C1933: =Purchase_Entry!D84 -> MINA LAMICHHANE 322 | D1933: Purchase | E1933: =Purchase_Entry!C84 -> BILL-5019 | F1933: =Purchase_Entry!F84 -> Cow Milk | G1933: 0 | H1933: =N(Purchase_Entry!P84) -> 445.3026 | I1933: =IF($C1933="","",IF($C1933=$C664,$I664+$G1933-$H1933,$G1933-$H1933)) -> -445.3026 | K1933: {=IF($C1933="","",IF(AND($C1933=Party_Statement!$C$5,$B1933>=Party_Statement!$C$6,$B1933<=Party_Statement!$E$6),SUMPRODUCT(($C$3:$C1933=Party_Statement!$C$5)*($B$3:$B1933>=Party_Statement!$C$6)*($B$3:$B1933<=Party_Statement!$E$6)),""))}
A1934: =Purchase_Entry!A85 -> 66919 | B1934: =Purchase_Entry!B85 -> 46206 | C1934: =Purchase_Entry!D85 -> MINA LAMICHHANE 322 | D1934: Purchase | E1934: =Purchase_Entry!C85 -> BILL-5026 | F1934: =Purchase_Entry!F85 -> Cow Milk | G1934: 0 | H1934: =N(Purchase_Entry!P85) -> 440.9751 | I1934: =IF($C1934="","",IF($C1934=$C665,$I665+$G1934-$H1934,$G1934-$H1934)) -> -440.9751 | K1934: {=IF($C1934="","",IF(AND($C1934=Party_Statement!$C$5,$B1934>=Party_Statement!$C$6,$B1934<=Party_Statement!$E$6),SUMPRODUCT(($C$3:$C1934=Party_Statement!$C$5)*($B$3:$B1934>=Party_Statement!$C$6)*($B$3:$B1934<=Party_Statement!$E$6)),""))}
A1935: =Purchase_Entry!A86 -> 66920 | B1935: =Purchase_Entry!B86 -> 46207 | C1935: =Purchase_Entry!D86 -> MINA LAMICHHANE 322 | D1935: Purchase | E1935: =Purchase_Entry!C86 -> BILL-5033 | F1935: =Purchase_Entry!F86 -> Cow Milk | G1935: 0 | H1935: =N(Purchase_Entry!P86) -> 395.3125 | I1935: =IF($C1935="","",IF($C1935=$C666,$I666+$G1935-$H1935,$G1935-$H1935)) -> -395.3125 | K1935: {=IF($C1935="","",IF(AND($C1935=Party_Statement!$C$5,$B1935>=Party_Statement!$C$6,$B1935<=Party_Statement!$E$6),SUMPRODUCT(($C$3:$C1935=Party_Statement!$C$5)*($B$3:$B1935>=Party_Statement!$C$6)*($B$3:$B1935<=Party_Statement!$E$6)),""))}
A1936: =Purchase_Entry!A87 -> 66921 | B1936: =Purchase_Entry!B87 -> 46208 | C1936: =Purchase_Entry!D87 -> MINA LAMICHHANE 322 | D1936: Purchase | E1936: =Purchase_Entry!C87 -> BILL-5040 | F1936: =Purchase_Entry!F87 -> Cow Milk | G1936: 0 | H1936: =N(Purchase_Entry!P87) -> 366.5625 | I1936: =IF($C1936="","",IF($C1936=$C667,$I667+$G1936-$H1936,$G1936-$H1936)) -> -366.5625 | K1936: {=IF($C1936="","",IF(AND($C1936=Party_Statement!$C$5,$B1936>=Party_Statement!$C$6,$B1936<=Party_Statement!$E$6),SUMPRODUCT(($C$3:$C1936=Party_Statement!$C$5)*($B$3:$B1936>=Party_Statement!$C$6)*($B$3:$B1936<=Party_Statement!$E$6)),""))}
A1937: =Purchase_Entry!A88 -> 66922 | B1937: =Purchase_Entry!B88 -> 46209 | C1937: =Purchase_Entry!D88 -> MINA LAMICHHANE 322 | D1937: Purchase | E1937: =Purchase_Entry!C88 -> BILL-5047 | F1937: =Purchase_Entry!F88 -> Cow Milk | G1937: 0 | H1937: =N(Purchase_Entry!P88) -> 401.226 | I1937: =IF($C1937="","",IF($C1937=$C668,$I668+$G1937-$H1937,$G1937-$H1937)) -> -401.226 | K1937: {=IF($C1937="","",IF(AND($C1937=Party_Statement!$C$5,$B1937>=Party_Statement!$C$6,$B1937<=Party_Statement!$E$6),SUMPRODUCT(($C$3:$C1937=Party_Statement!$C$5)*($B$3:$B1937>=Party_Statement!$C$6)*($B$3:$B1937<=Party_Statement!$E$6)),""))}
A1938: =Purchase_Entry!A89 -> 66923 | B1938: =Purchase_Entry!B89 -> 46210 | C1938: =Purchase_Entry!D89 -> MINA LAMICHHANE 322 | D1938: Purchase | E1938: =Purchase_Entry!C89 -> BILL-5054 | F1938: =Purchase_Entry!F89 -> Cow Milk | G1938: 0 | H1938: =N(Purchase_Entry!P89) -> 432.615 | I1938: =IF($C1938="","",IF($C1938=$C669,$I669+$G1938-$H1938,$G1938-$H1938)) -> -432.615 | K1938: {=IF($C1938="","",IF(AND($C1938=Party_Statement!$C$5,$B1938>=Party_Statement!$C$6,$B1938<=Party_Statement!$E$6),SUMPRODUCT(($C$3:$C1938=Party_Statement!$C$5)*($B$3:$B1938>=Party_Statement!$C$6)*($B$3:$B1938<=Party_Statement!$E$6)),""))}
A1939: =Purchase_Entry!A90 -> 66924 | B1939: =Purchase_Entry!B90 -> 46211 | C1939: =Purchase_Entry!D90 -> MINA LAMICHHANE 322 | D1939: Purchase | E1939: =Purchase_Entry!C90 -> BILL-5061 | F1939: =Purchase_Entry!F90 -> Cow Milk | G1939: 0 | H1939: =N(Purchase_Entry!P90) -> 431.25 | I1939: =IF($C1939="","",IF($C1939=$C670,$I670+$G1939-$H1939,$G1939-$H1939)) -> -431.25 | K1939: {=IF($C1939="","",IF(AND($C1939=Party_Statement!$C$5,$B1939>=Party_Statement!$C$6,$B1939<=Party_Statement!$E$6),SUMPRODUCT(($C$3:$C1939=Party_Statement!$C$5)*($B$3:$B1939>=Party_Statement!$C$6)*($B$3:$B1939<=Party_Statement!$E$6)),""))}
A1940: =Purchase_Entry!A91 -> 66925 | B1940: =Purchase_Entry!B91 -> 46212 | C1940: =Purchase_Entry!D91 -> MINA LAMICHHANE 322 | D1940: Purchase | E1940: =Purchase_Entry!C91 -> BILL-5068 | F1940: =Purchase_Entry!F91 -> Cow Milk | G1940: 0 | H1940: =N(Purchase_Entry!P91) -> 447.8415 | I1940: =IF($C1940="","",IF($C1940=$C671,$I671+$G1940-$H1940,$G1940-$H1940)) -> -447.8415 | K1940: {=IF($C1940="","",IF(AND($C1940=Party_Statement!$C$5,$B1940>=Party_Statement!$C$6,$B1940<=Party_Statement!$E$6),SUMPRODUCT(($C$3:$C1940=Party_Statement!$C$5)*($B$3:$B1940>=Party_Statement!$C$6)*($B$3:$B1940<=Party_Statement!$E$6)),""))}
A1941: =Purchase_Entry!A92 -> 66926 | B1941: =Purchase_Entry!B92 -> 46213 | C1941: =Purchase_Entry!D92 -> MINA LAMICHHANE 322 | D1941: Purchase | E1941: =Purchase_Entry!C92 -> BILL-5075 | F1941: =Purchase_Entry!F92 -> Cow Milk | G1941: 0 | H1941: =N(Purchase_Entry!P92) -> 452.8125 | I1941: =IF($C1941="","",IF($C1941=$C672,$I672+$G1941-$H1941,$G1941-$H1941)) -> -452.8125 | K1941: {=IF($C1941="","",IF(AND($C1941=Party_Statement!$C$5,$B1941>=Party_Statement!$C$6,$B1941<=Party_Statement!$E$6),SUMPRODUCT(($C$3:$C1941=Party_Statement!$C$5)*($B$3:$B1941>=Party_Statement!$C$6)*($B$3:$B1941<=Party_Statement!$E$6)),""))}
... A2004: =Purchase_Entry!A155 -> 66984 | B2004: =Purchase_Entry!B155 -> 46273 | C2004: =Purchase_Entry!D155 -> MINA LAMICHHANE 322 | D2004: Purchase | E2004: =Purchase_Entry!C155 -> BILL-5204 | F2004: =Purchase_Entry!F155 -> Cow Milk | G2004: 0 | H2004: =N(Purchase_Entry!P155) -> 194.0625 | I2004: =IF($C2004="","",IF($C2004=$C735,$I735+$G2004-$H2004,$G2004-$H2004)) -> -194.0625 | K2004: {=IF($C2004="","",IF(AND($C2004=Party_Statement!$C$5,$B2004>=Party_Statement!$C$6,$B2004<=Party_Statement!$E$6),SUMPRODUCT(($C$3:$C2004=Party_Statement!$C$5)*($B$3:$B2004>=Party_Statement!$C$6)*($B$3:$B2004<=Party_Statement!$E$6)),""))}
A2005: =Purchase_Entry!A171 -> 66916 | B2005: =Purchase_Entry!B171 -> 46203 | C2005: =Purchase_Entry!D171 -> MODERN AGRO -315 | D2005: Purchase | E2005: =Purchase_Entry!C171 -> BILL-5001 | F2005: =Purchase_Entry!F171 -> Cow Milk | G2005: 0 | H2005: =N(Purchase_Entry!P171) -> 3069.1832 | I2005: =IF($C2005="","",IF($C2005=$C736,$I736+$G2005-$H2005,$G2005-$H2005)) -> -3069.1832 | K2005: {=IF($C2005="","",IF(AND($C2005=Party_Statement!$C$5,$B2005>=Party_Statement!$C$6,$B2005<=Party_Statement!$E$6),SUMPRODUCT(($C$3:$C2005=Party_Statement!$C$5)*($B$3:$B2005>=Party_Statement!$C$6)*($B$3:$B2005<=Party_Statement!$E$6)),""))}
A2006: =Purchase_Entry!A172 -> 66916 | B2006: =Purchase_Entry!B172 -> 46203 | C2006: =Purchase_Entry!D172 -> MODERN AGRO -315 | D2006: Purchase | E2006: =Purchase_Entry!C172 -> BILL-5002 | F2006: =Purchase_Entry!F172 -> Buffalo Milk | G2006: 0 | H2006: =N(Purchase_Entry!P172) -> 1709.844 | I2006: =IF($C2006="","",IF($C2006=$C737,$I737+$G2006-$H2006,$G2006-$H2006)) -> -1709.844 | K2006: {=IF($C2006="","",IF(AND($C2006=Party_Statement!$C$5,$B2006>=Party_Statement!$C$6,$B2006<=Party_Statement!$E$6),SUMPRODUCT(($C$3:$C2006=Party_Statement!$C$5)*($B$3:$B2006>=Party_Statement!$C$6)*($B$3:$B2006<=Party_Statement!$E$6)),""))}
A2007: =Purchase_Entry!A173 -> 66916 | B2007: =Purchase_Entry!B173 -> 46203 | C2007: =Purchase_Entry!D173 -> MODERN AGRO -315 | D2007: Purchase | E2007: =Purchase_Entry!C173 -> BILL-5001 | F2007: =Purchase_Entry!F173 -> Cow Milk | G2007: 0 | H2007: =N(Purchase_Entry!P173) -> 2056.7348 | I2007: =IF($C2007="","",IF($C2007=$C738,$I738+$G2007-$H2007,$G2007-$H2007)) -> -2056.7348 | K2007: {=IF($C2007="","",IF(AND($C2007=Party_Statement!$C$5,$B2007>=Party_Statement!$C$6,$B2007<=Party_Statement!$E$6),SUMPRODUCT(($C$3:$C2007=Party_Statement!$C$5)*($B$3:$B2007>=Party_Statement!$C$6)*($B$3:$B2007<=Party_Statement!$E$6)),""))}
A2008: =Purchase_Entry!A174 -> 66916 | B2008: =Purchase_Entry!B174 -> 46203 | C2008: =Purchase_Entry!D174 -> MODERN AGRO -315 | D2008: Purchase | E2008: =Purchase_Entry!C174 -> BILL-5002 | F2008: =Purchase_Entry!F174 -> Buffalo Milk | G2008: 0 | H2008: =N(Purchase_Entry!P174) -> 1309.34 | I2008: =IF($C2008="","",IF($C2008=$C739,$I739+$G2008-$H2008,$G2008-$H2008)) -> -1309.34 | K2008: {=IF($C2008="","",IF(AND($C2008=Party_Statement!$C$5,$B2008>=Party_Statement!$C$6,$B2008<=Party_Statement!$E$6),SUMPRODUCT(($C$3:$C2008=Party_Statement!$C$5)*($B$3:$B2008>=Party_Statement!$C$6)*($B$3:$B2008<=Party_Statement!$E$6)),""))}
A2009: =Purchase_Entry!A175 -> 66917 | B2009: =Purchase_Entry!B175 -> 46204 | C2009: =Purchase_Entry!D175 -> MODERN AGRO -315 | D2009: Purchase | E2009: =Purchase_Entry!C175 -> BILL-5008 | F2009: =Purchase_Entry!F175 -> Cow Milk | G2009: 0 | H2009: =N(Purchase_Entry!P175) -> 3262.9445 | I2009: =IF($C2009="","",IF($C2009=$C740,$I740+$G2009-$H2009,$G2009-$H2009)) -> -3262.9445 | K2009: {=IF($C2009="","",IF(AND($C2009=Party_Statement!$C$5,$B2009>=Party_Statement!$C$6,$B2009<=Party_Statement!$E$6),SUMPRODUCT(($C$3:$C2009=Party_Statement!$C$5)*($B$3:$B2009>=Party_Statement!$C$6)*($B$3:$B2009<=Party_Statement!$E$6)),""))}
A2010: =Purchase_Entry!A176 -> 66917 | B2010: =Purchase_Entry!B176 -> 46204 | C2010: =Purchase_Entry!D176 -> MODERN AGRO -315 | D2010: Purchase | E2010: =Purchase_Entry!C176 -> BILL-5009 | F2010: =Purchase_Entry!F176 -> Buffalo Milk | G2010: 0 | H2010: =N(Purchase_Entry!P176) -> 1775.048 | I2010: =IF($C2010="","",IF($C2010=$C741,$I741+$G2010-$H2010,$G2010-$H2010)) -> -1775.048 | K2010: {=IF($C2010="","",IF(AND($C2010=Party_Statement!$C$5,$B2010>=Party_Statement!$C$6,$B2010<=Party_Statement!$E$6),SUMPRODUCT(($C$3:$C2010=Party_Statement!$C$5)*($B$3:$B2010>=Party_Statement!$C$6)*($B$3:$B2010<=Party_Statement!$E$6)),""))}
A2011: =Purchase_Entry!A177 -> 66917 | B2011: =Purchase_Entry!B177 -> 46204 | C2011: =Purchase_Entry!D177 -> MODERN AGRO -315 | D2011: Purchase | E2011: =Purchase_Entry!C177 -> BILL-5008 | F2011: =Purchase_Entry!F177 -> Cow Milk | G2011: 0 | H2011: =N(Purchase_Entry!P177) -> 2480.8635 | I2011: =IF($C2011="","",IF($C2011=$C742,$I742+$G2011-$H2011,$G2011-$H2011)) -> -2480.8635 | K2011: {=IF($C2011="","",IF(AND($C2011=Party_Statement!$C$5,$B2011>=Party_Statement!$C$6,$B2011<=Party_Statement!$E$6),SUMPRODUCT(($C$3:$C2011=Party_Statement!$C$5)*($B$3:$B2011>=Party_Statement!$C$6)*($B$3:$B2011<=Party_Statement!$E$6)),""))}
A2012: =Purchase_Entry!A178 -> 66917 | B2012: =Purchase_Entry!B178 -> 46204 | C2012: =Purchase_Entry!D178 -> MODERN AGRO -315 | D2012: Purchase | E2012: =Purchase_Entry!C178 -> BILL-5009 | F2012: =Purchase_Entry!F178 -> Buffalo Milk | G2012: 0 | H2012: =N(Purchase_Entry!P178) -> 1049.5936 | I2012: =IF($C2012="","",IF($C2012=$C743,$I743+$G2012-$H2012,$G2012-$H2012)) -> -1049.5936 | K2012: {=IF($C2012="","",IF(AND($C2012=Party_Statement!$C$5,$B2012>=Party_Statement!$C$6,$B2012<=Party_Statement!$E$6),SUMPRODUCT(($C$3:$C2012=Party_Statement!$C$5)*($B$3:$B2012>=Party_Statement!$C$6)*($B$3:$B2012<=Party_Statement!$E$6)),""))}
A2013: =Purchase_Entry!A179 -> 66918 | B2013: =Purchase_Entry!B179 -> 46205 | C2013: =Purchase_Entry!D179 -> MODERN AGRO -315 | D2013: Purchase | E2013: =Purchase_Entry!C179 -> BILL-5015 | F2013: =Purchase_Entry!F179 -> Cow Milk | G2013: 0 | H2013: =N(Purchase_Entry!P179) -> 3245.568 | I2013: =IF($C2013="","",IF($C2013=$C744,$I744+$G2013-$H2013,$G2013-$H2013)) -> -3245.568 | K2013: {=IF($C2013="","",IF(AND($C2013=Party_Statement!$C$5,$B2013>=Party_Statement!$C$6,$B2013<=Party_Statement!$E$6),SUMPRODUCT(($C$3:$C2013=Party_Statement!$C$5)*($B$3:$B2013>=Party_Statement!$C$6)*($B$3:$B2013<=Party_Statement!$E$6)),""))}
A2014: =Purchase_Entry!A180 -> 66918 | B2014: =Purchase_Entry!B180 -> 46205 | C2014: =Purchase_Entry!D180 -> MODERN AGRO -315 | D2014: Purchase | E2014: =Purchase_Entry!C180 -> BILL-5016 | F2014: =Purchase_Entry!F180 -> Buffalo Milk | G2014: 0 | H2014: =N(Purchase_Entry!P180) -> 1778.038 | I2014: =IF($C2014="","",IF($C2014=$C745,$I745+$G2014-$H2014,$G2014-$H2014)) -> -1778.038 | K2014: {=IF($C2014="","",IF(AND($C2014=Party_Statement!$C$5,$B2014>=Party_Statement!$C$6,$B2014<=Party_Statement!$E$6),SUMPRODUCT(($C$3:$C2014=Party_Statement!$C$5)*($B$3:$B2014>=Party_Statement!$C$6)*($B$3:$B2014<=Party_Statement!$E$6)),""))}
A2015: =Purchase_Entry!A181 -> 66918 | B2015: =Purchase_Entry!B181 -> 46205 | C2015: =Purchase_Entry!D181 -> MODERN AGRO -315 | D2015: Purchase | E2015: =Purchase_Entry!C181 -> BILL-5015 | F2015: =Purchase_Entry!F181 -> Cow Milk | G2015: 0 | H2015: =N(Purchase_Entry!P181) -> 2332.752 | I2015: =IF($C2015="","",IF($C2015=$C746,$I746+$G2015-$H2015,$G2015-$H2015)) -> -2332.752 | K2015: {=IF($C2015="","",IF(AND($C2015=Party_Statement!$C$5,$B2015>=Party_Statement!$C$6,$B2015<=Party_Statement!$E$6),SUMPRODUCT(($C$3:$C2015=Party_Statement!$C$5)*($B$3:$B2015>=Party_Statement!$C$6)*($B$3:$B2015<=Party_Statement!$E$6)),""))}
A2016: =Purchase_Entry!A182 -> 66918 | B2016: =Purchase_Entry!B182 -> 46205 | C2016: =Purchase_Entry!D182 -> MODERN AGRO -315 | D2016: Purchase | E2016: =Purchase_Entry!C182 -> BILL-5016 | F2016: =Purchase_Entry!F182 -> Buffalo Milk | G2016: 0 | H2016: =N(Purchase_Entry!P182) -> 1205.9736 | I2016: =IF($C2016="","",IF($C2016=$C747,$I747+$G2016-$H2016,$G2016-$H2016)) -> -1205.9736 | K2016: {=IF($C2016="","",IF(AND($C2016=Party_Statement!$C$5,$B2016>=Party_Statement!$C$6,$B2016<=Party_Statement!$E$6),SUMPRODUCT(($C$3:$C2016=Party_Statement!$C$5)*($B$3:$B2016>=Party_Statement!$C$6)*($B$3:$B2016<=Party_Statement!$E$6)),""))}
... A2288: =Purchase_Entry!A454 -> 66984 | B2288: =Purchase_Entry!B454 -> 46273 | C2288: =Purchase_Entry!D454 -> MODERN AGRO -315 | D2288: Purchase | E2288: =Purchase_Entry!C454 -> BILL-5176 | F2288: =Purchase_Entry!F454 -> Buffalo Milk | G2288: 0 | H2288: =N(Purchase_Entry!P454) -> 1064.9695 | I2288: =IF($C2288="","",IF($C2288=$C1019,$I1019+$G2288-$H2288,$G2288-$H2288)) -> -1064.9695 | K2288: {=IF($C2288="","",IF(AND($C2288=Party_Statement!$C$5,$B2288>=Party_Statement!$C$6,$B2288<=Party_Statement!$E$6),SUMPRODUCT(($C$3:$C2288=Party_Statement!$C$5)*($B$3:$B2288>=Party_Statement!$C$6)*($B$3:$B2288<=Party_Statement!$E$6)),""))}
A2289: =Purchase_Entry!A487 -> 66916 | B2289: =Purchase_Entry!B487 -> 46203 | C2289: =Purchase_Entry!D487 -> NAWA DURGA -317 | D2289: Purchase | E2289: =Purchase_Entry!C487 -> BILL-5003 | F2289: =Purchase_Entry!F487 -> Cow Milk | G2289: 0 | H2289: =N(Purchase_Entry!P487) -> 2304.2075 | I2289: =IF($C2289="","",IF($C2289=$C1020,$I1020+$G2289-$H2289,$G2289-$H2289)) -> -2304.2075 | K2289: {=IF($C2289="","",IF(AND($C2289=Party_Statement!$C$5,$B2289>=Party_Statement!$C$6,$B2289<=Party_Statement!$E$6),SUMPRODUCT(($C$3:$C2289=Party_Statement!$C$5)*($B$3:$B2289>=Party_Statement!$C$6)*($B$3:$B2289<=Party_Statement!$E$6)),""))}
A2290: =Purchase_Entry!A488 -> 66917 | B2290: =Purchase_Entry!B488 -> 46204 | C2290: =Purchase_Entry!D488 -> NAWA DURGA -317 | D2290: Purchase | E2290: =Purchase_Entry!C488 -> BILL-5010 | F2290: =Purchase_Entry!F488 -> Cow Milk | G2290: 0 | H2290: =N(Purchase_Entry!P488) -> 2573.61 | I2290: =IF($C2290="","",IF($C2290=$C1021,$I1021+$G2290-$H2290,$G2290-$H2290)) -> -2573.61 | K2290: {=IF($C2290="","",IF(AND($C2290=Party_Statement!$C$5,$B2290>=Party_Statement!$C$6,$B2290<=Party_Statement!$E$6),SUMPRODUCT(($C$3:$C2290=Party_Statement!$C$5)*($B$3:$B2290>=Party_Statement!$C$6)*($B$3:$B2290<=Party_Statement!$E$6)),""))}
A2291: =Purchase_Entry!A489 -> 66918 | B2291: =Purchase_Entry!B489 -> 46205 | C2291: =Purchase_Entry!D489 -> NAWA DURGA -317 | D2291: Purchase | E2291: =Purchase_Entry!C489 -> BILL-5017 | F2291: =Purchase_Entry!F489 -> Cow Milk | G2291: 0 | H2291: =N(Purchase_Entry!P489) -> 2434.7575 | I2291: =IF($C2291="","",IF($C2291=$C1022,$I1022+$G2291-$H2291,$G2291-$H2291)) -> -2434.7575 | K2291: {=IF($C2291="","",IF(AND($C2291=Party_Statement!$C$5,$B2291>=Party_Statement!$C$6,$B2291<=Party_Statement!$E$6),SUMPRODUCT(($C$3:$C2291=Party_Statement!$C$5)*($B$3:$B2291>=Party_Statement!$C$6)*($B$3:$B2291<=Party_Statement!$E$6)),""))}
A2292: =Purchase_Entry!A490 -> 66919 | B2292: =Purchase_Entry!B490 -> 46206 | C2292: =Purchase_Entry!D490 -> NAWA DURGA -317 | D2292: Purchase | E2292: =Purchase_Entry!C490 -> BILL-5024 | F2292: =Purchase_Entry!F490 -> Cow Milk | G2292: 0 | H2292: =N(Purchase_Entry!P490) -> 1880.715 | I2292: =IF($C2292="","",IF($C2292=$C1023,$I1023+$G2292-$H2292,$G2292-$H2292)) -> -1880.715 | K2292: {=IF($C2292="","",IF(AND($C2292=Party_Statement!$C$5,$B2292>=Party_Statement!$C$6,$B2292<=Party_Statement!$E$6),SUMPRODUCT(($C$3:$C2292=Party_Statement!$C$5)*($B$3:$B2292>=Party_Statement!$C$6)*($B$3:$B2292<=Party_Statement!$E$6)),""))}
A2293: =Purchase_Entry!A491 -> 66920 | B2293: =Purchase_Entry!B491 -> 46207 | C2293: =Purchase_Entry!D491 -> NAWA DURGA -317 | D2293: Purchase | E2293: =Purchase_Entry!C491 -> BILL-5031 | F2293: =Purchase_Entry!F491 -> Cow Milk | G2293: 0 | H2293: =N(Purchase_Entry!P491) -> 2173.6575 | I2293: =IF($C2293="","",IF($C2293=$C1024,$I1024+$G2293-$H2293,$G2293-$H2293)) -> -2173.6575 | K2293: {=IF($C2293="","",IF(AND($C2293=Party_Statement!$C$5,$B2293>=Party_Statement!$C$6,$B2293<=Party_Statement!$E$6),SUMPRODUCT(($C$3:$C2293=Party_Statement!$C$5)*($B$3:$B2293>=Party_Statement!$C$6)*($B$3:$B2293<=Party_Statement!$E$6)),""))}
A2294: =Purchase_Entry!A492 -> 66921 | B2294: =Purchase_Entry!B492 -> 46208 | C2294: =Purchase_Entry!D492 -> NAWA DURGA -317 | D2294: Purchase | E2294: =Purchase_Entry!C492 -> BILL-5038 | F2294: =Purchase_Entry!F492 -> Cow Milk | G2294: 0 | H2294: =N(Purchase_Entry!P492) -> 1997.415 | I2294: =IF($C2294="","",IF($C2294=$C1025,$I1025+$G2294-$H2294,$G2294-$H2294)) -> -1997.415 | K2294: {=IF($C2294="","",IF(AND($C2294=Party_Statement!$C$5,$B2294>=Party_Statement!$C$6,$B2294<=Party_Statement!$E$6),SUMPRODUCT(($C$3:$C2294=Party_Statement!$C$5)*($B$3:$B2294>=Party_Statement!$C$6)*($B$3:$B2294<=Party_Statement!$E$6)),""))}
A2295: =Purchase_Entry!A493 -> 66922 | B2295: =Purchase_Entry!B493 -> 46209 | C2295: =Purchase_Entry!D493 -> NAWA DURGA -317 | D2295: Purchase | E2295: =Purchase_Entry!C493 -> BILL-5045 | F2295: =Purchase_Entry!F493 -> Cow Milk | G2295: 0 | H2295: =N(Purchase_Entry!P493) -> 1754.991 | I2295: =IF($C2295="","",IF($C2295=$C1026,$I1026+$G2295-$H2295,$G2295-$H2295)) -> -1754.991 | K2295: {=IF($C2295="","",IF(AND($C2295=Party_Statement!$C$5,$B2295>=Party_Statement!$C$6,$B2295<=Party_Statement!$E$6),SUMPRODUCT(($C$3:$C2295=Party_Statement!$C$5)*($B$3:$B2295>=Party_Statement!$C$6)*($B$3:$B2295<=Party_Statement!$E$6)),""))}
A2296: =Purchase_Entry!A494 -> 66923 | B2296: =Purchase_Entry!B494 -> 46210 | C2296: =Purchase_Entry!D494 -> NAWA DURGA -317 | D2296: Purchase | E2296: =Purchase_Entry!C494 -> BILL-5052 | F2296: =Purchase_Entry!F494 -> Cow Milk | G2296: 0 | H2296: =N(Purchase_Entry!P494) -> 2346.561 | I2296: =IF($C2296="","",IF($C2296=$C1027,$I1027+$G2296-$H2296,$G2296-$H2296)) -> -2346.561 | K2296: {=IF($C2296="","",IF(AND($C2296=Party_Statement!$C$5,$B2296>=Party_Statement!$C$6,$B2296<=Party_Statement!$E$6),SUMPRODUCT(($C$3:$C2296=Party_Statement!$C$5)*($B$3:$B2296>=Party_Statement!$C$6)*($B$3:$B2296<=Party_Statement!$E$6)),""))}
A2297: =Purchase_Entry!A495 -> 66924 | B2297: =Purchase_Entry!B495 -> 46211 | C2297: =Purchase_Entry!D495 -> NAWA DURGA -317 | D2297: Purchase | E2297: =Purchase_Entry!C495 -> BILL-5059 | F2297: =Purchase_Entry!F495 -> Cow Milk | G2297: 0 | H2297: =N(Purchase_Entry!P495) -> 2088.8 | I2297: =IF($C2297="","",IF($C2297=$C1028,$I1028+$G2297-$H2297,$G2297-$H2297)) -> -2088.8 | K2297: {=IF($C2297="","",IF(AND($C2297=Party_Statement!$C$5,$B2297>=Party_Statement!$C$6,$B2297<=Party_Statement!$E$6),SUMPRODUCT(($C$3:$C2297=Party_Statement!$C$5)*($B$3:$B2297>=Party_Statement!$C$6)*($B$3:$B2297<=Party_Statement!$E$6)),""))}
A2298: =Purchase_Entry!A496 -> 66925 | B2298: =Purchase_Entry!B496 -> 46212 | C2298: =Purchase_Entry!D496 -> NAWA DURGA -317 | D2298: Purchase | E2298: =Purchase_Entry!C496 -> BILL-5066 | F2298: =Purchase_Entry!F496 -> Cow Milk | G2298: 0 | H2298: =N(Purchase_Entry!P496) -> 1979.7 | I2298: =IF($C2298="","",IF($C2298=$C1029,$I1029+$G2298-$H2298,$G2298-$H2298)) -> -1979.7 | K2298: {=IF($C2298="","",IF(AND($C2298=Party_Statement!$C$5,$B2298>=Party_Statement!$C$6,$B2298<=Party_Statement!$E$6),SUMPRODUCT(($C$3:$C2298=Party_Statement!$C$5)*($B$3:$B2298>=Party_Statement!$C$6)*($B$3:$B2298<=Party_Statement!$E$6)),""))}
A2299: =Purchase_Entry!A497 -> 66926 | B2299: =Purchase_Entry!B497 -> 46213 | C2299: =Purchase_Entry!D497 -> NAWA DURGA -317 | D2299: Purchase | E2299: =Purchase_Entry!C497 -> BILL-5073 | F2299: =Purchase_Entry!F497 -> Cow Milk | G2299: 0 | H2299: =N(Purchase_Entry!P497) -> 1939.035 | I2299: =IF($C2299="","",IF($C2299=$C1030,$I1030+$G2299-$H2299,$G2299-$H2299)) -> -1939.035 | K2299: {=IF($C2299="","",IF(AND($C2299=Party_Statement!$C$5,$B2299>=Party_Statement!$C$6,$B2299<=Party_Statement!$E$6),SUMPRODUCT(($C$3:$C2299=Party_Statement!$C$5)*($B$3:$B2299>=Party_Statement!$C$6)*($B$3:$B2299<=Party_Statement!$E$6)),""))}
A2300: =Purchase_Entry!A498 -> 66927 | B2300: =Purchase_Entry!B498 -> 46214 | C2300: =Purchase_Entry!D498 -> NAWA DURGA -317 | D2300: Purchase | E2300: =Purchase_Entry!C498 -> BILL-5081 | F2300: =Purchase_Entry!F498 -> Cow Milk | G2300: 0 | H2300: =N(Purchase_Entry!P498) -> 1939.035 | I2300: =IF($C2300="","",IF($C2300=$C1031,$I1031+$G2300-$H2300,$G2300-$H2300)) -> -1939.035 | K2300: {=IF($C2300="","",IF(AND($C2300=Party_Statement!$C$5,$B2300>=Party_Statement!$C$6,$B2300<=Party_Statement!$E$6),SUMPRODUCT(($C$3:$C2300=Party_Statement!$C$5)*($B$3:$B2300>=Party_Statement!$C$6)*($B$3:$B2300<=Party_Statement!$E$6)),""))}
... A2475: =Purchase_Entry!A673 -> 66976 | B2475: =Purchase_Entry!B673 -> 46265 | C2475: =Purchase_Entry!D673 -> NEW FARM PHARSATIKAT | D2475: Purchase | E2475: =Purchase_Entry!C673 -> BILL-5154 | F2475: =Purchase_Entry!F673 -> Cow Milk | G2475: 0 | H2475: =N(Purchase_Entry!P673) -> 1521 | I2475: =IF($C2475="","",IF($C2475=$C1206,$I1206+$G2475-$H2475,$G2475-$H2475)) -> -1521 | K2475: {=IF($C2475="","",IF(AND($C2475=Party_Statement!$C$5,$B2475>=Party_Statement!$C$6,$B2475<=Party_Statement!$E$6),SUMPRODUCT(($C$3:$C2475=Party_Statement!$C$5)*($B$3:$B2475>=Party_Statement!$C$6)*($B$3:$B2475<=Party_Statement!$E$6)),""))}
A2476: =Purchase_Entry!A738 -> 66916 | B2476: =Purchase_Entry!B738 -> 46203 | C2476: =Purchase_Entry!D738 -> PARSURAM THARU -333 | D2476: Purchase | E2476: =Purchase_Entry!C738 -> BILL-5004 | F2476: =Purchase_Entry!F738 -> Cow Milk | G2476: 0 | H2476: =N(Purchase_Entry!P738) -> 607.008 | I2476: =IF($C2476="","",IF($C2476=$C1207,$I1207+$G2476-$H2476,$G2476-$H2476)) -> -607.008 | K2476: {=IF($C2476="","",IF(AND($C2476=Party_Statement!$C$5,$B2476>=Party_Statement!$C$6,$B2476<=Party_Statement!$E$6),SUMPRODUCT(($C$3:$C2476=Party_Statement!$C$5)*($B$3:$B2476>=Party_Statement!$C$6)*($B$3:$B2476<=Party_Statement!$E$6)),""))}
A2477: =Purchase_Entry!A739 -> 66917 | B2477: =Purchase_Entry!B739 -> 46204 | C2477: =Purchase_Entry!D739 -> PARSURAM THARU -333 | D2477: Purchase | E2477: =Purchase_Entry!C739 -> BILL-5011 | F2477: =Purchase_Entry!F739 -> Cow Milk | G2477: 0 | H2477: =N(Purchase_Entry!P739) -> 573.75 | I2477: =IF($C2477="","",IF($C2477=$C1208,$I1208+$G2477-$H2477,$G2477-$H2477)) -> -573.75 | K2477: {=IF($C2477="","",IF(AND($C2477=Party_Statement!$C$5,$B2477>=Party_Statement!$C$6,$B2477<=Party_Statement!$E$6),SUMPRODUCT(($C$3:$C2477=Party_Statement!$C$5)*($B$3:$B2477>=Party_Statement!$C$6)*($B$3:$B2477<=Party_Statement!$E$6)),""))}
A2478: =Purchase_Entry!A740 -> 66918 | B2478: =Purchase_Entry!B740 -> 46205 | C2478: =Purchase_Entry!D740 -> PARSURAM THARU -333 | D2478: Purchase | E2478: =Purchase_Entry!C740 -> BILL-5018 | F2478: =Purchase_Entry!F740 -> Cow Milk | G2478: 0 | H2478: =N(Purchase_Entry!P740) -> 635.30775 | I2478: =IF($C2478="","",IF($C2478=$C1209,$I1209+$G2478-$H2478,$G2478-$H2478)) -> -635.30775 | K2478: {=IF($C2478="","",IF(AND($C2478=Party_Statement!$C$5,$B2478>=Party_Statement!$C$6,$B2478<=Party_Statement!$E$6),SUMPRODUCT(($C$3:$C2478=Party_Statement!$C$5)*($B$3:$B2478>=Party_Statement!$C$6)*($B$3:$B2478<=Party_Statement!$E$6)),""))}
A2479: =Purchase_Entry!A741 -> 66919 | B2479: =Purchase_Entry!B741 -> 46206 | C2479: =Purchase_Entry!D741 -> PARSURAM THARU -333 | D2479: Purchase | E2479: =Purchase_Entry!C741 -> BILL-5025 | F2479: =Purchase_Entry!F741 -> Cow Milk | G2479: 0 | H2479: =N(Purchase_Entry!P741) -> 646.272 | I2479: =IF($C2479="","",IF($C2479=$C1210,$I1210+$G2479-$H2479,$G2479-$H2479)) -> -646.272 | K2479: {=IF($C2479="","",IF(AND($C2479=Party_Statement!$C$5,$B2479>=Party_Statement!$C$6,$B2479<=Party_Statement!$E$6),SUMPRODUCT(($C$3:$C2479=Party_Statement!$C$5)*($B$3:$B2479>=Party_Statement!$C$6)*($B$3:$B2479<=Party_Statement!$E$6)),""))}
A2480: =Purchase_Entry!A742 -> 66920 | B2480: =Purchase_Entry!B742 -> 46207 | C2480: =Purchase_Entry!D742 -> PARSURAM THARU -333 | D2480: Purchase | E2480: =Purchase_Entry!C742 -> BILL-5032 | F2480: =Purchase_Entry!F742 -> Cow Milk | G2480: 0 | H2480: =N(Purchase_Entry!P742) -> 633.76335 | I2480: =IF($C2480="","",IF($C2480=$C1211,$I1211+$G2480-$H2480,$G2480-$H2480)) -> -633.76335 | K2480: {=IF($C2480="","",IF(AND($C2480=Party_Statement!$C$5,$B2480>=Party_Statement!$C$6,$B2480<=Party_Statement!$E$6),SUMPRODUCT(($C$3:$C2480=Party_Statement!$C$5)*($B$3:$B2480>=Party_Statement!$C$6)*($B$3:$B2480<=Party_Statement!$E$6)),""))}
A2481: =Purchase_Entry!A743 -> 66921 | B2481: =Purchase_Entry!B743 -> 46208 | C2481: =Purchase_Entry!D743 -> PARSURAM THARU -333 | D2481: Purchase | E2481: =Purchase_Entry!C743 -> BILL-5039 | F2481: =Purchase_Entry!F743 -> Cow Milk | G2481: 0 | H2481: =N(Purchase_Entry!P743) -> 564.718 | I2481: =IF($C2481="","",IF($C2481=$C1212,$I1212+$G2481-$H2481,$G2481-$H2481)) -> -564.718 | K2481: {=IF($C2481="","",IF(AND($C2481=Party_Statement!$C$5,$B2481>=Party_Statement!$C$6,$B2481<=Party_Statement!$E$6),SUMPRODUCT(($C$3:$C2481=Party_Statement!$C$5)*($B$3:$B2481>=Party_Statement!$C$6)*($B$3:$B2481<=Party_Statement!$E$6)),""))}
A2482: =Purchase_Entry!A744 -> 66922 | B2482: =Purchase_Entry!B744 -> 46209 | C2482: =Purchase_Entry!D744 -> PARSURAM THARU -333 | D2482: Purchase | E2482: =Purchase_Entry!C744 -> BILL-5046 | F2482: =Purchase_Entry!F744 -> Cow Milk | G2482: 0 | H2482: =N(Purchase_Entry!P744) -> 588.4136 | I2482: =IF($C2482="","",IF($C2482=$C1213,$I1213+$G2482-$H2482,$G2482-$H2482)) -> -588.4136 | K2482: {=IF($C2482="","",IF(AND($C2482=Party_Statement!$C$5,$B2482>=Party_Statement!$C$6,$B2482<=Party_Statement!$E$6),SUMPRODUCT(($C$3:$C2482=Party_Statement!$C$5)*($B$3:$B2482>=Party_Statement!$C$6)*($B$3:$B2482<=Party_Statement!$E$6)),""))}
A2483: =Purchase_Entry!A745 -> 66923 | B2483: =Purchase_Entry!B745 -> 46210 | C2483: =Purchase_Entry!D745 -> PARSURAM THARU -333 | D2483: Purchase | E2483: =Purchase_Entry!C745 -> BILL-5053 | F2483: =Purchase_Entry!F745 -> Cow Milk | G2483: 0 | H2483: =N(Purchase_Entry!P745) -> 606.2425 | I2483: =IF($C2483="","",IF($C2483=$C1214,$I1214+$G2483-$H2483,$G2483-$H2483)) -> -606.2425 | K2483: {=IF($C2483="","",IF(AND($C2483=Party_Statement!$C$5,$B2483>=Party_Statement!$C$6,$B2483<=Party_Statement!$E$6),SUMPRODUCT(($C$3:$C2483=Party_Statement!$C$5)*($B$3:$B2483>=Party_Statement!$C$6)*($B$3:$B2483<=Party_Statement!$E$6)),""))}
A2484: =Purchase_Entry!A746 -> 66924 | B2484: =Purchase_Entry!B746 -> 46211 | C2484: =Purchase_Entry!D746 -> PARSURAM THARU -333 | D2484: Purchase | E2484: =Purchase_Entry!C746 -> BILL-5060 | F2484: =Purchase_Entry!F746 -> Cow Milk | G2484: 0 | H2484: =N(Purchase_Entry!P746) -> 598.6782 | I2484: =IF($C2484="","",IF($C2484=$C1215,$I1215+$G2484-$H2484,$G2484-$H2484)) -> -598.6782 | K2484: {=IF($C2484="","",IF(AND($C2484=Party_Statement!$C$5,$B2484>=Party_Statement!$C$6,$B2484<=Party_Statement!$E$6),SUMPRODUCT(($C$3:$C2484=Party_Statement!$C$5)*($B$3:$B2484>=Party_Statement!$C$6)*($B$3:$B2484<=Party_Statement!$E$6)),""))}
A2485: =Purchase_Entry!A747 -> 66925 | B2485: =Purchase_Entry!B747 -> 46212 | C2485: =Purchase_Entry!D747 -> PARSURAM THARU -333 | D2485: Purchase | E2485: =Purchase_Entry!C747 -> BILL-5067 | F2485: =Purchase_Entry!F747 -> Cow Milk | G2485: 0 | H2485: =N(Purchase_Entry!P747) -> 563.9744 | I2485: =IF($C2485="","",IF($C2485=$C1216,$I1216+$G2485-$H2485,$G2485-$H2485)) -> -563.9744 | K2485: {=IF($C2485="","",IF(AND($C2485=Party_Statement!$C$5,$B2485>=Party_Statement!$C$6,$B2485<=Party_Statement!$E$6),SUMPRODUCT(($C$3:$C2485=Party_Statement!$C$5)*($B$3:$B2485>=Party_Statement!$C$6)*($B$3:$B2485<=Party_Statement!$E$6)),""))}
A2486: =Purchase_Entry!A748 -> 66926 | B2486: =Purchase_Entry!B748 -> 46213 | C2486: =Purchase_Entry!D748 -> PARSURAM THARU -333 | D2486: Purchase | E2486: =Purchase_Entry!C748 -> BILL-5074 | F2486: =Purchase_Entry!F748 -> Cow Milk | G2486: 0 | H2486: =N(Purchase_Entry!P748) -> 495.9825 | I2486: =IF($C2486="","",IF($C2486=$C1217,$I1217+$G2486-$H2486,$G2486-$H2486)) -> -495.9825 | K2486: {=IF($C2486="","",IF(AND($C2486=Party_Statement!$C$5,$B2486>=Party_Statement!$C$6,$B2486<=Party_Statement!$E$6),SUMPRODUCT(($C$3:$C2486=Party_Statement!$C$5)*($B$3:$B2486>=Party_Statement!$C$6)*($B$3:$B2486<=Party_Statement!$E$6)),""))}
A2487: =Purchase_Entry!A749 -> 66927 | B2487: =Purchase_Entry!B749 -> 46214 | C2487: =Purchase_Entry!D749 -> PARSURAM THARU -333 | D2487: Purchase | E2487: =Purchase_Entry!C749 -> BILL-5082 | F2487: =Purchase_Entry!F749 -> Cow Milk | G2487: 0 | H2487: =N(Purchase_Entry!P749) -> 620.2665 | I2487: =IF($C2487="","",IF($C2487=$C1218,$I1218+$G2487-$H2487,$G2487-$H2487)) -> -620.2665 | K2487: {=IF($C2487="","",IF(AND($C2487=Party_Statement!$C$5,$B2487>=Party_Statement!$C$6,$B2487<=Party_Statement!$E$6),SUMPRODUCT(($C$3:$C2487=Party_Statement!$C$5)*($B$3:$B2487>=Party_Statement!$C$6)*($B$3:$B2487<=Party_Statement!$E$6)),""))}
... A2565: =Purchase_Entry!A827 -> 66984 | B2565: =Purchase_Entry!B827 -> 46273 | C2565: =Purchase_Entry!D827 -> RADHA PANDEY | D2565: Purchase | E2565: =Purchase_Entry!C827 -> BILL-5204 | F2565: =Purchase_Entry!F827 -> Cow Milk | G2565: 0 | H2565: =N(Purchase_Entry!P827) -> 243.8555 | I2565: =IF($C2565="","",IF($C2565=$C1296,$I1296+$G2565-$H2565,$G2565-$H2565)) -> -243.8555 | K2565: {=IF($C2565="","",IF(AND($C2565=Party_Statement!$C$5,$B2565>=Party_Statement!$C$6,$B2565<=Party_Statement!$E$6),SUMPRODUCT(($C$3:$C2565=Party_Statement!$C$5)*($B$3:$B2565>=Party_Statement!$C$6)*($B$3:$B2565<=Party_Statement!$E$6)),""))}
A2566: =Purchase_Entry!A829 -> 2083/05/31 | B2566: =Purchase_Entry!B829 -> 46281 | C2566: =Purchase_Entry!D829 -> SHREE PAROHA DAIRY UDHYOG | D2566: Purchase | E2566: =Purchase_Entry!C829 -> BILL-5204 | F2566: =Purchase_Entry!F829 -> Mix Milk | G2566: 0 | H2566: =N(Purchase_Entry!P829) -> 33200 | I2566: =IF($C2566="","",IF($C2566=$C1297,$I1297+$G2566-$H2566,$G2566-$H2566)) -> -33200 | K2566: {=IF($C2566="","",IF(AND($C2566=Party_Statement!$C$5,$B2566>=Party_Statement!$C$6,$B2566<=Party_Statement!$E$6),SUMPRODUCT(($C$3:$C2566=Party_Statement!$C$5)*($B$3:$B2566>=Party_Statement!$C$6)*($B$3:$B2566<=Party_Statement!$E$6)),""))}
A2567: =Purchase_Entry!A830 -> 2083/05/27 | B2567: =Purchase_Entry!B830 -> 46277 | C2567: =Purchase_Entry!D830 -> SHIV GANGA DAIRY | D2567: Purchase | E2567: =Purchase_Entry!C830 -> BILL-5204 | F2567: =Purchase_Entry!F830 -> SMP | G2567: 0 | H2567: =N(Purchase_Entry!P830) -> 20000 | I2567: =IF($C2567="","",IF($C2567=$C1298,$I1298+$G2567-$H2567,$G2567-$H2567)) -> -20000 | K2567: {=IF($C2567="","",IF(AND($C2567=Party_Statement!$C$5,$B2567>=Party_Statement!$C$6,$B2567<=Party_Statement!$E$6),SUMPRODUCT(($C$3:$C2567=Party_Statement!$C$5)*($B$3:$B2567>=Party_Statement!$C$6)*($B$3:$B2567<=Party_Statement!$E$6)),""))}
A2568: =Purchase_Entry!A831 -> 2083/03/15 | B2568: =Purchase_Entry!B831 -> 46202 | C2568: =Purchase_Entry!D831 -> 0 | D2568: Purchase | E2568: =Purchase_Entry!C831 -> 0 | F2568: =Purchase_Entry!F831 -> 0 | G2568: 0 | H2568: =N(Purchase_Entry!P831) -> 0 | I2568: =IF($C2568="","",IF($C2568=$C1299,$I1299+$G2568-$H2568,$G2568-$H2568)) -> 0 | K2568: {=IF($C2568="","",IF(AND($C2568=Party_Statement!$C$5,$B2568>=Party_Statement!$C$6,$B2568<=Party_Statement!$E$6),SUMPRODUCT(($C$3:$C2568=Party_Statement!$C$5)*($B$3:$B2568>=Party_Statement!$C$6)*($B$3:$B2568<=Party_Statement!$E$6)),""))}
...

Sheet Sales_Entry
A1: =D33 -> CHHATRABHUMI STORE
A2: Date | B2: AD Date | C2: Invoice No | D2: Party Name | E2: Product | F2: Quantity | G2: Rate | H2: Amount | I2: Discount % | J2: Net Amount | K2: Payment Mode | L2: Status | M2: Remarks
A3: 66915 | B3: =IF(A3="","",IF(ISNUMBER(A3),IFERROR(VLOOKUP(TEXT(A3,"yyyy/mm/dd"),BSAD,2,FALSE),""),IFERROR(VLOOKUP(A3,BSAD,2,FALSE),""))) -> 46202 | C3: OPN-1001 | D3: NAWA DURGA -317 | E3: OPENING | F3: 1 | G3: 81953 | H3: =IF($F3="","",$F3*$G3) -> 81953 | I3: 0 | J3: =IF($F3="","",$H3*(1-$I3/100)) -> 81953 | K3: Credit | L3: Unpaid
A4: 66915 | B4: =IF(A4="","",IF(ISNUMBER(A4),IFERROR(VLOOKUP(TEXT(A4,"yyyy/mm/dd"),BSAD,2,FALSE),""),IFERROR(VLOOKUP(A4,BSAD,2,FALSE),""))) -> 46202 | C4: OPN-1002 | D4: THE DARBAR PARTY PALACE | E4: OPENING | F4: 1 | G4: 28322 | H4: =IF($F4="","",$F4*$G4) -> 28322 | I4: 0 | J4: =IF($F4="","",$H4*(1-$I4/100)) -> 28322 | K4: Credit | L4: Unpaid
A5: 66915 | B5: =IF(A5="","",IF(ISNUMBER(A5),IFERROR(VLOOKUP(TEXT(A5,"yyyy/mm/dd"),BSAD,2,FALSE),""),IFERROR(VLOOKUP(A5,BSAD,2,FALSE),""))) -> 46202 | C5: OPN-1003 | D5: SRIJANA DAIRY | E5: OPENING | F5: 1 | G5: 6950 | H5: =IF($F5="","",$F5*$G5) -> 6950 | I5: 0 | J5: =IF($F5="","",$H5*(1-$I5/100)) -> 6950 | K5: Credit | L5: Unpaid
A6: 66915 | B6: =IF(A6="","",IF(ISNUMBER(A6),IFERROR(VLOOKUP(TEXT(A6,"yyyy/mm/dd"),BSAD,2,FALSE),""),IFERROR(VLOOKUP(A6,BSAD,2,FALSE),""))) -> 46202 | C6: OPN-1004 | D6: SOBHA BHATTARAI | E6: OPENING | F6: 1 | G6: 3400 | H6: =IF($F6="","",$F6*$G6) -> 3400 | I6: 0 | J6: =IF($F6="","",$H6*(1-$I6/100)) -> 3400 | K6: Credit | L6: Unpaid
A7: 66915 | B7: =IF(A7="","",IF(ISNUMBER(A7),IFERROR(VLOOKUP(TEXT(A7,"yyyy/mm/dd"),BSAD,2,FALSE),""),IFERROR(VLOOKUP(A7,BSAD,2,FALSE),""))) -> 46202 | C7: OPN-1005 | D7: CHHATRABHUMI STORE | E7: OPENING | F7: 1 | G7: 44495 | H7: =IF($F7="","",$F7*$G7) -> 44495 | I7: 0 | J7: =IF($F7="","",$H7*(1-$I7/100)) -> 44495 | K7: Credit | L7: Unpaid
A8: 66915 | B8: =IF(A8="","",IF(ISNUMBER(A8),IFERROR(VLOOKUP(TEXT(A8,"yyyy/mm/dd"),BSAD,2,FALSE),""),IFERROR(VLOOKUP(A8,BSAD,2,FALSE),""))) -> 46202 | C8: OPN-1006 | D8: AAMOSH KIRANA | E8: OPENING | F8: 1 | G8: 208022 | H8: =IF($F8="","",$F8*$G8) -> 208022 | I8: 0 | J8: =IF($F8="","",$H8*(1-$I8/100)) -> 208022 | K8: Credit | L8: Unpaid
A9: 66915 | B9: =IF(A9="","",IF(ISNUMBER(A9),IFERROR(VLOOKUP(TEXT(A9,"yyyy/mm/dd"),BSAD,2,FALSE),""),IFERROR(VLOOKUP(A9,BSAD,2,FALSE),""))) -> 46202 | C9: OPN-1007 | D9: ORGANIC TARKALI | E9: OPENING | F9: 1 | G9: 9310 | H9: =IF($F9="","",$F9*$G9) -> 9310 | I9: 0 | J9: =IF($F9="","",$H9*(1-$I9/100)) -> 9310 | K9: Credit | L9: Unpaid
A10: 66915 | B10: =IF(A10="","",IF(ISNUMBER(A10),IFERROR(VLOOKUP(TEXT(A10,"yyyy/mm/dd"),BSAD,2,FALSE),""),IFERROR(VLOOKUP(A10,BSAD,2,FALSE),""))) -> 46202 | C10: OPN-1008 | D10: SHARMA DAI | E10: OPENING | F10: 1 | G10: 39602 | H10: =IF($F10="","",$F10*$G10) -> 39602 | I10: 0 | J10: =IF($F10="","",$H10*(1-$I10/100)) -> 39602 | K10: Credit | L10: Unpaid
A11: 66915 | B11: =IF(A11="","",IF(ISNUMBER(A11),IFERROR(VLOOKUP(TEXT(A11,"yyyy/mm/dd"),BSAD,2,FALSE),""),IFERROR(VLOOKUP(A11,BSAD,2,FALSE),""))) -> 46202 | C11: OPN-1009 | D11: GANGA NEUPANE | E11: OPENING | F11: 1 | G11: 14507 | H11: =IF($F11="","",$F11*$G11) -> 14507 | I11: 0 | J11: =IF($F11="","",$H11*(1-$I11/100)) -> 14507 | K11: Credit | L11: Unpaid
A12: 66915 | B12: =IF(A12="","",IF(ISNUMBER(A12),IFERROR(VLOOKUP(TEXT(A12,"yyyy/mm/dd"),BSAD,2,FALSE),""),IFERROR(VLOOKUP(A12,BSAD,2,FALSE),""))) -> 46202 | C12: OPN-1010 | D12: GIRI KIRANA | E12: OPENING | F12: 1 | G12: 2550 | H12: =IF($F12="","",$F12*$G12) -> 2550 | I12: 0 | J12: =IF($F12="","",$H12*(1-$I12/100)) -> 2550 | K12: Credit | L12: Unpaid
A13: 66915 | B13: =IF(A13="","",IF(ISNUMBER(A13),IFERROR(VLOOKUP(TEXT(A13,"yyyy/mm/dd"),BSAD,2,FALSE),""),IFERROR(VLOOKUP(A13,BSAD,2,FALSE),""))) -> 46202 | C13: OPN-1011 | D13: NAR BAHADUR RANA | E13: OPENING | F13: 1 | G13: 8117.5 | H13: =IF($F13="","",$F13*$G13) -> 8117.5 | I13: 0 | J13: =IF($F13="","",$H13*(1-$I13/100)) -> 8117.5 | K13: Credit | L13: Unpaid
A14: 66915 | B14: =IF(A14="","",IF(ISNUMBER(A14),IFERROR(VLOOKUP(TEXT(A14,"yyyy/mm/dd"),BSAD,2,FALSE),""),IFERROR(VLOOKUP(A14,BSAD,2,FALSE),""))) -> 46202 | C14: OPN-1012 | D14: DIPAK NEPAL | E14: OPENING | F14: 1 | G14: 2750 | H14: =IF($F14="","",$F14*$G14) -> 2750 | I14: 0 | J14: =IF($F14="","",$H14*(1-$I14/100)) -> 2750 | K14: Credit | L14: Unpaid
... A382: 66931 | B382: =IF(A382="","",IF(ISNUMBER(A382),IFERROR(VLOOKUP(TEXT(A382,"yyyy/mm/dd"),BSAD,2,FALSE),""),IFERROR(VLOOKUP(A382,BSAD,2,FALSE),""))) -> 46218 | C382: BILL-6299 | D382: LOCAL | E382: Mix Milk | F382: 8.5 | G382: 92.94 | H382: =IF($F382="","",$F382*$G382) -> 789.99 | I382: 0 | J382: =IF($F382="","",$H382*(1-$I382/100)) -> 789.99 | K382: Credit | L382: Unpaid
A383: 2083/03/32 | B383: =IF(A383="","",IF(ISNUMBER(A383),IFERROR(VLOOKUP(TEXT(A383,"yyyy/mm/dd"),BSAD,2,FALSE),""),IFERROR(VLOOKUP(A383,BSAD,2,FALSE),""))) -> 46219 | C383: BILL-6300 | D383: CANCELED | H383: =IF($F383="","",$F383*$G383) | J383: =IF($F383="","",$H383*(1-$I383/100)) | K383: Credit | L383: Unpaid
A384: 2083/03/32 | B384: =IF(A384="","",IF(ISNUMBER(A384),IFERROR(VLOOKUP(TEXT(A384,"yyyy/mm/dd"),BSAD,2,FALSE),""),IFERROR(VLOOKUP(A384,BSAD,2,FALSE),""))) -> 46219 | C384: BILL-6301 | D384: SRIJANA DAIRY | E384: Mix Milk | F384: 60 | G384: 85 | H384: =IF($F384="","",$F384*$G384) -> 5100 | I384: 0 | J384: =IF($F384="","",$H384*(1-$I384/100)) -> 5100 | K384: Credit | L384: Unpaid | M384: =H384-J384 -> 0
A385: 2083/03/32 | B385: =IF(A385="","",IF(ISNUMBER(A385),IFERROR(VLOOKUP(TEXT(A385,"yyyy/mm/dd"),BSAD,2,FALSE),""),IFERROR(VLOOKUP(A385,BSAD,2,FALSE),""))) -> 46219 | C385: BILL-6301 | D385: SRIJANA DAIRY | E385: Cow Milk | F385: 1 | G385: 80 | H385: =IF($F385="","",$F385*$G385) -> 80 | I385: 0 | J385: =IF($F385="","",$H385*(1-$I385/100)) -> 80 | K385: Credit | L385: Unpaid | M385: =H385-J385 -> 0
A386: 2083/03/32 | B386: =IF(A386="","",IF(ISNUMBER(A386),IFERROR(VLOOKUP(TEXT(A386,"yyyy/mm/dd"),BSAD,2,FALSE),""),IFERROR(VLOOKUP(A386,BSAD,2,FALSE),""))) -> 46219 | C386: BILL-6302 | D386: AAMOSH KIRANA | E386: Mix Milk | F386: 40 | G386: 86 | H386: =IF($F386="","",$F386*$G386) -> 3440 | I386: 0 | J386: =IF($F386="","",$H386*(1-$I386/100)) -> 3440 | K386: Credit | L386: Unpaid | M386: =H386-J386 -> 0
A387: 2083/03/32 | B387: =IF(A387="","",IF(ISNUMBER(A387),IFERROR(VLOOKUP(TEXT(A387,"yyyy/mm/dd"),BSAD,2,FALSE),""),IFERROR(VLOOKUP(A387,BSAD,2,FALSE),""))) -> 46219 | C387: BILL-6302 | D387: AAMOSH KIRANA | E387: Mix Milk | F387: 50 | G387: 85 | H387: =IF($F387="","",$F387*$G387) -> 4250 | I387: 0 | J387: =IF($F387="","",$H387*(1-$I387/100)) -> 4250 | K387: Credit | L387: Unpaid | M387: =H387-J387 -> 0
A388: 2083/03/32 | B388: =IF(A388="","",IF(ISNUMBER(A388),IFERROR(VLOOKUP(TEXT(A388,"yyyy/mm/dd"),BSAD,2,FALSE),""),IFERROR(VLOOKUP(A388,BSAD,2,FALSE),""))) -> 46219 | C388: BILL-6302 | D388: AAMOSH KIRANA | E388: Cow Milk | F388: 1 | G388: 80 | H388: =IF($F388="","",$F388*$G388) -> 80 | I388: 0 | J388: =IF($F388="","",$H388*(1-$I388/100)) -> 80 | K388: Credit | L388: Unpaid | M388: =H388-J388 -> 0
A389: 2083/03/32 | B389: =IF(A389="","",IF(ISNUMBER(A389),IFERROR(VLOOKUP(TEXT(A389,"yyyy/mm/dd"),BSAD,2,FALSE),""),IFERROR(VLOOKUP(A389,BSAD,2,FALSE),""))) -> 46219 | C389: BILL-6303 | D389: SOBHA BHATTARAI | E389: Mix Milk | F389: 35 | G389: 85 | H389: =IF($F389="","",$F389*$G389) -> 2975 | I389: 0 | J389: =IF($F389="","",$H389*(1-$I389/100)) -> 2975 | K389: Credit | L389: Unpaid | M389: =H389-J389 -> 0
A390: 2083/03/32 | B390: =IF(A390="","",IF(ISNUMBER(A390),IFERROR(VLOOKUP(TEXT(A390,"yyyy/mm/dd"),BSAD,2,FALSE),""),IFERROR(VLOOKUP(A390,BSAD,2,FALSE),""))) -> 46219 | C390: BILL-6304 | D390: CHHATRABHUMI STORE | E390: Mix Milk | F390: 25 | G390: 86 | H390: =IF($F390="","",$F390*$G390) -> 2150 | I390: 0 | J390: =IF($F390="","",$H390*(1-$I390/100)) -> 2150 | K390: Credit | L390: Unpaid | M390: =H390-J390 -> 0
A391: 2083/03/32 | B391: =IF(A391="","",IF(ISNUMBER(A391),IFERROR(VLOOKUP(TEXT(A391,"yyyy/mm/dd"),BSAD,2,FALSE),""),IFERROR(VLOOKUP(A391,BSAD,2,FALSE),""))) -> 46219 | C391: BILL-6305 | D391: KRISHNA KHAREL | E391: Mix Milk | F391: 4.5 | G391: 86 | H391: =IF($F391="","",$F391*$G391) -> 387 | I391: 0 | J391: =IF($F391="","",$H391*(1-$I391/100)) -> 387 | K391: Credit | L391: Unpaid | M391: =H391-J391 -> 0
A392: 2083/03/32 | B392: =IF(A392="","",IF(ISNUMBER(A392),IFERROR(VLOOKUP(TEXT(A392,"yyyy/mm/dd"),BSAD,2,FALSE),""),IFERROR(VLOOKUP(A392,BSAD,2,FALSE),""))) -> 46219 | C392: BILL-6305 | D392: KRISHNA KHAREL | E392: NAUNI | F392: 1 | G392: 800 | H392: =IF($F392="","",$F392*$G392) -> 800 | I392: 0 | J392: =IF($F392="","",$H392*(1-$I392/100)) -> 800 | K392: Credit | L392: Unpaid | M392: =H392-J392 -> 0
A393: 2083/03/32 | B393: =IF(A393="","",IF(ISNUMBER(A393),IFERROR(VLOOKUP(TEXT(A393,"yyyy/mm/dd"),BSAD,2,FALSE),""),IFERROR(VLOOKUP(A393,BSAD,2,FALSE),""))) -> 46219 | C393: BILL-6306 | D393: SAMIKSHYA KIRANA | E393: Mix Milk | F393: 8 | G393: 85 | H393: =IF($F393="","",$F393*$G393) -> 680 | I393: 0 | J393: =IF($F393="","",$H393*(1-$I393/100)) -> 680 | K393: Credit | L393: Unpaid | M393: =H393-J393 -> 0
A394: 2083/03/32 | B394: =IF(A394="","",IF(ISNUMBER(A394),IFERROR(VLOOKUP(TEXT(A394,"yyyy/mm/dd"),BSAD,2,FALSE),""),IFERROR(VLOOKUP(A394,BSAD,2,FALSE),""))) -> 46219 | C394: BILL-6307 | D394: MANAKAMANA DAIRY | E394: Mix Milk | F394: 5 | G394: 85 | H394: =IF($F394="","",$F394*$G394) -> 425 | I394: 0 | J394: =IF($F394="","",$H394*(1-$I394/100)) -> 425 | K394: Credit | L394: Unpaid | M394: =H394-J394 -> 0
A395: 2083/03/32 | B395: =IF(A395="","",IF(ISNUMBER(A395),IFERROR(VLOOKUP(TEXT(A395,"yyyy/mm/dd"),BSAD,2,FALSE),""),IFERROR(VLOOKUP(A395,BSAD,2,FALSE),""))) -> 46219 | C395: BILL-6308 | D395: KRITIKA KIRANA | E395: Mix Milk | F395: 10 | G395: 86 | H395: =IF($F395="","",$F395*$G395) -> 860 | I395: 0 | J395: =IF($F395="","",$H395*(1-$I395/100)) -> 860 | K395: Credit | L395: Unpaid | M395: =H395-J395 -> 0
... A413: 2083/03/32 | B413: =IF(A413="","",IF(ISNUMBER(A413),IFERROR(VLOOKUP(TEXT(A413,"yyyy/mm/dd"),BSAD,2,FALSE),""),IFERROR(VLOOKUP(A413,BSAD,2,FALSE),""))) -> 46219 | C413: BILL-6340 | D413: SHANKAR KHAREL | E413: Mix Milk | F413: 35 | G413: 90 | H413: =IF($F413="","",$F413*$G413) -> 3150 | I413: 0 | J413: =IF($F413="","",$H413*(1-$I413/100)) -> 3150 | K413: Credit | L413: Unpaid | M413: =H413-J413 -> 0
A414: 66932 | B414: =IF(A414="","",IF(ISNUMBER(A414),IFERROR(VLOOKUP(TEXT(A414,"yyyy/mm/dd"),BSAD,2,FALSE),""),IFERROR(VLOOKUP(A414,BSAD,2,FALSE),""))) -> 46220 | C414: BILL-6320 | D414: SRIJANA DAIRY | E414: Mix Milk | F414: 60 | G414: 85 | H414: =IF($F414="","",$F414*$G414) -> 5100 | I414: 0 | J414: =IF($F414="","",$H414*(1-$I414/100)) -> 5100 | K414: Credit | L414: Unpaid | M414: =H414-J414 -> 0
A415: 66932 | B415: =IF(A415="","",IF(ISNUMBER(A415),IFERROR(VLOOKUP(TEXT(A415,"yyyy/mm/dd"),BSAD,2,FALSE),""),IFERROR(VLOOKUP(A415,BSAD,2,FALSE),""))) -> 46220 | C415: BILL-6320 | D415: SRIJANA DAIRY | E415: Cow Milk | F415: 1 | G415: 80 | H415: =IF($F415="","",$F415*$G415) -> 80 | I415: 0 | J415: =IF($F415="","",$H415*(1-$I415/100)) -> 80 | K415: Credit | L415: Unpaid | M415: =H415-J415 -> 0
A416: 66932 | B416: =IF(A416="","",IF(ISNUMBER(A416),IFERROR(VLOOKUP(TEXT(A416,"yyyy/mm/dd"),BSAD,2,FALSE),""),IFERROR(VLOOKUP(A416,BSAD,2,FALSE),""))) -> 46220 | C416: BILL-6321 | D416: SOBHA BHATTARAI | E416: Mix Milk | F416: 55 | G416: 85 | H416: =IF($F416="","",$F416*$G416) -> 4675 | I416: 0 | J416: =IF($F416="","",$H416*(1-$I416/100)) -> 4675 | K416: Credit | L416: Unpaid | M416: =H416-J416 -> 0
A417: 66932 | B417: =IF(A417="","",IF(ISNUMBER(A417),IFERROR(VLOOKUP(TEXT(A417,"yyyy/mm/dd"),BSAD,2,FALSE),""),IFERROR(VLOOKUP(A417,BSAD,2,FALSE),""))) -> 46220 | C417: BILL-6322 | D417: PALPALI KIRANA | E417: Mix Milk | F417: 25 | G417: 85 | H417: =IF($F417="","",$F417*$G417) -> 2125 | I417: 0 | J417: =IF($F417="","",$H417*(1-$I417/100)) -> 2125 | K417: Credit | L417: Unpaid | M417: =H417-J417 -> 0
A418: 66932 | B418: =IF(A418="","",IF(ISNUMBER(A418),IFERROR(VLOOKUP(TEXT(A418,"yyyy/mm/dd"),BSAD,2,FALSE),""),IFERROR(VLOOKUP(A418,BSAD,2,FALSE),""))) -> 46220 | C418: BILL-6323 | D418: AAMOSH KIRANA | E418: Mix Milk | F418: 40 | G418: 86 | H418: =IF($F418="","",$F418*$G418) -> 3440 | I418: 0 | J418: =IF($F418="","",$H418*(1-$I418/100)) -> 3440 | K418: Credit | L418: Unpaid | M418: =H418-J418 -> 0
A419: 66932 | B419: =IF(A419="","",IF(ISNUMBER(A419),IFERROR(VLOOKUP(TEXT(A419,"yyyy/mm/dd"),BSAD,2,FALSE),""),IFERROR(VLOOKUP(A419,BSAD,2,FALSE),""))) -> 46220 | C419: BILL-6323 | D419: AAMOSH KIRANA | E419: Mix Milk | F419: 55 | G419: 85 | H419: =IF($F419="","",$F419*$G419) -> 4675 | I419: 0 | J419: =IF($F419="","",$H419*(1-$I419/100)) -> 4675 | K419: Credit | L419: Unpaid | M419: =H419-J419 -> 0
A420: 66932 | B420: =IF(A420="","",IF(ISNUMBER(A420),IFERROR(VLOOKUP(TEXT(A420,"yyyy/mm/dd"),BSAD,2,FALSE),""),IFERROR(VLOOKUP(A420,BSAD,2,FALSE),""))) -> 46220 | C420: BILL-6323 | D420: AAMOSH KIRANA | E420: Ghee | F420: 4 | G420: 1100 | H420: =IF($F420="","",$F420*$G420) -> 4400 | I420: 0 | J420: =IF($F420="","",$H420*(1-$I420/100)) -> 4400 | K420: Credit | L420: Unpaid | M420: =H420-J420 -> 0
A421: 66932 | B421: =IF(A421="","",IF(ISNUMBER(A421),IFERROR(VLOOKUP(TEXT(A421,"yyyy/mm/dd"),BSAD,2,FALSE),""),IFERROR(VLOOKUP(A421,BSAD,2,FALSE),""))) -> 46220 | C421: BILL-6323 | D421: AAMOSH KIRANA | E421: Cow Milk | F421: 1 | G421: 80 | H421: =IF($F421="","",$F421*$G421) -> 80 | I421: 0 | J421: =IF($F421="","",$H421*(1-$I421/100)) -> 80 | K421: Credit | L421: Unpaid | M421: =H421-J421 -> 0
A422: 66932 | B422: =IF(A422="","",IF(ISNUMBER(A422),IFERROR(VLOOKUP(TEXT(A422,"yyyy/mm/dd"),BSAD,2,FALSE),""),IFERROR(VLOOKUP(A422,BSAD,2,FALSE),""))) -> 46220 | C422: BILL-6324 | D422: DEURALI KIRANA | E422: Mix Milk | F422: 5 | G422: 85 | H422: =IF($F422="","",$F422*$G422) -> 425 | I422: 0 | J422: =IF($F422="","",$H422*(1-$I422/100)) -> 425 | K422: Credit | L422: Unpaid | M422: =H422-J422 -> 0
A423: 66932 | B423: =IF(A423="","",IF(ISNUMBER(A423),IFERROR(VLOOKUP(TEXT(A423,"yyyy/mm/dd"),BSAD,2,FALSE),""),IFERROR(VLOOKUP(A423,BSAD,2,FALSE),""))) -> 46220 | C423: BILL-6325 | D423: GIRI KIRANA | E423: Mix Milk | F423: 35 | G423: 85 | H423: =IF($F423="","",$F423*$G423) -> 2975 | I423: 0 | J423: =IF($F423="","",$H423*(1-$I423/100)) -> 2975 | K423: Credit | L423: Unpaid | M423: =H423-J423 -> 0
A424: 66932 | B424: =IF(A424="","",IF(ISNUMBER(A424),IFERROR(VLOOKUP(TEXT(A424,"yyyy/mm/dd"),BSAD,2,FALSE),""),IFERROR(VLOOKUP(A424,BSAD,2,FALSE),""))) -> 46220 | C424: BILL-6326 | D424: CHHATRABHUMI STORE | E424: Mix Milk | F424: 30 | G424: 86 | H424: =IF($F424="","",$F424*$G424) -> 2580 | I424: 0 | J424: =IF($F424="","",$H424*(1-$I424/100)) -> 2580 | K424: Credit | L424: Unpaid | M424: =H424-J424 -> 0
A425: 66932 | B425: =IF(A425="","",IF(ISNUMBER(A425),IFERROR(VLOOKUP(TEXT(A425,"yyyy/mm/dd"),BSAD,2,FALSE),""),IFERROR(VLOOKUP(A425,BSAD,2,FALSE),""))) -> 46220 | C425: BILL-6327 | D425: KRISHNA KHAREL | E425: Mix Milk | F425: 4.5 | G425: 86 | H425: =IF($F425="","",$F425*$G425) -> 387 | I425: 0 | J425: =IF($F425="","",$H425*(1-$I425/100)) -> 387 | K425: Credit | L425: Unpaid | M425: =H425-J425 -> 0
... A611: 66940 | B611: =IF(A611="","",IF(ISNUMBER(A611),IFERROR(VLOOKUP(TEXT(A611,"yyyy/mm/dd"),BSAD,2,FALSE),""),IFERROR(VLOOKUP(A611,BSAD,2,FALSE),""))) -> 46228 | C611: BILL-6453 | D611: LOCAL | E611: NAUNI | F611: 2 | G611: 800 | H611: =IF($F611="","",$F611*$G611) -> 1600 | I611: 0 | J611: =IF($F611="","",$H611*(1-$I611/100)) -> 1600 | K611: Credit | L611: PAID | M611: =H611-J611 -> 0
A612: 2083/04/10 | B612: =IF(A612="","",IF(ISNUMBER(A612),IFERROR(VLOOKUP(TEXT(A612,"yyyy/mm/dd"),BSAD,2,FALSE),""),IFERROR(VLOOKUP(A612,BSAD,2,FALSE),""))) -> 46229 | C612: BILL-6532 | D612: NEUPANE KIRANA | E612: Mix Milk | F612: 4 | G612: 100 | H612: =IF($F612="","",$F612*$G612) -> 400 | I612: 0 | J612: =IF($F612="","",$H612*(1-$I612/100)) -> 400 | K612: Credit | L612: Unpaid | M612: =H612-J612 -> 0
A613: 2083/04/10 | B613: =IF(A613="","",IF(ISNUMBER(A613),IFERROR(VLOOKUP(TEXT(A613,"yyyy/mm/dd"),BSAD,2,FALSE),""),IFERROR(VLOOKUP(A613,BSAD,2,FALSE),""))) -> 46229 | C613: BILL-6533 | D613: SRIJANA DAIRY | E613: Mix Milk | F613: 55 | G613: 85 | H613: =IF($F613="","",$F613*$G613) -> 4675 | I613: 0 | J613: =IF($F613="","",$H613*(1-$I613/100)) -> 4675 | K613: Credit | L613: Unpaid | M613: =H613-J613 -> 0
A614: 2083/04/10 | B614: =IF(A614="","",IF(ISNUMBER(A614),IFERROR(VLOOKUP(TEXT(A614,"yyyy/mm/dd"),BSAD,2,FALSE),""),IFERROR(VLOOKUP(A614,BSAD,2,FALSE),""))) -> 46229 | C614: BILL-6533 | D614: SRIJANA DAIRY | E614: Cow Milk | F614: 1 | G614: 80 | H614: =IF($F614="","",$F614*$G614) -> 80 | I614: 0 | J614: =IF($F614="","",$H614*(1-$I614/100)) -> 80 | K614: Credit | L614: Unpaid | M614: =H614-J614 -> 0
A615: 2083/04/10 | B615: =IF(A615="","",IF(ISNUMBER(A615),IFERROR(VLOOKUP(TEXT(A615,"yyyy/mm/dd"),BSAD,2,FALSE),""),IFERROR(VLOOKUP(A615,BSAD,2,FALSE),""))) -> 46229 | C615: BILL-6534 | D615: CHHATRABHUMI STORE | E615: Mix Milk | F615: 44 | G615: 86 | H615: =IF($F615="","",$F615*$G615) -> 3784 | I615: 0 | J615: =IF($F615="","",$H615*(1-$I615/100)) -> 3784 | K615: Credit | L615: Unpaid | M615: =H615-J615 -> 0
A616: 2083/04/10 | B616: =IF(A616="","",IF(ISNUMBER(A616),IFERROR(VLOOKUP(TEXT(A616,"yyyy/mm/dd"),BSAD,2,FALSE),""),IFERROR(VLOOKUP(A616,BSAD,2,FALSE),""))) -> 46229 | C616: BILL-6534 | D616: CHHATRABHUMI STORE | E616: NAUNI | F616: 1 | G616: 800 | H616: =IF($F616="","",$F616*$G616) -> 800 | I616: 0 | J616: =IF($F616="","",$H616*(1-$I616/100)) -> 800 | K616: Credit | L616: Unpaid | M616: =H616-J616 -> 0
A617: 2083/04/10 | B617: =IF(A617="","",IF(ISNUMBER(A617),IFERROR(VLOOKUP(TEXT(A617,"yyyy/mm/dd"),BSAD,2,FALSE),""),IFERROR(VLOOKUP(A617,BSAD,2,FALSE),""))) -> 46229 | C617: BILL-6535 | D617: KRISHNA KHAREL | E617: Mix Milk | F617: 3 | G617: 86 | H617: =IF($F617="","",$F617*$G617) -> 258 | I617: 0 | J617: =IF($F617="","",$H617*(1-$I617/100)) -> 258 | K617: Credit | L617: Unpaid | M617: =H617-J617 -> 0
A618: 2083/04/10 | B618: =IF(A618="","",IF(ISNUMBER(A618),IFERROR(VLOOKUP(TEXT(A618,"yyyy/mm/dd"),BSAD,2,FALSE),""),IFERROR(VLOOKUP(A618,BSAD,2,FALSE),""))) -> 46229 | C618: BILL-6536 | D618: KRITIKA KIRANA | E618: Mix Milk | F618: 18 | G618: 86 | H618: =IF($F618="","",$F618*$G618) -> 1548 | I618: 0 | J618: =IF($F618="","",$H618*(1-$I618/100)) -> 1548 | K618: Credit | L618: Unpaid | M618: =H618-J618 -> 0
A619: 2083/04/10 | B619: =IF(A619="","",IF(ISNUMBER(A619),IFERROR(VLOOKUP(TEXT(A619,"yyyy/mm/dd"),BSAD,2,FALSE),""),IFERROR(VLOOKUP(A619,BSAD,2,FALSE),""))) -> 46229 | C619: BILL-6536 | D619: KRITIKA KIRANA | E619: NAUNI | F619: 7 | G619: 775 | H619: =IF($F619="","",$F619*$G619) -> 5425 | I619: 0 | J619: =IF($F619="","",$H619*(1-$I619/100)) -> 5425 | K619: Credit | L619: Unpaid | M619: =H619-J619 -> 0
A620: 2083/04/10 | B620: =IF(A620="","",IF(ISNUMBER(A620),IFERROR(VLOOKUP(TEXT(A620,"yyyy/mm/dd"),BSAD,2,FALSE),""),IFERROR(VLOOKUP(A620,BSAD,2,FALSE),""))) -> 46229 | C620: BILL-6537 | D620: SOBHA BHATTARAI | E620: Mix Milk | F620: 50 | G620: 85 | H620: =IF($F620="","",$F620*$G620) -> 4250 | I620: 0 | J620: =IF($F620="","",$H620*(1-$I620/100)) -> 4250 | K620: Credit | L620: Unpaid | M620: =H620-J620 -> 0
A621: 2083/04/10 | B621: =IF(A621="","",IF(ISNUMBER(A621),IFERROR(VLOOKUP(TEXT(A621,"yyyy/mm/dd"),BSAD,2,FALSE),""),IFERROR(VLOOKUP(A621,BSAD,2,FALSE),""))) -> 46229 | C621: BILL-6538 | D621: PALPALI KIRANA | E621: Mix Milk | F621: 25 | G621: 85 | H621: =IF($F621="","",$F621*$G621) -> 2125 | I621: 0 | J621: =IF($F621="","",$H621*(1-$I621/100)) -> 2125 | K621: Credit | L621: Unpaid | M621: =H621-J621 -> 0
A622: 2083/04/10 | B622: =IF(A622="","",IF(ISNUMBER(A622),IFERROR(VLOOKUP(TEXT(A622,"yyyy/mm/dd"),BSAD,2,FALSE),""),IFERROR(VLOOKUP(A622,BSAD,2,FALSE),""))) -> 46229 | C622: BILL-6539 | D622: AAMOSH KIRANA | E622: Mix Milk | F622: 40 | G622: 86 | H622: =IF($F622="","",$F622*$G622) -> 3440 | I622: 0 | J622: =IF($F622="","",$H622*(1-$I622/100)) -> 3440 | K622: Credit | L622: Unpaid | M622: =H622-J622 -> 0
A623: 2083/04/10 | B623: =IF(A623="","",IF(ISNUMBER(A623),IFERROR(VLOOKUP(TEXT(A623,"yyyy/mm/dd"),BSAD,2,FALSE),""),IFERROR(VLOOKUP(A623,BSAD,2,FALSE),""))) -> 46229 | C623: BILL-6539 | D623: AAMOSH KIRANA | E623: Mix Milk | F623: 50 | G623: 85 | H623: =IF($F623="","",$F623*$G623) -> 4250 | I623: 0 | J623: =IF($F623="","",$H623*(1-$I623/100)) -> 4250 | K623: Credit | L623: Unpaid | M623: =H623-J623 -> 0
... A761: 2083/04/15 | B761: =IF(A761="","",IF(ISNUMBER(A761),IFERROR(VLOOKUP(TEXT(A761,"yyyy/mm/dd"),BSAD,2,FALSE),""),IFERROR(VLOOKUP(A761,BSAD,2,FALSE),""))) -> 46234 | C761: BILL-6640 | D761: NEUPANE KIRANA | E761: Mix Milk | F761: 6 | G761: 100 | H761: =IF($F761="","",$F761*$G761) -> 600 | I761: 0 | J761: =IF($F761="","",$H761*(1-$I761/100)) -> 600 | K761: Credit | L761: Unpaid | M761: =H761-J761 -> 0
A762: 2083/04/15 | B762: =IF(A762="","",IF(ISNUMBER(A762),IFERROR(VLOOKUP(TEXT(A762,"yyyy/mm/dd"),BSAD,2,FALSE),""),IFERROR(VLOOKUP(A762,BSAD,2,FALSE),""))) -> 46234 | C762: BILL-6459 | D762: LOCAL | E762: Mix Milk | F762: =40+2+0.5+17.5+1.5 -> 61.5 | G762: 93.5 | H762: =IF($F762="","",$F762*$G762) -> 5750.25 | I762: 0 | J762: =IF($F762="","",$H762*(1-$I762/100)) -> 5750.25 | K762: Credit | L762: Unpaid | M762: =H762-J762 -> 0
A763: 2083/04/15 | B763: =IF(A763="","",IF(ISNUMBER(A763),IFERROR(VLOOKUP(TEXT(A763,"yyyy/mm/dd"),BSAD,2,FALSE),""),IFERROR(VLOOKUP(A763,BSAD,2,FALSE),""))) -> 46234 | C763: BILL-6460 | D763: LOCAL | E763: Mix Milk | F763: 12 | G763: 90 | H763: =IF($F763="","",$F763*$G763) -> 1080 | I763: 0 | J763: =IF($F763="","",$H763*(1-$I763/100)) -> 1080 | K763: Credit | L763: Unpaid | M763: =H763-J763 -> 0
A764: 2083/04/15 | B764: =IF(A764="","",IF(ISNUMBER(A764),IFERROR(VLOOKUP(TEXT(A764,"yyyy/mm/dd"),BSAD,2,FALSE),""),IFERROR(VLOOKUP(A764,BSAD,2,FALSE),""))) -> 46234 | C764: BILL-6460 | D764: LOCAL | E764: GHEE | F764: 0.5 | G764: 1100 | H764: =IF($F764="","",$F764*$G764) -> 550 | I764: 0 | J764: =IF($F764="","",$H764*(1-$I764/100)) -> 550 | K764: Credit | L764: Unpaid | M764: =H764-J764 -> 0
A765: 2083/04/16 | B765: =IF(A765="","",IF(ISNUMBER(A765),IFERROR(VLOOKUP(TEXT(A765,"yyyy/mm/dd"),BSAD,2,FALSE),""),IFERROR(VLOOKUP(A765,BSAD,2,FALSE),""))) -> 46235 | C765: BILL-6641 | D765: SRIJANA DAIRY | E765: Mix Milk | F765: 60 | G765: 85 | H765: =IF($F765="","",$F765*$G765) -> 5100 | I765: 0 | J765: =IF($F765="","",$H765*(1-$I765/100)) -> 5100 | K765: Credit | L765: Unpaid | M765: =H765-J765 -> 0
A766: 2083/04/16 | B766: =IF(A766="","",IF(ISNUMBER(A766),IFERROR(VLOOKUP(TEXT(A766,"yyyy/mm/dd"),BSAD,2,FALSE),""),IFERROR(VLOOKUP(A766,BSAD,2,FALSE),""))) -> 46235 | C766: BILL-6641 | D766: SRIJANA DAIRY | E766: Cow Milk | F766: 1 | G766: 80 | H766: =IF($F766="","",$F766*$G766) -> 80 | I766: 0 | J766: =IF($F766="","",$H766*(1-$I766/100)) -> 80 | K766: Credit | L766: Unpaid | M766: =H766-J766 -> 0
A767: 2083/04/16 | B767: =IF(A767="","",IF(ISNUMBER(A767),IFERROR(VLOOKUP(TEXT(A767,"yyyy/mm/dd"),BSAD,2,FALSE),""),IFERROR(VLOOKUP(A767,BSAD,2,FALSE),""))) -> 46235 | C767: BILL-6642 | D767: SOBHA BHATTARAI | E767: Mix Milk | F767: 30 | G767: 85 | H767: =IF($F767="","",$F767*$G767) -> 2550 | I767: 0 | J767: =IF($F767="","",$H767*(1-$I767/100)) -> 2550 | K767: Credit | L767: Unpaid | M767: =H767-J767 -> 0
A768: 2083/04/16 | B768: =IF(A768="","",IF(ISNUMBER(A768),IFERROR(VLOOKUP(TEXT(A768,"yyyy/mm/dd"),BSAD,2,FALSE),""),IFERROR(VLOOKUP(A768,BSAD,2,FALSE),""))) -> 46235 | C768: BILL-6643 | D768: AAMOSH KIRANA | E768: Mix Milk | F768: 80 | G768: 85 | H768: =IF($F768="","",$F768*$G768) -> 6800 | I768: 0 | J768: =IF($F768="","",$H768*(1-$I768/100)) -> 6800 | K768: Credit | L768: Unpaid | M768: =H768-J768 -> 0
A769: 2083/04/16 | B769: =IF(A769="","",IF(ISNUMBER(A769),IFERROR(VLOOKUP(TEXT(A769,"yyyy/mm/dd"),BSAD,2,FALSE),""),IFERROR(VLOOKUP(A769,BSAD,2,FALSE),""))) -> 46235 | C769: BILL-6644 | D769: KRISHNA KHAREL | E769: Mix Milk | F769: 3.5 | G769: 86 | H769: =IF($F769="","",$F769*$G769) -> 301 | I769: 0 | J769: =IF($F769="","",$H769*(1-$I769/100)) -> 301 | K769: Credit | L769: Unpaid | M769: =H769-J769 -> 0
A770: 2083/04/16 | B770: =IF(A770="","",IF(ISNUMBER(A770),IFERROR(VLOOKUP(TEXT(A770,"yyyy/mm/dd"),BSAD,2,FALSE),""),IFERROR(VLOOKUP(A770,BSAD,2,FALSE),""))) -> 46235 | C770: BILL-6645 | D770: SAMIKSHYA KIRANA | E770: Mix Milk | F770: 8 | G770: 85 | H770: =IF($F770="","",$F770*$G770) -> 680 | I770: 0 | J770: =IF($F770="","",$H770*(1-$I770/100)) -> 680 | K770: Credit | L770: Unpaid | M770: =H770-J770 -> 0
A771: 2083/04/16 | B771: =IF(A771="","",IF(ISNUMBER(A771),IFERROR(VLOOKUP(TEXT(A771,"yyyy/mm/dd"),BSAD,2,FALSE),""),IFERROR(VLOOKUP(A771,BSAD,2,FALSE),""))) -> 46235 | C771: BILL-6646 | D771: AAYUSH AND AAYUSHMA | E771: Mix Milk | F771: 5 | G771: 85 | H771: =IF($F771="","",$F771*$G771) -> 425 | I771: 0 | J771: =IF($F771="","",$H771*(1-$I771/100)) -> 425 | K771: Credit | L771: Unpaid | M771: =H771-J771 -> 0
A772: 2083/04/16 | B772: =IF(A772="","",IF(ISNUMBER(A772),IFERROR(VLOOKUP(TEXT(A772,"yyyy/mm/dd"),BSAD,2,FALSE),""),IFERROR(VLOOKUP(A772,BSAD,2,FALSE),""))) -> 46235 | C772: BILL-6647 | D772: DEURALI KIRANA | E772: Mix Milk | F772: 5 | G772: 85 | H772: =IF($F772="","",$F772*$G772) -> 425 | I772: 0 | J772: =IF($F772="","",$H772*(1-$I772/100)) -> 425 | K772: Credit | L772: Unpaid | M772: =H772-J772 -> 0
A773: 2083/04/16 | B773: =IF(A773="","",IF(ISNUMBER(A773),IFERROR(VLOOKUP(TEXT(A773,"yyyy/mm/dd"),BSAD,2,FALSE),""),IFERROR(VLOOKUP(A773,BSAD,2,FALSE),""))) -> 46235 | C773: BILL-6648 | D773: ORGANIC TARKALI | E773: Mix Milk | F773: 30 | G773: 95 | H773: =IF($F773="","",$F773*$G773) -> 2850 | I773: 0 | J773: =IF($F773="","",$H773*(1-$I773/100)) -> 2850 | K773: Credit | L773: Unpaid | M773: =H773-J773 -> 0
A774: 2083/04/16 | B774: =IF(A774="","",IF(ISNUMBER(A774),IFERROR(VLOOKUP(TEXT(A774,"yyyy/mm/dd"),BSAD,2,FALSE),""),IFERROR(VLOOKUP(A774,BSAD,2,FALSE),""))) -> 46235 | C774: BILL-6649 | D774: SHARMA DAI | E774: Mix Milk | F774: 30 | G774: 84 | H774: =IF($F774="","",$F774*$G774) -> 2520 | I774: 0 | J774: =IF($F774="","",$H774*(1-$I774/100)) -> 2520 | K774: Credit | L774: Unpaid | M774: =H774-J774 -> 0
... A895: 2083/04/21 | B895: =IF(A895="","",IF(ISNUMBER(A895),IFERROR(VLOOKUP(TEXT(A895,"yyyy/mm/dd"),BSAD,2,FALSE),""),IFERROR(VLOOKUP(A895,BSAD,2,FALSE),""))) -> 46240 | C895: BILL-6839 | D895: NEUPANE KIRANA | E895: Mix Milk | F895: 2 | G895: 100 | H895: =IF($F895="","",$F895*$G895) -> 200 | I895: 0 | J895: =IF($F895="","",$H895*(1-$I895/100)) -> 200 | K895: Credit | L895: Unpaid | M895: =H895-J895 -> 0
A896: 2083/04/21 | B896: =IF(A896="","",IF(ISNUMBER(A896),IFERROR(VLOOKUP(TEXT(A896,"yyyy/mm/dd"),BSAD,2,FALSE),""),IFERROR(VLOOKUP(A896,BSAD,2,FALSE),""))) -> 46240 | C896: BILL-6840 | D896: CANCELED | F896: 0 | G896: 0 | H896: =IF($F896="","",$F896*$G896) -> 0 | I896: 0 | J896: =IF($F896="","",$H896*(1-$I896/100)) -> 0 | K896: Credit | L896: Unpaid | M896: =H896-J896 -> 0
A897: 2083/04/21 | B897: =IF(A897="","",IF(ISNUMBER(A897),IFERROR(VLOOKUP(TEXT(A897,"yyyy/mm/dd"),BSAD,2,FALSE),""),IFERROR(VLOOKUP(A897,BSAD,2,FALSE),""))) -> 46240 | C897: BILL-6465 | D897: LOCAL | E897: Mix Milk | F897: 3.5 | G897: 100 | H897: =IF($F897="","",$F897*$G897) -> 350 | I897: 0 | J897: =IF($F897="","",$H897*(1-$I897/100)) -> 350 | K897: Credit | L897: Unpaid | M897: =H897-J897 -> 0
A898: 2083/04/22 | B898: =IF(A898="","",IF(ISNUMBER(A898),IFERROR(VLOOKUP(TEXT(A898,"yyyy/mm/dd"),BSAD,2,FALSE),""),IFERROR(VLOOKUP(A898,BSAD,2,FALSE),""))) -> 46241 | C898: BILL-6841 | D898: SOBHA BHATTARAI | E898: Mix Milk | F898: 55 | G898: 85 | H898: =IF($F898="","",$F898*$G898) -> 4675 | I898: 0 | J898: =IF($F898="","",$H898*(1-$I898/100)) -> 4675 | K898: Credit | L898: Unpaid | M898: =H898-J898 -> 0
A899: 2083/04/22 | B899: =IF(A899="","",IF(ISNUMBER(A899),IFERROR(VLOOKUP(TEXT(A899,"yyyy/mm/dd"),BSAD,2,FALSE),""),IFERROR(VLOOKUP(A899,BSAD,2,FALSE),""))) -> 46241 | C899: BILL-6842 | D899: AAMOSH KIRANA | E899: Mix Milk | F899: 40 | G899: 86 | H899: =IF($F899="","",$F899*$G899) -> 3440 | I899: 0 | J899: =IF($F899="","",$H899*(1-$I899/100)) -> 3440 | K899: Credit | L899: Unpaid | M899: =H899-J899 -> 0
A900: 2083/04/22 | B900: =IF(A900="","",IF(ISNUMBER(A900),IFERROR(VLOOKUP(TEXT(A900,"yyyy/mm/dd"),BSAD,2,FALSE),""),IFERROR(VLOOKUP(A900,BSAD,2,FALSE),""))) -> 46241 | C900: BILL-6842 | D900: AAMOSH KIRANA | E900: Mix Milk | F900: 46 | G900: 85 | H900: =IF($F900="","",$F900*$G900) -> 3910 | I900: 0 | J900: =IF($F900="","",$H900*(1-$I900/100)) -> 3910 | K900: Credit | L900: Unpaid | M900: =H900-J900 -> 0
A901: 2083/04/22 | B901: =IF(A901="","",IF(ISNUMBER(A901),IFERROR(VLOOKUP(TEXT(A901,"yyyy/mm/dd"),BSAD,2,FALSE),""),IFERROR(VLOOKUP(A901,BSAD,2,FALSE),""))) -> 46241 | C901: BILL-6842 | D901: AAMOSH KIRANA | E901: Cow Milk | F901: 1 | G901: 80 | H901: =IF($F901="","",$F901*$G901) -> 80 | I901: 0 | J901: =IF($F901="","",$H901*(1-$I901/100)) -> 80 | K901: Credit | L901: Unpaid | M901: =H901-J901 -> 0
A902: 2083/04/22 | B902: =IF(A902="","",IF(ISNUMBER(A902),IFERROR(VLOOKUP(TEXT(A902,"yyyy/mm/dd"),BSAD,2,FALSE),""),IFERROR(VLOOKUP(A902,BSAD,2,FALSE),""))) -> 46241 | C902: BILL-6843 | D902: GIRI KIRANA | E902: Mix Milk | F902: 15 | G902: 85 | H902: =IF($F902="","",$F902*$G902) -> 1275 | I902: 0 | J902: =IF($F902="","",$H902*(1-$I902/100)) -> 1275 | K902: Credit | L902: Unpaid | M902: =H902-J902 -> 0
A903: 2083/04/22 | B903: =IF(A903="","",IF(ISNUMBER(A903),IFERROR(VLOOKUP(TEXT(A903,"yyyy/mm/dd"),BSAD,2,FALSE),""),IFERROR(VLOOKUP(A903,BSAD,2,FALSE),""))) -> 46241 | C903: BILL-6844 | D903: PALPALI KIRANA | E903: Mix Milk | F903: 30 | G903: 85 | H903: =IF($F903="","",$F903*$G903) -> 2550 | I903: 0 | J903: =IF($F903="","",$H903*(1-$I903/100)) -> 2550 | K903: Credit | L903: Unpaid | M903: =H903-J903 -> 0
A904: 2083/04/22 | B904: =IF(A904="","",IF(ISNUMBER(A904),IFERROR(VLOOKUP(TEXT(A904,"yyyy/mm/dd"),BSAD,2,FALSE),""),IFERROR(VLOOKUP(A904,BSAD,2,FALSE),""))) -> 46241 | C904: BILL-6845 | D904: CHHATRABHUMI STORE | E904: Mix Milk | F904: 25 | G904: 86 | H904: =IF($F904="","",$F904*$G904) -> 2150 | I904: 0 | J904: =IF($F904="","",$H904*(1-$I904/100)) -> 2150 | K904: Credit | L904: Unpaid | M904: =H904-J904 -> 0
A905: 2083/04/22 | B905: =IF(A905="","",IF(ISNUMBER(A905),IFERROR(VLOOKUP(TEXT(A905,"yyyy/mm/dd"),BSAD,2,FALSE),""),IFERROR(VLOOKUP(A905,BSAD,2,FALSE),""))) -> 46241 | C905: BILL-6846 | D905: KRISHNA KHAREL | E905: Mix Milk | F905: 3.5 | G905: 86 | H905: =IF($F905="","",$F905*$G905) -> 301 | I905: 0 | J905: =IF($F905="","",$H905*(1-$I905/100)) -> 301 | K905: Credit | L905: Unpaid | M905: =H905-J905 -> 0
A906: 2083/04/22 | B906: =IF(A906="","",IF(ISNUMBER(A906),IFERROR(VLOOKUP(TEXT(A906,"yyyy/mm/dd"),BSAD,2,FALSE),""),IFERROR(VLOOKUP(A906,BSAD,2,FALSE),""))) -> 46241 | C906: BILL-6847 | D906: SAMIKSHYA KIRANA | E906: Mix Milk | F906: 8 | G906: 85 | H906: =IF($F906="","",$F906*$G906) -> 680 | I906: 0 | J906: =IF($F906="","",$H906*(1-$I906/100)) -> 680 | K906: Credit | L906: Unpaid | M906: =H906-J906 -> 0
A907: 2083/04/22 | B907: =IF(A907="","",IF(ISNUMBER(A907),IFERROR(VLOOKUP(TEXT(A907,"yyyy/mm/dd"),BSAD,2,FALSE),""),IFERROR(VLOOKUP(A907,BSAD,2,FALSE),""))) -> 46241 | C907: BILL-6848 | D907: YUBARAJ AND SAMRAT | E907: Mix Milk | F907: 12 | G907: 85 | H907: =IF($F907="","",$F907*$G907) -> 1020 | I907: 0 | J907: =IF($F907="","",$H907*(1-$I907/100)) -> 1020 | K907: Credit | L907: Unpaid | M907: =H907-J907 -> 0
A908: 2083/04/22 | B908: =IF(A908="","",IF(ISNUMBER(A908),IFERROR(VLOOKUP(TEXT(A908,"yyyy/mm/dd"),BSAD,2,FALSE),""),IFERROR(VLOOKUP(A908,BSAD,2,FALSE),""))) -> 46241 | C908: BILL-6849 | D908: MANAKAMANA DAIRY | E908: Mix Milk | F908: 10 | G908: 85 | H908: =IF($F908="","",$F908*$G908) -> 850 | I908: 0 | J908: =IF($F908="","",$H908*(1-$I908/100)) -> 850 | K908: Credit | L908: Unpaid | M908: =H908-J908 -> 0
... A981: 2083/04/25 | B981: =IF(A981="","",IF(ISNUMBER(A981),IFERROR(VLOOKUP(TEXT(A981,"yyyy/mm/dd"),BSAD,2,FALSE),""),IFERROR(VLOOKUP(A981,BSAD,2,FALSE),""))) -> 46244 | C981: BILL-6469 | D981: LOCAL | E981: Mix Milk | F981: 5.5 | G981: 100 | H981: =IF($F981="","",$F981*$G981) -> 550 | I981: 0 | J981: =IF($F981="","",$H981*(1-$I981/100)) -> 550 | K981: Credit | L981: Unpaid | M981: =H981-J981 -> 0
A982: 2083/04/25 | B982: =IF(A982="","",IF(ISNUMBER(A982),IFERROR(VLOOKUP(TEXT(A982,"yyyy/mm/dd"),BSAD,2,FALSE),""),IFERROR(VLOOKUP(A982,BSAD,2,FALSE),""))) -> 46244 | D982: LOCAL DAMAGE | E982: Mix Milk | F982: 243 | G982: 0 | H982: =IF($F982="","",$F982*$G982) -> 0 | I982: 0 | J982: =IF($F982="","",$H982*(1-$I982/100)) -> 0 | K982: Credit | L982: Unpaid | M982: =H982-J982 -> 0
A983: 2083/03/18 | B983: =IF(A983="","",IF(ISNUMBER(A983),IFERROR(VLOOKUP(TEXT(A983,"yyyy/mm/dd"),BSAD,2,FALSE),""),IFERROR(VLOOKUP(A983,BSAD,2,FALSE),""))) -> 46205 | D983: FACTORY PRODUCTION | E983: CREAM | F983: 37.5 | G983: 500 | H983: =IF($F983="","",$F983*$G983) -> 18750 | I983: 0 | J983: =IF($F983="","",$H983*(1-$I983/100)) -> 18750 | K983: Credit | L983: Unpaid | M983: =H983-J983 -> 0
A984: 2083/03/20 | B984: =IF(A984="","",IF(ISNUMBER(A984),IFERROR(VLOOKUP(TEXT(A984,"yyyy/mm/dd"),BSAD,2,FALSE),""),IFERROR(VLOOKUP(A984,BSAD,2,FALSE),""))) -> 46207 | D984: FACTORY PRODUCTION | E984: CREAM | F984: 11 | G984: 500 | H984: =IF($F984="","",$F984*$G984) -> 5500 | I984: 0 | J984: =IF($F984="","",$H984*(1-$I984/100)) -> 5500 | K984: Credit | L984: Unpaid | M984: =H984-J984 -> 0
A985: 2083/03/24 | B985: =IF(A985="","",IF(ISNUMBER(A985),IFERROR(VLOOKUP(TEXT(A985,"yyyy/mm/dd"),BSAD,2,FALSE),""),IFERROR(VLOOKUP(A985,BSAD,2,FALSE),""))) -> 46211 | D985: FACTORY PRODUCTION | E985: CREAM | F985: 8.5 | G985: 500 | H985: =IF($F985="","",$F985*$G985) -> 4250 | I985: 0 | J985: =IF($F985="","",$H985*(1-$I985/100)) -> 4250 | K985: Credit | L985: Unpaid | M985: =H985-J985 -> 0
A986: 2083/03/28 | B986: =IF(A986="","",IF(ISNUMBER(A986),IFERROR(VLOOKUP(TEXT(A986,"yyyy/mm/dd"),BSAD,2,FALSE),""),IFERROR(VLOOKUP(A986,BSAD,2,FALSE),""))) -> 46215 | D986: FACTORY PRODUCTION | E986: CREAM | F986: 71 | G986: 500 | H986: =IF($F986="","",$F986*$G986) -> 35500 | I986: 0 | J986: =IF($F986="","",$H986*(1-$I986/100)) -> 35500 | K986: Credit | L986: Unpaid | M986: =H986-J986 -> 0
A987: 2083/04/26 | B987: =IF(A987="","",IF(ISNUMBER(A987),IFERROR(VLOOKUP(TEXT(A987,"yyyy/mm/dd"),BSAD,2,FALSE),""),IFERROR(VLOOKUP(A987,BSAD,2,FALSE),""))) -> 46245 | C987: BILL-6706 | D987: SRIJANA DAIRY | E987: Mix Milk | F987: 20 | G987: 85 | H987: =IF($F987="","",$F987*$G987) -> 1700 | I987: 0 | J987: =IF($F987="","",$H987*(1-$I987/100)) -> 1700 | K987: Credit | L987: Unpaid | M987: =H987-J987 -> 0
A988: 2083/04/26 | B988: =IF(A988="","",IF(ISNUMBER(A988),IFERROR(VLOOKUP(TEXT(A988,"yyyy/mm/dd"),BSAD,2,FALSE),""),IFERROR(VLOOKUP(A988,BSAD,2,FALSE),""))) -> 46245 | C988: BILL-6706 | D988: SRIJANA DAIRY | E988: Cow Milk | F988: 1 | G988: 80 | H988: =IF($F988="","",$F988*$G988) -> 80 | I988: 0 | J988: =IF($F988="","",$H988*(1-$I988/100)) -> 80 | K988: Credit | L988: Unpaid | M988: =H988-J988 -> 0
A989: 2083/04/26 | B989: =IF(A989="","",IF(ISNUMBER(A989),IFERROR(VLOOKUP(TEXT(A989,"yyyy/mm/dd"),BSAD,2,FALSE),""),IFERROR(VLOOKUP(A989,BSAD,2,FALSE),""))) -> 46245 | C989: BILL-6707 | D989: KRITIKA KIRANA | E989: Mix Milk | F989: 10 | G989: 86 | H989: =IF($F989="","",$F989*$G989) -> 860 | I989: 0 | J989: =IF($F989="","",$H989*(1-$I989/100)) -> 860 | K989: Credit | L989: Unpaid | M989: =H989-J989 -> 0
A990: 2083/04/26 | B990: =IF(A990="","",IF(ISNUMBER(A990),IFERROR(VLOOKUP(TEXT(A990,"yyyy/mm/dd"),BSAD,2,FALSE),""),IFERROR(VLOOKUP(A990,BSAD,2,FALSE),""))) -> 46245 | C990: BILL-6707 | D990: KRITIKA KIRANA | E990: NAUNI | F990: 1 | G990: 850 | H990: =IF($F990="","",$F990*$G990) -> 850 | I990: 0 | J990: =IF($F990="","",$H990*(1-$I990/100)) -> 850 | K990: Credit | L990: Unpaid | M990: =H990-J990 -> 0
A991: 2083/04/26 | B991: =IF(A991="","",IF(ISNUMBER(A991),IFERROR(VLOOKUP(TEXT(A991,"yyyy/mm/dd"),BSAD,2,FALSE),""),IFERROR(VLOOKUP(A991,BSAD,2,FALSE),""))) -> 46245 | C991: BILL-6708 | D991: SOBHA BHATTARAI | E991: Mix Milk | F991: 50 | G991: 85 | H991: =IF($F991="","",$F991*$G991) -> 4250 | I991: 0 | J991: =IF($F991="","",$H991*(1-$I991/100)) -> 4250 | K991: Credit | L991: Unpaid | M991: =H991-J991 -> 0
A992: 2083/04/26 | B992: =IF(A992="","",IF(ISNUMBER(A992),IFERROR(VLOOKUP(TEXT(A992,"yyyy/mm/dd"),BSAD,2,FALSE),""),IFERROR(VLOOKUP(A992,BSAD,2,FALSE),""))) -> 46245 | C992: BILL-6709 | D992: AAYUSH AND AAYUSHMA | E992: Mix Milk | F992: 12 | G992: 85 | H992: =IF($F992="","",$F992*$G992) -> 1020 | I992: 0 | J992: =IF($F992="","",$H992*(1-$I992/100)) -> 1020 | K992: Credit | L992: Unpaid | M992: =H992-J992 -> 0
A993: 2083/04/26 | B993: =IF(A993="","",IF(ISNUMBER(A993),IFERROR(VLOOKUP(TEXT(A993,"yyyy/mm/dd"),BSAD,2,FALSE),""),IFERROR(VLOOKUP(A993,BSAD,2,FALSE),""))) -> 46245 | C993: BILL-6710 | D993: SAMIKSHYA KIRANA | E993: Mix Milk | F993: 8 | G993: 85 | H993: =IF($F993="","",$F993*$G993) -> 680 | I993: 0 | J993: =IF($F993="","",$H993*(1-$I993/100)) -> 680 | K993: Credit | L993: Unpaid | M993: =H993-J993 -> 0
A994: 2083/04/26 | B994: =IF(A994="","",IF(ISNUMBER(A994),IFERROR(VLOOKUP(TEXT(A994,"yyyy/mm/dd"),BSAD,2,FALSE),""),IFERROR(VLOOKUP(A994,BSAD,2,FALSE),""))) -> 46245 | C994: BILL-6711 | D994: KRISHNA KHAREL | E994: Mix Milk | F994: 2 | G994: 86 | H994: =IF($F994="","",$F994*$G994) -> 172 | I994: 0 | J994: =IF($F994="","",$H994*(1-$I994/100)) -> 172 | K994: Credit | L994: Unpaid | M994: =H994-J994 -> 0
A995: 2083/04/26 | B995: =IF(A995="","",IF(ISNUMBER(A995),IFERROR(VLOOKUP(TEXT(A995,"yyyy/mm/dd"),BSAD,2,FALSE),""),IFERROR(VLOOKUP(A995,BSAD,2,FALSE),""))) -> 46245 | C995: BILL-6712 | D995: CHHATRABHUMI STORE | E995: Mix Milk | F995: 25 | G995: 86 | H995: =IF($F995="","",$F995*$G995) -> 2150 | I995: 0 | J995: =IF($F995="","",$H995*(1-$I995/100)) -> 2150 | K995: Credit | L995: Unpaid | M995: =H995-J995 -> 0
A996: 2083/04/26 | B996: =IF(A996="","",IF(ISNUMBER(A996),IFERROR(VLOOKUP(TEXT(A996,"yyyy/mm/dd"),BSAD,2,FALSE),""),IFERROR(VLOOKUP(A996,BSAD,2,FALSE),""))) -> 46245 | C996: BILL-6713 | D996: PALPALI KIRANA | E996: Mix Milk | F996: 30 | G996: 85 | H996: =IF($F996="","",$F996*$G996) -> 2550 | I996: 0 | J996: =IF($F996="","",$H996*(1-$I996/100)) -> 2550 | K996: Credit | L996: Unpaid | M996: =H996-J996 -> 0
A997: 2083/04/26 | B997: =IF(A997="","",IF(ISNUMBER(A997),IFERROR(VLOOKUP(TEXT(A997,"yyyy/mm/dd"),BSAD,2,FALSE),""),IFERROR(VLOOKUP(A997,BSAD,2,FALSE),""))) -> 46245 | C997: BILL-6714 | D997: GIRI KIRANA | E997: Mix Milk | F997: 15 | G997: 85 | H997: =IF($F997="","",$F997*$G997) -> 1275 | I997: 0 | J997: =IF($F997="","",$H997*(1-$I997/100)) -> 1275 | K997: Credit | L997: Unpaid | M997: =H997-J997 -> 0
A998: 2083/04/26 | B998: =IF(A998="","",IF(ISNUMBER(A998),IFERROR(VLOOKUP(TEXT(A998,"yyyy/mm/dd"),BSAD,2,FALSE),""),IFERROR(VLOOKUP(A998,BSAD,2,FALSE),""))) -> 46245 | C998: BILL-6715 | D998: MANAKAMANA DAIRY | E998: Mix Milk | F998: 10 | G998: 85 | H998: =IF($F998="","",$F998*$G998) -> 850 | I998: 0 | J998: =IF($F998="","",$H998*(1-$I998/100)) -> 850 | K998: Credit | L998: Unpaid | M998: =H998-J998 -> 0
...

Sheet Purchase_Entry
A1: ACCOUNT OF STATEMENT
A2: Date | B2: AD Date | C2: Bill No | D2: Supplier Name | E2: Shift | F2: Product | G2: FAT % | H2: SNF % | I2: Extra/Unit | J2: Rate Type | K2: Fixed Rate | L2: Rate/Unit | M2: Quantity | N2: Amount | O2: Transport | P2: Net Amount | Q2: Payment Mode | R2: Status | S2: Remarks
A3: 2083/03/15 | B3: =IF(A3="","",IF(ISNUMBER(A3),IFERROR(VLOOKUP(TEXT(A3,"yyyy/mm/dd"),BSAD,2,FALSE),""),IFERROR(VLOOKUP(A3,BSAD,2,FALSE),""))) -> 46202 | C3: OPN2001 | D3: MUKTESHWOR ENTERPRISES | F3: OPENING | G3: 0 | H3: 0 | I3: 0 | J3: FIXED | K3: 69018 | L3: =IF($F3="","",IF($J3="FIXED",$K3,($G3*FAT_MULT)+($H3*SNF_MULT)+$I3)) -> 69018 | M3: 1 | N3: =IF($M3="","",$M3*$L3) -> 69018 | O3: 0 | P3: =IF($M3="","",$N3+$O3) -> 69018 | Q3: Credit | R3: Unpaid
A4: 2083/03/32 | B4: =IF(A4="","",IF(ISNUMBER(A4),IFERROR(VLOOKUP(TEXT(A4,"yyyy/mm/dd"),BSAD,2,FALSE),""),IFERROR(VLOOKUP(A4,BSAD,2,FALSE),""))) -> 46219 | C4: BILL-0809 | D4: MUKTESHWOR ENTERPRISES | F4: DISSEL | G4: 0 | H4: 0 | I4: 0 | J4: FIXED | K4: 23295 | L4: =IF($F4="","",IF($J4="FIXED",$K4,($G4*FAT_MULT)+($H4*SNF_MULT)+$I4)) -> 23295 | M4: 1 | N4: =IF($M4="","",$M4*$L4) -> 23295 | O4: 0 | P4: =IF($M4="","",$N4+$O4) -> 23295 | Q4: Credit | R4: Unpaid
A5: 2083/04/31 | B5: =IF(A5="","",IF(ISNUMBER(A5),IFERROR(VLOOKUP(TEXT(A5,"yyyy/mm/dd"),BSAD,2,FALSE),""),IFERROR(VLOOKUP(A5,BSAD,2,FALSE),""))) -> 46250 | C5: BILL-0079 | D5: MUKTESHWOR ENTERPRISES | F5: DISSEL | G5: 0 | H5: 0 | I5: 0 | J5: FIXED | K5: 50715 | L5: =IF($F5="","",IF($J5="FIXED",$K5,($G5*FAT_MULT)+($H5*SNF_MULT)+$I5)) -> 50715 | M5: 1 | N5: =IF($M5="","",$M5*$L5) -> 50715 | O5: 0 | P5: =IF($M5="","",$N5+$O5) -> 50715 | Q5: Credit | R5: Unpaid
A6: 2083/03/15 | B6: =IF(A6="","",IF(ISNUMBER(A6),IFERROR(VLOOKUP(TEXT(A6,"yyyy/mm/dd"),BSAD,2,FALSE),""),IFERROR(VLOOKUP(A6,BSAD,2,FALSE),""))) -> 46202 | C6: OPN2002 | D6: MODERN AGRO -315 | F6: OPENING | G6: 0 | H6: 0 | I6: 0 | J6: FIXED | K6: 172184 | L6: =IF($F6="","",IF($J6="FIXED",$K6,($G6*FAT_MULT)+($H6*SNF_MULT)+$I6)) -> 172184 | M6: 1 | N6: =IF($M6="","",$M6*$L6) -> 172184 | O6: 0 | P6: =IF($M6="","",$N6+$O6) -> 172184 | Q6: Credit | R6: PAID
A7: 2083/03/15 | B7: =IF(A7="","",IF(ISNUMBER(A7),IFERROR(VLOOKUP(TEXT(A7,"yyyy/mm/dd"),BSAD,2,FALSE),""),IFERROR(VLOOKUP(A7,BSAD,2,FALSE),""))) -> 46202 | C7: OPN2003 | D7: LUSCAN | F7: OPENING | G7: 0 | H7: 0 | I7: 0 | J7: FIXED | K7: 278851 | L7: =IF($F7="","",IF($J7="FIXED",$K7,($G7*FAT_MULT)+($H7*SNF_MULT)+$I7)) -> 278851 | M7: 1 | N7: =IF($M7="","",$M7*$L7) -> 278851 | O7: 0 | P7: =IF($M7="","",$N7+$O7) -> 278851 | Q7: Credit | R7: Unpaid
A8: 2083/03/15 | B8: =IF(A8="","",IF(ISNUMBER(A8),IFERROR(VLOOKUP(TEXT(A8,"yyyy/mm/dd"),BSAD,2,FALSE),""),IFERROR(VLOOKUP(A8,BSAD,2,FALSE),""))) -> 46202 | C8: OPN2004 | D8: PRARAMBHA DAIRY SUPPLIERS | F8: OPENING | G8: 0 | H8: 0 | I8: 0 | J8: FIXED | K8: 11932 | L8: =IF($F8="","",IF($J8="FIXED",$K8,($G8*FAT_MULT)+($H8*SNF_MULT)+$I8)) -> 11932 | M8: 1 | N8: =IF($M8="","",$M8*$L8) -> 11932 | O8: 0 | P8: =IF($M8="","",$N8+$O8) -> 11932 | Q8: Credit | R8: Unpaid
A9: 66916 | B9: =IF(A9="","",IF(ISNUMBER(A9),IFERROR(VLOOKUP(TEXT(A9,"yyyy/mm/dd"),BSAD,2,FALSE),""),IFERROR(VLOOKUP(A9,BSAD,2,FALSE),""))) -> 46203 | C9: BILL-5006 | D9: BASUDEV DAIRY 316 | E9: EVENING | F9: Buffalo Milk | G9: 5.9 | H9: 0 | I9: 15.5 | J9: FIXED | K9: =I9*G9 -> 91.45 | L9: =IF($F9="","",IF($J9="FIXED",$K9,($G9*FAT_MULT)+($H9*SNF_MULT)+$I9)) -> 91.45 | M9: 240 | N9: =IF($M9="","",$M9*$L9) -> 21948 | O9: 0 | P9: =IF($M9="","",$N9+$O9) -> 21948 | Q9: Credit | R9: PAID
A10: 66918 | B10: =IF(A10="","",IF(ISNUMBER(A10),IFERROR(VLOOKUP(TEXT(A10,"yyyy/mm/dd"),BSAD,2,FALSE),""),IFERROR(VLOOKUP(A10,BSAD,2,FALSE),""))) -> 46205 | C10: BILL-5020 | D10: BASUDEV DAIRY 316 | E10: EVENING | F10: Buffalo Milk | G10: 6.3 | H10: 0 | I10: 15.5 | J10: FIXED | K10: =I10*G10 -> 97.65 | L10: =IF($F10="","",IF($J10="FIXED",$K10,($G10*FAT_MULT)+($H10*SNF_MULT)+$I10)) -> 97.65 | M10: 240 | N10: =IF($M10="","",$M10*$L10) -> 23436 | O10: 0 | P10: =IF($M10="","",$N10+$O10) -> 23436 | Q10: Credit | R10: PAID
A11: 66920 | B11: =IF(A11="","",IF(ISNUMBER(A11),IFERROR(VLOOKUP(TEXT(A11,"yyyy/mm/dd"),BSAD,2,FALSE),""),IFERROR(VLOOKUP(A11,BSAD,2,FALSE),""))) -> 46207 | C11: BILL-5034 | D11: BASUDEV DAIRY 316 | E11: EVENING | F11: Buffalo Milk | G11: 6.5 | H11: 0 | I11: 15.5 | J11: FIXED | K11: =I11*G11 -> 100.75 | L11: =IF($F11="","",IF($J11="FIXED",$K11,($G11*FAT_MULT)+($H11*SNF_MULT)+$I11)) -> 100.75 | M11: 240 | N11: =IF($M11="","",$M11*$L11) -> 24180 | O11: 0 | P11: =IF($M11="","",$N11+$O11) -> 24180 | Q11: Credit | R11: PAID
A12: 66922 | B12: =IF(A12="","",IF(ISNUMBER(A12),IFERROR(VLOOKUP(TEXT(A12,"yyyy/mm/dd"),BSAD,2,FALSE),""),IFERROR(VLOOKUP(A12,BSAD,2,FALSE),""))) -> 46209 | C12: BILL-5048 | D12: BASUDEV DAIRY 316 | E12: EVENING | F12: Buffalo Milk | G12: 6.2 | H12: 0 | I12: 15.5 | J12: FIXED | K12: =I12*G12 -> 96.1 | L12: =IF($F12="","",IF($J12="FIXED",$K12,($G12*FAT_MULT)+($H12*SNF_MULT)+$I12)) -> 96.1 | M12: 240 | N12: =IF($M12="","",$M12*$L12) -> 23064 | O12: 0 | P12: =IF($M12="","",$N12+$O12) -> 23064 | Q12: Credit | R12: PAID
A13: 66924 | B13: =IF(A13="","",IF(ISNUMBER(A13),IFERROR(VLOOKUP(TEXT(A13,"yyyy/mm/dd"),BSAD,2,FALSE),""),IFERROR(VLOOKUP(A13,BSAD,2,FALSE),""))) -> 46211 | C13: BILL-5062 | D13: BASUDEV DAIRY 316 | E13: EVENING | F13: Buffalo Milk | G13: 6.3 | H13: 0 | I13: 15.5 | J13: FIXED | K13: =I13*G13 -> 97.65 | L13: =IF($F13="","",IF($J13="FIXED",$K13,($G13*FAT_MULT)+($H13*SNF_MULT)+$I13)) -> 97.65 | M13: 240 | N13: =IF($M13="","",$M13*$L13) -> 23436 | O13: 0 | P13: =IF($M13="","",$N13+$O13) -> 23436 | Q13: Credit | R13: PAID
A14: 66926 | B14: =IF(A14="","",IF(ISNUMBER(A14),IFERROR(VLOOKUP(TEXT(A14,"yyyy/mm/dd"),BSAD,2,FALSE),""),IFERROR(VLOOKUP(A14,BSAD,2,FALSE),""))) -> 46213 | C14: BILL-5076 | D14: BASUDEV DAIRY 316 | E14: EVENING | F14: Buffalo Milk | G14: 6.3 | H14: 0 | I14: 15.5 | J14: FIXED | K14: =I14*G14 -> 97.65 | L14: =IF($F14="","",IF($J14="FIXED",$K14,($G14*FAT_MULT)+($H14*SNF_MULT)+$I14)) -> 97.65 | M14: 240 | N14: =IF($M14="","",$M14*$L14) -> 23436 | O14: 0 | P14: =IF($M14="","",$N14+$O14) -> 23436 | Q14: Credit | R14: PAID
A15: 66928 | B15: =IF(A15="","",IF(ISNUMBER(A15),IFERROR(VLOOKUP(TEXT(A15,"yyyy/mm/dd"),BSAD,2,FALSE),""),IFERROR(VLOOKUP(A15,BSAD,2,FALSE),""))) -> 46215 | C15: BILL-5092 | D15: BASUDEV DAIRY 316 | E15: EVENING | F15: Buffalo Milk | G15: 5.4 | H15: 0 | I15: 15.5 | J15: FIXED | K15: =I15*G15 -> 83.7 | L15: =IF($F15="","",IF($J15="FIXED",$K15,($G15*FAT_MULT)+($H15*SNF_MULT)+$I15)) -> 83.7 | M15: 240 | N15: =IF($M15="","",$M15*$L15) -> 20088 | O15: 0 | P15: =IF($M15="","",$N15+$O15) -> 20088 | Q15: Credit | R15: PAID
A16: 66930 | B16: =IF(A16="","",IF(ISNUMBER(A16),IFERROR(VLOOKUP(TEXT(A16,"yyyy/mm/dd"),BSAD,2,FALSE),""),IFERROR(VLOOKUP(A16,BSAD,2,FALSE),""))) -> 46217 | C16: BILL-5108 | D16: BASUDEV DAIRY 316 | E16: EVENING | F16: Buffalo Milk | G16: 6 | H16: 0 | I16: 15.5 | J16: FIXED | K16: =I16*G16 -> 93 | L16: =IF($F16="","",IF($J16="FIXED",$K16,($G16*FAT_MULT)+($H16*SNF_MULT)+$I16)) -> 93 | M16: 240 | N16: =IF($M16="","",$M16*$L16) -> 22320 | O16: 0 | P16: =IF($M16="","",$N16+$O16) -> 22320 | Q16: Credit | R16: PAID
A17: 2083/03/32 | B17: =IF(A17="","",IF(ISNUMBER(A17),IFERROR(VLOOKUP(TEXT(A17,"yyyy/mm/dd"),BSAD,2,FALSE),""),IFERROR(VLOOKUP(A17,BSAD,2,FALSE),""))) -> 46219 | C17: BILL-5124 | D17: BASUDEV DAIRY 316 | E17: EVENING | F17: Buffalo Milk | G17: 5.6 | H17: 0 | I17: 15.5 | J17: FIXED | K17: =I17*G17 -> 86.8 | L17: =IF($F17="","",IF($J17="FIXED",$K17,($G17*FAT_MULT)+($H17*SNF_MULT)+$I17)) -> 86.8 | M17: 240 | N17: =IF($M17="","",$M17*$L17) -> 20832 | O17: 0 | P17: =IF($M17="","",$N17+$O17) -> 20832 | Q17: Credit | R17: PAID
A18: 66934 | B18: =IF(A18="","",IF(ISNUMBER(A18),IFERROR(VLOOKUP(TEXT(A18,"yyyy/mm/dd"),BSAD,2,FALSE),""),IFERROR(VLOOKUP(A18,BSAD,2,FALSE),""))) -> 46222 | C18: BILL-5145 | D18: BASUDEV DAIRY 316 | E18: EVENING | F18: Buffalo Milk | G18: 5.8 | H18: 0 | I18: 15.5 | J18: FIXED | K18: =I18*G18 -> 89.9 | L18: =IF($F18="","",IF($J18="FIXED",$K18,($G18*FAT_MULT)+($H18*SNF_MULT)+$I18)) -> 89.9 | M18: 229 | N18: =IF($M18="","",$M18*$L18) -> 20587.1 | O18: 0 | P18: =IF($M18="","",$N18+$O18) -> 20587.1 | Q18: Credit | R18: PAID
A19: 66936 | B19: =IF(A19="","",IF(ISNUMBER(A19),IFERROR(VLOOKUP(TEXT(A19,"yyyy/mm/dd"),BSAD,2,FALSE),""),IFERROR(VLOOKUP(A19,BSAD,2,FALSE),""))) -> 46224 | C19: BILL-5152 | D19: BASUDEV DAIRY 316 | E19: EVENING | F19: Buffalo Milk | G19: 6 | H19: 0 | I19: 15.5 | J19: FIXED | K19: =I19*G19 -> 93 | L19: =IF($F19="","",IF($J19="FIXED",$K19,($G19*FAT_MULT)+($H19*SNF_MULT)+$I19)) -> 93 | M19: 200 | N19: =IF($M19="","",$M19*$L19) -> 18600 | O19: 0 | P19: =IF($M19="","",$N19+$O19) -> 18600 | Q19: Credit | R19: PAID
A20: 66938 | B20: =IF(A20="","",IF(ISNUMBER(A20),IFERROR(VLOOKUP(TEXT(A20,"yyyy/mm/dd"),BSAD,2,FALSE),""),IFERROR(VLOOKUP(A20,BSAD,2,FALSE),""))) -> 46226 | C20: BILL-5152 | D20: BASUDEV DAIRY 316 | E20: EVENING | F20: Buffalo Milk | G20: 5.8 | H20: 0 | I20: 15.5 | J20: FIXED | K20: =I20*G20 -> 89.9 | L20: =IF($F20="","",IF($J20="FIXED",$K20,($G20*FAT_MULT)+($H20*SNF_MULT)+$I20)) -> 89.9 | M20: 200 | N20: =IF($M20="","",$M20*$L20) -> 17980 | O20: 0 | P20: =IF($M20="","",$N20+$O20) -> 17980 | Q20: Credit | R20: PAID
A21: 66939 | B21: =IF(A21="","",IF(ISNUMBER(A21),IFERROR(VLOOKUP(TEXT(A21,"yyyy/mm/dd"),BSAD,2,FALSE),""),IFERROR(VLOOKUP(A21,BSAD,2,FALSE),""))) -> 46227 | C21: BILL-5152 | D21: BASUDEV DAIRY 316 | E21: EVENING | F21: Buffalo Milk | G21: 6.2 | H21: 0 | I21: 15.5 | J21: FIXED | K21: =I21*G21 -> 96.1 | L21: =IF($F21="","",IF($J21="FIXED",$K21,($G21*FAT_MULT)+($H21*SNF_MULT)+$I21)) -> 96.1 | M21: 120 | N21: =IF($M21="","",$M21*$L21) -> 11532 | O21: 0 | P21: =IF($M21="","",$N21+$O21) -> 11532 | Q21: Credit | R21: PAID
A22: 66941 | B22: =IF(A22="","",IF(ISNUMBER(A22),IFERROR(VLOOKUP(TEXT(A22,"yyyy/mm/dd"),BSAD,2,FALSE),""),IFERROR(VLOOKUP(A22,BSAD,2,FALSE),""))) -> 46229 | C22: BILL-5152 | D22: BASUDEV DAIRY 316 | E22: EVENING | F22: Buffalo Milk | G22: 5.1 | H22: 0 | I22: 15.5 | J22: FIXED | K22: =I22*G22 -> 79.05 | L22: =IF($F22="","",IF($J22="FIXED",$K22,($G22*FAT_MULT)+($H22*SNF_MULT)+$I22)) -> 79.05 | M22: 240 | N22: =IF($M22="","",$M22*$L22) -> 18972 | O22: 0 | P22: =IF($M22="","",$N22+$O22) -> 18972 | Q22: Credit | R22: PAID
A23: 66943 | B23: =IF(A23="","",IF(ISNUMBER(A23),IFERROR(VLOOKUP(TEXT(A23,"yyyy/mm/dd"),BSAD,2,FALSE),""),IFERROR(VLOOKUP(A23,BSAD,2,FALSE),""))) -> 46231 | C23: BILL-5152 | D23: BASUDEV DAIRY 316 | E23: EVENING | F23: Buffalo Milk | G23: 5.3 | H23: 0 | I23: 15.5 | J23: FIXED | K23: =I23*G23 -> 82.15 | L23: =IF($F23="","",IF($J23="FIXED",$K23,($G23*FAT_MULT)+($H23*SNF_MULT)+$I23)) -> 82.15 | M23: 200 | N23: =IF($M23="","",$M23*$L23) -> 16430 | O23: 0 | P23: =IF($M23="","",$N23+$O23) -> 16430 | Q23: Credit | R23: PAID
A24: 66945 | B24: =IF(A24="","",IF(ISNUMBER(A24),IFERROR(VLOOKUP(TEXT(A24,"yyyy/mm/dd"),BSAD,2,FALSE),""),IFERROR(VLOOKUP(A24,BSAD,2,FALSE),""))) -> 46233 | C24: BILL-5152 | D24: BASUDEV DAIRY 316 | E24: EVENING | F24: Buffalo Milk | G24: 5.3 | H24: 0 | I24: 15.5 | J24: FIXED | K24: =I24*G24 -> 82.15 | L24: =IF($F24="","",IF($J24="FIXED",$K24,($G24*FAT_MULT)+($H24*SNF_MULT)+$I24)) -> 82.15 | M24: 240 | N24: =IF($M24="","",$M24*$L24) -> 19716 | O24: 0 | P24: =IF($M24="","",$N24+$O24) -> 19716 | Q24: Credit | R24: PAID
A25: 66947 | B25: =IF(A25="","",IF(ISNUMBER(A25),IFERROR(VLOOKUP(TEXT(A25,"yyyy/mm/dd"),BSAD,2,FALSE),""),IFERROR(VLOOKUP(A25,BSAD,2,FALSE),""))) -> 46235 | C25: BILL-5152 | D25: BASUDEV DAIRY 316 | E25: EVENING | F25: Buffalo Milk | G25: 5.1 | H25: 0 | I25: 15.5 | J25: FIXED | K25: =I25*G25 -> 79.05 | L25: =IF($F25="","",IF($J25="FIXED",$K25,($G25*FAT_MULT)+($H25*SNF_MULT)+$I25)) -> 79.05 | M25: 200 | N25: =IF($M25="","",$M25*$L25) -> 15810 | O25: 0 | P25: =IF($M25="","",$N25+$O25) -> 15810 | Q25: Credit | R25: PAID
A26: 66949 | B26: =IF(A26="","",IF(ISNUMBER(A26),IFERROR(VLOOKUP(TEXT(A26,"yyyy/mm/dd"),BSAD,2,FALSE),""),IFERROR(VLOOKUP(A26,BSAD,2,FALSE),""))) -> 46237 | C26: BILL-5152 | D26: BASUDEV DAIRY 316 | E26: EVENING | F26: Buffalo Milk | G26: 5.3 | H26: 0 | I26: 15.5 | J26: FIXED | K26: =I26*G26 -> 82.15 | L26: =IF($F26="","",IF($J26="FIXED",$K26,($G26*FAT_MULT)+($H26*SNF_MULT)+$I26)) -> 82.15 | M26: 160 | N26: =IF($M26="","",$M26*$L26) -> 13144 | O26: 0 | P26: =IF($M26="","",$N26+$O26) -> 13144 | Q26: Credit | R26: PAID
A27: 66951 | B27: =IF(A27="","",IF(ISNUMBER(A27),IFERROR(VLOOKUP(TEXT(A27,"yyyy/mm/dd"),BSAD,2,FALSE),""),IFERROR(VLOOKUP(A27,BSAD,2,FALSE),""))) -> 46239 | C27: BILL-5152 | D27: BASUDEV DAIRY 316 | E27: EVENING | F27: Buffalo Milk | G27: 5.3 | H27: 0 | I27: 15.5 | J27: FIXED | K27: =I27*G27 -> 82.15 | L27: =IF($F27="","",IF($J27="FIXED",$K27,($G27*FAT_MULT)+($H27*SNF_MULT)+$I27)) -> 82.15 | M27: 143.5 | N27: =IF($M27="","",$M27*$L27) -> 11788.525 | O27: 0 | P27: =IF($M27="","",$N27+$O27) -> 11788.525 | Q27: Credit | R27: PAID
A28: 66953 | B28: =IF(A28="","",IF(ISNUMBER(A28),IFERROR(VLOOKUP(TEXT(A28,"yyyy/mm/dd"),BSAD,2,FALSE),""),IFERROR(VLOOKUP(A28,BSAD,2,FALSE),""))) -> 46241 | C28: BILL-5152 | D28: BASUDEV DAIRY 316 | E28: EVENING | F28: Buffalo Milk | G28: 5.1 | H28: 0 | I28: 15.5 | J28: FIXED | K28: =I28*G28 -> 79.05 | L28: =IF($F28="","",IF($J28="FIXED",$K28,($G28*FAT_MULT)+($H28*SNF_MULT)+$I28)) -> 79.05 | M28: 172 | N28: =IF($M28="","",$M28*$L28) -> 13596.6 | O28: 0 | P28: =IF($M28="","",$N28+$O28) -> 13596.6 | Q28: Credit | R28: PAID
A29: 66955 | B29: =IF(A29="","",IF(ISNUMBER(A29),IFERROR(VLOOKUP(TEXT(A29,"yyyy/mm/dd"),BSAD,2,FALSE),""),IFERROR(VLOOKUP(A29,BSAD,2,FALSE),""))) -> 46243 | C29: BILL-5152 | D29: BASUDEV DAIRY 316 | E29: EVENING | F29: Buffalo Milk | G29: 5.2 | H29: 0 | I29: 15.5 | J29: FIXED | K29: =I29*G29 -> 80.6 | L29: =IF($F29="","",IF($J29="FIXED",$K29,($G29*FAT_MULT)+($H29*SNF_MULT)+$I29)) -> 80.6 | M29: 200 | N29: =IF($M29="","",$M29*$L29) -> 16120 | O29: 0 | P29: =IF($M29="","",$N29+$O29) -> 16120 | Q29: Credit | R29: PAID
... A48: 66992 | B48: =IF(A48="","",IF(ISNUMBER(A48),IFERROR(VLOOKUP(TEXT(A48,"yyyy/mm/dd"),BSAD,2,FALSE),""),IFERROR(VLOOKUP(A48,BSAD,2,FALSE),""))) -> 46281 | C48: BILL-5152 | D48: BASUDEV DAIRY 316 | E48: EVENING | F48: Buffalo Milk | G48: 5.6 | H48: 0 | I48: 15.5 | J48: FIXED | K48: =I48*G48 -> 86.8 | L48: =IF($F48="","",IF($J48="FIXED",$K48,($G48*FAT_MULT)+($H48*SNF_MULT)+$I48)) -> 86.8 | M48: 360 | N48: =IF($M48="","",$M48*$L48) -> 31248 | O48: 0 | P48: =IF($M48="","",$N48+$O48) -> 31248 | Q48: Credit | R48: Unpaid
A49: 66926 | B49: =IF(A49="","",IF(ISNUMBER(A49),IFERROR(VLOOKUP(TEXT(A49,"yyyy/mm/dd"),BSAD,2,FALSE),""),IFERROR(VLOOKUP(A49,BSAD,2,FALSE),""))) -> 46213 | C49: BILL-5078 | D49: BODESH 310 | E49: MORNING | F49: Buffalo Milk | G49: 0 | H49: 0 | I49: 0 | J49: FIXED | K49: 75 | L49: =IF($F49="","",IF($J49="FIXED",$K49,($G49*FAT_MULT)+($H49*SNF_MULT)+$I49)) -> 75 | M49: 40 | N49: =IF($M49="","",$M49*$L49) -> 3000 | O49: 0 | P49: =IF($M49="","",$N49+$O49) -> 3000 | Q49: Credit | R49: Unpaid
A50: 66927 | B50: =IF(A50="","",IF(ISNUMBER(A50),IFERROR(VLOOKUP(TEXT(A50,"yyyy/mm/dd"),BSAD,2,FALSE),""),IFERROR(VLOOKUP(A50,BSAD,2,FALSE),""))) -> 46214 | C50: BILL-5086 | D50: BODESH 310 | E50: MORNING | F50: Buffalo Milk | G50: 0 | H50: 0 | I50: 0 | J50: FIXED | K50: 75 | L50: =IF($F50="","",IF($J50="FIXED",$K50,($G50*FAT_MULT)+($H50*SNF_MULT)+$I50)) -> 75 | M50: 120 | N50: =IF($M50="","",$M50*$L50) -> 9000 | O50: 0 | P50: =IF($M50="","",$N50+$O50) -> 9000 | Q50: Credit | R50: Unpaid
A51: 66928 | B51: =IF(A51="","",IF(ISNUMBER(A51),IFERROR(VLOOKUP(TEXT(A51,"yyyy/mm/dd"),BSAD,2,FALSE),""),IFERROR(VLOOKUP(A51,BSAD,2,FALSE),""))) -> 46215 | C51: BILL-5094 | D51: BODESH 310 | E51: MORNING | F51: Buffalo Milk | G51: 0 | H51: 0 | I51: 0 | J51: FIXED | K51: 75 | L51: =IF($F51="","",IF($J51="FIXED",$K51,($G51*FAT_MULT)+($H51*SNF_MULT)+$I51)) -> 75 | M51: 120 | N51: =IF($M51="","",$M51*$L51) -> 9000 | O51: 0 | P51: =IF($M51="","",$N51+$O51) -> 9000 | Q51: Credit | R51: Unpaid
A52: 66929 | B52: =IF(A52="","",IF(ISNUMBER(A52),IFERROR(VLOOKUP(TEXT(A52,"yyyy/mm/dd"),BSAD,2,FALSE),""),IFERROR(VLOOKUP(A52,BSAD,2,FALSE),""))) -> 46216 | C52: BILL-5102 | D52: BODESH 310 | E52: MORNING | F52: Buffalo Milk | G52: 0 | H52: 0 | I52: 0 | J52: FIXED | K52: 75 | L52: =IF($F52="","",IF($J52="FIXED",$K52,($G52*FAT_MULT)+($H52*SNF_MULT)+$I52)) -> 75 | M52: 150 | N52: =IF($M52="","",$M52*$L52) -> 11250 | O52: 0 | P52: =IF($M52="","",$N52+$O52) -> 11250 | Q52: Credit | R52: Unpaid
