Workbook

Sheet Daily Sales
A1: Date | B1: Bill No | C1: Customer Name | D1: Item / Particular | E1: Quantity | F1: Rate | G1: Gross Amount | H1: Discount | I1: Net Sales | J1: Payment Type | K1: Remarks
A2: 46082 | B2: B001 | C2: Krishna Store | D2: Milk (1L Pouch) | E2: 50 | F2: 80 | G2: =E2*F2 -> 4000 | H2: 40 | I2: =G2-H2 -> 3960 | J2: Cash | K2: Morning supply
A3: 46082 | B3: B002 | C3: Ganesh Dairy | D3: Curd (500g) | E3: 30 | F3: 50 | G3: =E3*F3 -> 1500 | H3: 20 | I3: =G3-H3 -> 1480 | J3: Credit
A4: 46083 | B4: B003 | C4: Shiva Hotel | D4: Paneer (1kg) | E4: 20 | F4: 340 | G4: =E4*F4 -> 6800 | H4: 30 | I4: =G4-H4 -> 6770 | J4: Cash
A5: 46083 | B5: B004 | C5: Annapurna Foods | D5: Ghee (1L Tin) | E5: 10 | F5: 620 | G5: =E5*F5 -> 6200 | H5: 50 | I5: =G5-H5 -> 6150 | J5: Bank | K5: Bulk order
A6: 46084 | B6: B005 | C6: Krishna Store | D6: Milk (1L Pouch) | E6: 80 | F6: 80 | G6: =E6*F6 -> 6400 | H6: 60 | I6: =G6-H6 -> 6340 | J6: Cash
A7: 46085 | B7: B006 | C7: Himalaya Mart | D7: Butter (500g) | E7: 25 | F7: 220 | G7: =E7*F7 -> 5500 | H7: 25 | I7: =G7-H7 -> 5475 | J7: Cash
A8: 46086 | B8: B007 | C8: Patan Traders | D8: Milk Powder (1kg) | E8: 15 | F8: 480 | G8: =E8*F8 -> 7200 | H8: 30 | I8: =G8-H8 -> 7170 | J8: Credit
A9: 46086 | B9: B008 | C9: Ganesh Dairy | D9: Cheese (200g) | E9: 40 | F9: 160 | G9: =E9*F9 -> 6400 | H9: 40 | I9: =G9-H9 -> 6360 | J9: Cash
A10: 46086 | B10: B009 | C10: Shiva Hotel | D10: Curd (500g) | E10: 35 | F10: 50 | G10: =E10*F10 -> 1750 | H10: 15 | I10: =G10-H10 -> 1735 | J10: Bank
G11: =IF(E11="","",E11*F11) | I11: =IF(G11="","",G11-H11)
G12: =IF(E12="","",E12*F12) | I12: =IF(G12="","",G12-H12)
G13: =IF(E13="","",E13*F13) | I13: =IF(G13="","",G13-H13)
G14: =IF(E14="","",E14*F14) | I14: =IF(G14="","",G14-H14)
G15: =IF(E15="","",E15*F15) | I15: =IF(G15="","",G15-H15)
G16: =IF(E16="","",E16*F16) | I16: =IF(G16="","",G16-H16)
G17: =IF(E17="","",E17*F17) | I17: =IF(G17="","",G17-H17)
G18: =IF(E18="","",E18*F18) | I18: =IF(G18="","",G18-H18)
G19: =IF(E19="","",E19*F19) | I19: =IF(G19="","",G19-H19)
G20: =IF(E20="","",E20*F20) | I20: =IF(G20="","",G20-H20)
G21: =IF(E21="","",E21*F21) | I21: =IF(G21="","",G21-H21)
G22: =IF(E22="","",E22*F22) | I22: =IF(G22="","",G22-H22)
... G32: =IF(E32="","",E32*F32) | I32: =IF(G32="","",G32-H32)
A33: TOTAL | G33: =SUM(G2:G32) -> 45750 | H33: =SUM(H2:H32) -> 310 | I33: =SUM(I2:I32) -> 45440

Sheet Cash Collection
A1: Date | B1: Receipt No | C1: Customer Name | D1: Against Bill No | E1: Opening Due | F1: Collected Amount | G1: Payment Mode | H1: Closing Due | I1: Remarks
A2: 46082 | B2: R001 | C2: Krishna Store | D2: B001 | E2: 4000 | F2: 4000 | G2: Cash | H2: =E2-F2 -> 0
A3: 46082 | B3: R002 | C3: Shiva Hotel | D3: B003 | E3: 6800 | F3: 3000 | G3: Bank | H3: =E3-F3 -> 3800 | I3: Partial
A4: 46083 | B4: R003 | C4: Annapurna Foods | D4: B004 | E4: 6200 | F4: 6200 | G4: Cash | H4: =E4-F4 -> 0 | I4: Full paid
A5: 46083 | B5: R004 | C5: Patan Traders | D5: B007 | E5: 7200 | F5: 2000 | G5: Online | H5: =E5-F5 -> 5200 | I5: Advance
A6: 46084 | B6: R005 | C6: Ganesh Dairy | E6: 1500 | F6: 1500 | G6: Cash | H6: =E6-F6 -> 0
H7: =IF(E7="","",E7-F7)
H8: =IF(E8="","",E8-F8)
H9: =IF(E9="","",E9-F9)
H10: =IF(E10="","",E10-F10)
H11: =IF(E11="","",E11-F11)
H12: =IF(E12="","",E12-F12)
H13: =IF(E13="","",E13-F13)
H14: =IF(E14="","",E14-F14)
H15: =IF(E15="","",E15-F15)
H16: =IF(E16="","",E16-F16)
H17: =IF(E17="","",E17-F17)
H18: =IF(E18="","",E18-F18)
... H32: =IF(E32="","",E32-F32)
A33: TOTAL | F33: =SUM(F2:F32) -> 16700

Sheet Day Book
A1: Date | B1: Opening Cash | C1: Cash Sales | D1: Credit Sales | E1: Cash Collection | F1: Other Income | G1: Total In | H1: Purchase Expense | I1: Salary/Wages | J1: Transport | K1: Driver Advance | L1: Fuel/Diesel | M1: Misc Expense | N1: Electricity | O1: Rent | P1: Marketing | Q1: Petty Cash | R1: Commission | S1: Total Out | T1: Bank Deposit | U1: Expected Closing Cash | V1: Physical Cash Count | W1: Difference | X1: Remarks
A2: 46082 | B2: 10000 | C2: =SUMIFS('Daily Sales'!I:I,'Daily Sales'!A:A,A2,'Daily Sales'!J:J,"Cash") -> 3960 | D2: =SUMIFS('Daily Sales'!I:I,'Daily Sales'!A:A,A2,'Daily Sales'!J:J,"Credit") -> 1480 | E2: =SUMIFS('Cash Collection'!F:F,'Cash Collection'!A:A,A2) -> 7000 | F2: 500 | G2: =B2+C2+E2+F2 -> 21460 | H2: =SUMIFS('Supplier Payments'!E:E,'Supplier Payments'!A:A,A2) -> 3500 | I2: 1500 | J2: 800 | K2: 0 | L2: 1200 | M2: 300 | N2: 400 | O2: 250 | P2: 300 | Q2: 200 | R2: 150 | S2: =H2+I2+J2+K2+L2+M2+N2+O2+P2+Q2+R2 -> 8600 | T2: 5000 | U2: =G2-S2-T2 -> 7860 | V2: =XLOOKUP(A2,'Denomination Count'!A:A,'Denomination Count'!Q:Q) -> #NAME? | W2: =IF(ISNUMBER(V2),V2-U2,"")
A3: 46083 | B3: =IF(ISNUMBER(U2),U2,0) -> 7860 | C3: =SUMIFS('Daily Sales'!I:I,'Daily Sales'!A:A,A3,'Daily Sales'!J:J,"Cash") -> 6770 | D3: =SUMIFS('Daily Sales'!I:I,'Daily Sales'!A:A,A3,'Daily Sales'!J:J,"Credit") -> 0 | E3: =SUMIFS('Cash Collection'!F:F,'Cash Collection'!A:A,A3) -> 8200 | F3: 300 | G3: =B3+C3+E3+F3 -> 23130 | H3: =SUMIFS('Supplier Payments'!E:E,'Supplier Payments'!A:A,A3) -> 3000 | I3: 1500 | J3: 600 | K3: 0 | L3: 1000 | M3: 200 | N3: 300 | O3: 250 | P3: 200 | Q3: 100 | R3: 100 | S3: =H3+I3+J3+K3+L3+M3+N3+O3+P3+Q3+R3 -> 7250 | T3: 12500 | U3: =G3-S3-T3 -> 3380 | V3: =XLOOKUP(A3,'Denomination Count'!A:A,'Denomination Count'!Q:Q) -> #NAME? | W3: =IF(ISNUMBER(V3),V3-U3,"")
A4: 46084 | B4: =IF(ISNUMBER(U3),U3,0) -> 3380 | C4: =SUMIFS('Daily Sales'!I:I,'Daily Sales'!A:A,A4,'Daily Sales'!J:J,"Cash") -> 6340 | D4: =SUMIFS('Daily Sales'!I:I,'Daily Sales'!A:A,A4,'Daily Sales'!J:J,"Credit") -> 0 | E4: =SUMIFS('Cash Collection'!F:F,'Cash Collection'!A:A,A4) -> 1500 | F4: 200 | G4: =B4+C4+E4+F4 -> 11420 | H4: =SUMIFS('Supplier Payments'!E:E,'Supplier Payments'!A:A,A4) -> 2500 | I4: 1500 | J4: 500 | K4: 200 | L4: 800 | M4: 150 | N4: 300 | O4: 250 | P4: 150 | Q4: 100 | R4: 50 | S4: =H4+I4+J4+K4+L4+M4+N4+O4+P4+Q4+R4 -> 6500 | T4: 13200 | U4: =G4-S4-T4 -> -8280 | V4: =XLOOKUP(A4,'Denomination Count'!A:A,'Denomination Count'!Q:Q) -> #NAME? | W4: =IF(ISNUMBER(V4),V4-U4,"")
A5: 46085 | B5: =IF(ISNUMBER(U4),U4,0) -> -8280 | C5: =SUMIFS('Daily Sales'!I:I,'Daily Sales'!A:A,A5,'Daily Sales'!J:J,"Cash") -> 5475 | D5: =SUMIFS('Daily Sales'!I:I,'Daily Sales'!A:A,A5,'Daily Sales'!J:J,"Credit") -> 0 | E5: =SUMIFS('Cash Collection'!F:F,'Cash Collection'!A:A,A5) -> 0 | F5: 400 | G5: =B5+C5+E5+F5 -> -2405 | H5: =SUMIFS('Supplier Payments'!E:E,'Supplier Payments'!A:A,A5) -> 1200 | I5: 1500 | J5: 700 | K5: 0 | L5: 900 | M5: 100 | N5: 300 | O5: 250 | P5: 250 | Q5: 150 | R5: 100 | S5: =H5+I5+J5+K5+L5+M5+N5+O5+P5+Q5+R5 -> 5450 | T5: 14500 | U5: =G5-S5-T5 -> -22355 | V5: =XLOOKUP(A5,'Denomination Count'!A:A,'Denomination Count'!Q:Q) -> #NAME? | W5: =IF(ISNUMBER(V5),V5-U5,"")
A6: 46086 | B6: =IF(ISNUMBER(U5),U5,0) -> -22355 | C6: =SUMIFS('Daily Sales'!I:I,'Daily Sales'!A:A,A6,'Daily Sales'!J:J,"Cash") -> 6360 | D6: =SUMIFS('Daily Sales'!I:I,'Daily Sales'!A:A,A6,'Daily Sales'!J:J,"Credit") -> 7170 | E6: =SUMIFS('Cash Collection'!F:F,'Cash Collection'!A:A,A6) -> 0 | F6: 500 | G6: =B6+C6+E6+F6 -> -15495 | H6: =SUMIFS('Supplier Payments'!E:E,'Supplier Payments'!A:A,A6) -> 1800 | I6: 1500 | J6: 500 | K6: 0 | L6: 1100 | M6: 200 | N6: 300 | O6: 250 | P6: 300 | Q6: 100 | R6: 150 | S6: =H6+I6+J6+K6+L6+M6+N6+O6+P6+Q6+R6 -> 6200 | T6: 15100 | U6: =G6-S6-T6 -> -36795 | V6: =XLOOKUP(A6,'Denomination Count'!A:A,'Denomination Count'!Q:Q) -> #NAME? | W6: =IF(ISNUMBER(V6),V6-U6,"")
B7: =IF(ISNUMBER(U6),U6,0) -> -36795 | C7: =SUMIFS('Daily Sales'!I:I,'Daily Sales'!A:A,A7,'Daily Sales'!J:J,"Cash") -> 0 | D7: =SUMIFS('Daily Sales'!I:I,'Daily Sales'!A:A,A7,'Daily Sales'!J:J,"Credit") -> 0 | E7: =SUMIFS('Cash Collection'!F:F,'Cash Collection'!A:A,A7) -> 0 | G7: =B7+C7+E7+F7 -> -36795 | H7: =SUMIFS('Supplier Payments'!E:E,'Supplier Payments'!A:A,A7) -> 0 | I7: 0 | J7: 0 | K7: 0 | L7: 0 | M7: 0 | N7: 0 | O7: 0 | P7: 0 | Q7: 0 | R7: 0 | S7: =H7+I7+J7+K7+L7+M7+N7+O7+P7+Q7+R7 -> 0 | U7: =G7-S7-T7 -> -36795 | V7: =XLOOKUP(A7,'Denomination Count'!A:A,'Denomination Count'!Q:Q) -> #NAME? | W7: =IF(ISNUMBER(V7),V7-U7,"")
B8: =IF(ISNUMBER(U7),U7,0) -> -36795 | C8: =SUMIFS('Daily Sales'!I:I,'Daily Sales'!A:A,A8,'Daily Sales'!J:J,"Cash") -> 0 | D8: =SUMIFS('Daily Sales'!I:I,'Daily Sales'!A:A,A8,'Daily Sales'!J:J,"Credit") -> 0 | E8: =SUMIFS('Cash Collection'!F:F,'Cash Collection'!A:A,A8) -> 0 | G8: =B8+C8+E8+F8 -> -36795 | H8: =SUMIFS('Supplier Payments'!E:E,'Supplier Payments'!A:A,A8) -> 0 | I8: 0 | J8: 0 | K8: 0 | L8: 0 | M8: 0 | N8: 0 | O8: 0 | P8: 0 | Q8: 0 | R8: 0 | S8: =H8+I8+J8+K8+L8+M8+N8+O8+P8+Q8+R8 -> 0 | U8: =G8-S8-T8 -> -36795 | V8: =XLOOKUP(A8,'Denomination Count'!A:A,'Denomination Count'!Q:Q) -> #NAME? | W8: =IF(ISNUMBER(V8),V8-U8,"")
B9: =IF(ISNUMBER(U8),U8,0) -> -36795 | C9: =SUMIFS('Daily Sales'!I:I,'Daily Sales'!A:A,A9,'Daily Sales'!J:J,"Cash") -> 0 | D9: =SUMIFS('Daily Sales'!I:I,'Daily Sales'!A:A,A9,'Daily Sales'!J:J,"Credit") -> 0 | E9: =SUMIFS('Cash Collection'!F:F,'Cash Collection'!A:A,A9) -> 0 | G9: =B9+C9+E9+F9 -> -36795 | H9: =SUMIFS('Supplier Payments'!E:E,'Supplier Payments'!A:A,A9) -> 0 | I9: 0 | J9: 0 | K9: 0 | L9: 0 | M9: 0 | N9: 0 | O9: 0 | P9: 0 | Q9: 0 | R9: 0 | S9: =H9+I9+J9+K9+L9+M9+N9+O9+P9+Q9+R9 -> 0 | U9: =G9-S9-T9 -> -36795 | V9: =XLOOKUP(A9,'Denomination Count'!A:A,'Denomination Count'!Q:Q) -> #NAME? | W9: =IF(ISNUMBER(V9),V9-U9,"")
B10: =IF(ISNUMBER(U9),U9,0) -> -36795 | C10: =SUMIFS('Daily Sales'!I:I,'Daily Sales'!A:A,A10,'Daily Sales'!J:J,"Cash") -> 0 | D10: =SUMIFS('Daily Sales'!I:I,'Daily Sales'!A:A,A10,'Daily Sales'!J:J,"Credit") -> 0 | E10: =SUMIFS('Cash Collection'!F:F,'Cash Collection'!A:A,A10) -> 0 | G10: =B10+C10+E10+F10 -> -36795 | H10: =SUMIFS('Supplier Payments'!E:E,'Supplier Payments'!A:A,A10) -> 0 | I10: 0 | J10: 0 | K10: 0 | L10: 0 | M10: 0 | N10: 0 | O10: 0 | P10: 0 | Q10: 0 | R10: 0 | S10: =H10+I10+J10+K10+L10+M10+N10+O10+P10+Q10+R10 -> 0 | U10: =G10-S10-T10 -> -36795 | V10: =XLOOKUP(A10,'Denomination Count'!A:A,'Denomination Count'!Q:Q) -> #NAME? | W10: =IF(ISNUMBER(V10),V10-U10,"")
B11: =IF(ISNUMBER(U10),U10,0) -> -36795 | C11: =SUMIFS('Daily Sales'!I:I,'Daily Sales'!A:A,A11,'Daily Sales'!J:J,"Cash") -> 0 | D11: =SUMIFS('Daily Sales'!I:I,'Daily Sales'!A:A,A11,'Daily Sales'!J:J,"Credit") -> 0 | E11: =SUMIFS('Cash Collection'!F:F,'Cash Collection'!A:A,A11) -> 0 | G11: =B11+C11+E11+F11 -> -36795 | H11: =SUMIFS('Supplier Payments'!E:E,'Supplier Payments'!A:A,A11) -> 0 | I11: 0 | J11: 0 | K11: 0 | L11: 0 | M11: 0 | N11: 0 | O11: 0 | P11: 0 | Q11: 0 | R11: 0 | S11: =H11+I11+J11+K11+L11+M11+N11+O11+P11+Q11+R11 -> 0 | U11: =G11-S11-T11 -> -36795 | V11: =XLOOKUP(A11,'Denomination Count'!A:A,'Denomination Count'!Q:Q) -> #NAME? | W11: =IF(ISNUMBER(V11),V11-U11,"")
B12: =IF(ISNUMBER(U11),U11,0) -> -36795 | C12: =SUMIFS('Daily Sales'!I:I,'Daily Sales'!A:A,A12,'Daily Sales'!J:J,"Cash") -> 0 | D12: =SUMIFS('Daily Sales'!I:I,'Daily Sales'!A:A,A12,'Daily Sales'!J:J,"Credit") -> 0 | E12: =SUMIFS('Cash Collection'!F:F,'Cash Collection'!A:A,A12) -> 0 | G12: =B12+C12+E12+F12 -> -36795 | H12: =SUMIFS('Supplier Payments'!E:E,'Supplier Payments'!A:A,A12) -> 0 | I12: 0 | J12: 0 | K12: 0 | L12: 0 | M12: 0 | N12: 0 | O12: 0 | P12: 0 | Q12: 0 | R12: 0 | S12: =H12+I12+J12+K12+L12+M12+N12+O12+P12+Q12+R12 -> 0 | U12: =G12-S12-T12 -> -36795 | V12: =XLOOKUP(A12,'Denomination Count'!A:A,'Denomination Count'!Q:Q) -> #NAME? | W12: =IF(ISNUMBER(V12),V12-U12,"")
B13: =IF(ISNUMBER(U12),U12,0) -> -36795 | C13: =SUMIFS('Daily Sales'!I:I,'Daily Sales'!A:A,A13,'Daily Sales'!J:J,"Cash") -> 0 | D13: =SUMIFS('Daily Sales'!I:I,'Daily Sales'!A:A,A13,'Daily Sales'!J:J,"Credit") -> 0 | E13: =SUMIFS('Cash Collection'!F:F,'Cash Collection'!A:A,A13) -> 0 | G13: =B13+C13+E13+F13 -> -36795 | H13: =SUMIFS('Supplier Payments'!E:E,'Supplier Payments'!A:A,A13) -> 0 | I13: 0 | J13: 0 | K13: 0 | L13: 0 | M13: 0 | N13: 0 | O13: 0 | P13: 0 | Q13: 0 | R13: 0 | S13: =H13+I13+J13+K13+L13+M13+N13+O13+P13+Q13+R13 -> 0 | U13: =G13-S13-T13 -> -36795 | V13: =XLOOKUP(A13,'Denomination Count'!A:A,'Denomination Count'!Q:Q) -> #NAME? | W13: =IF(ISNUMBER(V13),V13-U13,"")
B14: =IF(ISNUMBER(U13),U13,0) -> -36795 | C14: =SUMIFS('Daily Sales'!I:I,'Daily Sales'!A:A,A14,'Daily Sales'!J:J,"Cash") -> 0 | D14: =SUMIFS('Daily Sales'!I:I,'Daily Sales'!A:A,A14,'Daily Sales'!J:J,"Credit") -> 0 | E14: =SUMIFS('Cash Collection'!F:F,'Cash Collection'!A:A,A14) -> 0 | G14: =B14+C14+E14+F14 -> -36795 | H14: =SUMIFS('Supplier Payments'!E:E,'Supplier Payments'!A:A,A14) -> 0 | I14: 0 | J14: 0 | K14: 0 | L14: 0 | M14: 0 | N14: 0 | O14: 0 | P14: 0 | Q14: 0 | R14: 0 | S14: =H14+I14+J14+K14+L14+M14+N14+O14+P14+Q14+R14 -> 0 | U14: =G14-S14-T14 -> -36795 | V14: =XLOOKUP(A14,'Denomination Count'!A:A,'Denomination Count'!Q:Q) -> #NAME? | W14: =IF(ISNUMBER(V14),V14-U14,"")
B15: =IF(ISNUMBER(U14),U14,0) -> -36795 | C15: =SUMIFS('Daily Sales'!I:I,'Daily Sales'!A:A,A15,'Daily Sales'!J:J,"Cash") -> 0 | D15: =SUMIFS('Daily Sales'!I:I,'Daily Sales'!A:A,A15,'Daily Sales'!J:J,"Credit") -> 0 | E15: =SUMIFS('Cash Collection'!F:F,'Cash Collection'!A:A,A15) -> 0 | G15: =B15+C15+E15+F15 -> -36795 | H15: =SUMIFS('Supplier Payments'!E:E,'Supplier Payments'!A:A,A15) -> 0 | I15: 0 | J15: 0 | K15: 0 | L15: 0 | M15: 0 | N15: 0 | O15: 0 | P15: 0 | Q15: 0 | R15: 0 | S15: =H15+I15+J15+K15+L15+M15+N15+O15+P15+Q15+R15 -> 0 | U15: =G15-S15-T15 -> -36795 | V15: =XLOOKUP(A15,'Denomination Count'!A:A,'Denomination Count'!Q:Q) -> #NAME? | W15: =IF(ISNUMBER(V15),V15-U15,"")
B16: =IF(ISNUMBER(U15),U15,0) -> -36795 | C16: =SUMIFS('Daily Sales'!I:I,'Daily Sales'!A:A,A16,'Daily Sales'!J:J,"Cash") -> 0 | D16: =SUMIFS('Daily Sales'!I:I,'Daily Sales'!A:A,A16,'Daily Sales'!J:J,"Credit") -> 0 | E16: =SUMIFS('Cash Collection'!F:F,'Cash Collection'!A:A,A16) -> 0 | G16: =B16+C16+E16+F16 -> -36795 | H16: =SUMIFS('Supplier Payments'!E:E,'Supplier Payments'!A:A,A16) -> 0 | I16: 0 | J16: 0 | K16: 0 | L16: 0 | M16: 0 | N16: 0 | O16: 0 | P16: 0 | Q16: 0 | R16: 0 | S16: =H16+I16+J16+K16+L16+M16+N16+O16+P16+Q16+R16 -> 0 | U16: =G16-S16-T16 -> -36795 | V16: =XLOOKUP(A16,'Denomination Count'!A:A,'Denomination Count'!Q:Q) -> #NAME? | W16: =IF(ISNUMBER(V16),V16-U16,"")
B17: =IF(ISNUMBER(U16),U16,0) -> -36795 | C17: =SUMIFS('Daily Sales'!I:I,'Daily Sales'!A:A,A17,'Daily Sales'!J:J,"Cash") -> 0 | D17: =SUMIFS('Daily Sales'!I:I,'Daily Sales'!A:A,A17,'Daily Sales'!J:J,"Credit") -> 0 | E17: =SUMIFS('Cash Collection'!F:F,'Cash Collection'!A:A,A17) -> 0 | G17: =B17+C17+E17+F17 -> -36795 | H17: =SUMIFS('Supplier Payments'!E:E,'Supplier Payments'!A:A,A17) -> 0 | I17: 0 | J17: 0 | K17: 0 | L17: 0 | M17: 0 | N17: 0 | O17: 0 | P17: 0 | Q17: 0 | R17: 0 | S17: =H17+I17+J17+K17+L17+M17+N17+O17+P17+Q17+R17 -> 0 | U17: =G17-S17-T17 -> -36795 | V17: =XLOOKUP(A17,'Denomination Count'!A:A,'Denomination Count'!Q:Q) -> #NAME? | W17: =IF(ISNUMBER(V17),V17-U17,"")
B18: =IF(ISNUMBER(U17),U17,0) -> -36795 | C18: =SUMIFS('Daily Sales'!I:I,'Daily Sales'!A:A,A18,'Daily Sales'!J:J,"Cash") -> 0 | D18: =SUMIFS('Daily Sales'!I:I,'Daily Sales'!A:A,A18,'Daily Sales'!J:J,"Credit") -> 0 | E18: =SUMIFS('Cash Collection'!F:F,'Cash Collection'!A:A,A18) -> 0 | G18: =B18+C18+E18+F18 -> -36795 | H18: =SUMIFS('Supplier Payments'!E:E,'Supplier Payments'!A:A,A18) -> 0 | I18: 0 | J18: 0 | K18: 0 | L18: 0 | M18: 0 | N18: 0 | O18: 0 | P18: 0 | Q18: 0 | R18: 0 | S18: =H18+I18+J18+K18+L18+M18+N18+O18+P18+Q18+R18 -> 0 | U18: =G18-S18-T18 -> -36795 | V18: =XLOOKUP(A18,'Denomination Count'!A:A,'Denomination Count'!Q:Q) -> #NAME? | W18: =IF(ISNUMBER(V18),V18-U18,"")
... B32: =IF(ISNUMBER(U31),U31,0) -> -36795 | C32: =SUMIFS('Daily Sales'!I:I,'Daily Sales'!A:A,A32,'Daily Sales'!J:J,"Cash") -> 0 | D32: =SUMIFS('Daily Sales'!I:I,'Daily Sales'!A:A,A32,'Daily Sales'!J:J,"Credit") -> 0 | E32: =SUMIFS('Cash Collection'!F:F,'Cash Collection'!A:A,A32) -> 0 | G32: =B32+C32+E32+F32 -> -36795 | H32: =SUMIFS('Supplier Payments'!E:E,'Supplier Payments'!A:A,A32) -> 0 | I32: 0 | J32: 0 | K32: 0 | L32: 0 | M32: 0 | N32: 0 | O32: 0 | P32: 0 | Q32: 0 | R32: 0 | S32: =H32+I32+J32+K32+L32+M32+N32+O32+P32+Q32+R32 -> 0 | U32: =G32-S32-T32 -> -36795 | V32: =XLOOKUP(A32,'Denomination Count'!A:A,'Denomination Count'!Q:Q) -> #NAME? | W32: =IF(ISNUMBER(V32),V32-U32,"")
A33: TOTAL | B33: =SUM(B2:B32) -> -966065 | C33: =SUM(C2:C32) -> 28905 | D33: =SUM(D2:D32) -> 8650 | E33: =SUM(E2:E32) -> 16700 | F33: =SUM(F2:F32) -> 1900 | G33: =SUM(G2:G32) -> -918560 | H33: =SUM(H2:H32) -> 12000 | I33: =SUM(I2:I32) -> 7500 | ... W33: =SUM(W2:W32) -> 0

Sheet Denomination Count
A1: Date | B1: 5 Count | C1: 5 Total | D1: 10 Count | E1: 10 Total | F1: 20 Count | G1: 20 Total | H1: 50 Count | I1: 50 Total | J1: 100 Count | K1: 100 Total | L1: 500 Count | M1: 500 Total | N1: 1000 Count | O1: 1000 Total | P1: Other Cash | Q1: Grand Total
A2: 46082 | B2: 10 | C2: =B2*5 -> 50 | D2: 8 | E2: =D2*10 -> 80 | F2: 6 | G2: =F2*20 -> 120 | H2: 24 | I2: =H2*50 -> 1200 | J2: 15 | K2: =J2*100 -> 1500 | L2: 10 | M2: =L2*500 -> 5000 | N2: 5 | O2: =N2*1000 -> 5000 | P2: 200 | Q2: =C2+E2+G2+I2+K2+M2+O2+P2 -> 13150
A3: 46083 | B3: 12 | C3: =B3*5 -> 60 | D3: 10 | E3: =D3*10 -> 100 | F3: 7 | G3: =F3*20 -> 140 | H3: 28 | I3: =H3*50 -> 1400 | J3: 18 | K3: =J3*100 -> 1800 | L3: 12 | M3: =L3*500 -> 6000 | N3: 6 | O3: =N3*1000 -> 6000 | P3: 300 | Q3: =C3+E3+G3+I3+K3+M3+O3+P3 -> 15800
A4: 46084 | B4: 15 | C4: =B4*5 -> 75 | D4: 12 | E4: =D4*10 -> 120 | F4: 8 | G4: =F4*20 -> 160 | H4: 30 | I4: =H4*50 -> 1500 | J4: 20 | K4: =J4*100 -> 2000 | L4: 15 | M4: =L4*500 -> 7500 | N4: 8 | O4: =N4*1000 -> 8000 | P4: 400 | Q4: =C4+E4+G4+I4+K4+M4+O4+P4 -> 19755
A5: 46085 | B5: 8 | C5: =B5*5 -> 40 | D5: 10 | E5: =D5*10 -> 100 | F5: 5 | G5: =F5*20 -> 100 | H5: 22 | I5: =H5*50 -> 1100 | J5: 16 | K5: =J5*100 -> 1600 | L5: 11 | M5: =L5*500 -> 5500 | N5: 4 | O5: =N5*1000 -> 4000 | P5: 250 | Q5: =C5+E5+G5+I5+K5+M5+O5+P5 -> 12690
A6: 46086 | B6: 11 | C6: =B6*5 -> 55 | D6: 9 | E6: =D6*10 -> 90 | F6: 7 | G6: =F6*20 -> 140 | H6: 26 | I6: =H6*50 -> 1300 | J6: 18 | K6: =J6*100 -> 1800 | L6: 13 | M6: =L6*500 -> 6500 | N6: 6 | O6: =N6*1000 -> 6000 | P6: 350 | Q6: =C6+E6+G6+I6+K6+M6+O6+P6 -> 16235
C7: =IF(B7="","",B7*5) | E7: =IF(D7="","",D7*10) | G7: =IF(F7="","",F7*20) | I7: =IF(H7="","",H7*50) | K7: =IF(J7="","",J7*100) | M7: =IF(L7="","",L7*500) | O7: =IF(N7="","",N7*1000) | Q7: =IF(COUNT(B7,D7,F7,H7,J7,L7,N7,P7)=0,"",C7+E7+G7+I7+K7+M7+O7+P7)
C8: =IF(B8="","",B8*5) | E8: =IF(D8="","",D8*10) | G8: =IF(F8="","",F8*20) | I8: =IF(H8="","",H8*50) | K8: =IF(J8="","",J8*100) | M8: =IF(L8="","",L8*500) | O8: =IF(N8="","",N8*1000) | Q8: =IF(COUNT(B8,D8,F8,H8,J8,L8,N8,P8)=0,"",C8+E8+G8+I8+K8+M8+O8+P8)
C9: =IF(B9="","",B9*5) | E9: =IF(D9="","",D9*10) | G9: =IF(F9="","",F9*20) | I9: =IF(H9="","",H9*50) | K9: =IF(J9="","",J9*100) | M9: =IF(L9="","",L9*500) | O9: =IF(N9="","",N9*1000) | Q9: =IF(COUNT(B9,D9,F9,H9,J9,L9,N9,P9)=0,"",C9+E9+G9+I9+K9+M9+O9+P9)
C10: =IF(B10="","",B10*5) | E10: =IF(D10="","",D10*10) | G10: =IF(F10="","",F10*20) | I10: =IF(H10="","",H10*50) | K10: =IF(J10="","",J10*100) | M10: =IF(L10="","",L10*500) | O10: =IF(N10="","",N10*1000) | Q10: =IF(COUNT(B10,D10,F10,H10,J10,L10,N10,P10)=0,"",C10+E10+G10+I10+K10+M10+O10+P10)
C11: =IF(B11="","",B11*5) | E11: =IF(D11="","",D11*10) | G11: =IF(F11="","",F11*20) | I11: =IF(H11="","",H11*50) | K11: =IF(J11="","",J11*100) | M11: =IF(L11="","",L11*500) | O11: =IF(N11="","",N11*1000) | Q11: =IF(COUNT(B11,D11,F11,H11,J11,L11,N11,P11)=0,"",C11+E11+G11+I11+K11+M11+O11+P11)
C12: =IF(B12="","",B12*5) | E12: =IF(D12="","",D12*10) | G12: =IF(F12="","",F12*20) | I12: =IF(H12="","",H12*50) | K12: =IF(J12="","",J12*100) | M12: =IF(L12="","",L12*500) | O12: =IF(N12="","",N12*1000) | Q12: =IF(COUNT(B12,D12,F12,H12,J12,L12,N12,P12)=0,"",C12+E12+G12+I12+K12+M12+O12+P12)
C13: =IF(B13="","",B13*5) | E13: =IF(D13="","",D13*10) | G13: =IF(F13="","",F13*20) | I13: =IF(H13="","",H13*50) | K13: =IF(J13="","",J13*100) | M13: =IF(L13="","",L13*500) | O13: =IF(N13="","",N13*1000) | Q13: =IF(COUNT(B13,D13,F13,H13,J13,L13,N13,P13)=0,"",C13+E13+G13+I13+K13+M13+O13+P13)
C14: =IF(B14="","",B14*5) | E14: =IF(D14="","",D14*10) | G14: =IF(F14="","",F14*20) | I14: =IF(H14="","",H14*50) | K14: =IF(J14="","",J14*100) | M14: =IF(L14="","",L14*500) | O14: =IF(N14="","",N14*1000) | Q14: =IF(COUNT(B14,D14,F14,H14,J14,L14,N14,P14)=0,"",C14+E14+G14+I14+K14+M14+O14+P14)
C15: =IF(B15="","",B15*5) | E15: =IF(D15="","",D15*10) | G15: =IF(F15="","",F15*20) | I15: =IF(H15="","",H15*50) | K15: =IF(J15="","",J15*100) | M15: =IF(L15="","",L15*500) | O15: =IF(N15="","",N15*1000) | Q15: =IF(COUNT(B15,D15,F15,H15,J15,L15,N15,P15)=0,"",C15+E15+G15+I15+K15+M15+O15+P15)
C16: =IF(B16="","",B16*5) | E16: =IF(D16="","",D16*10) | G16: =IF(F16="","",F16*20) | I16: =IF(H16="","",H16*50) | K16: =IF(J16="","",J16*100) | M16: =IF(L16="","",L16*500) | O16: =IF(N16="","",N16*1000) | Q16: =IF(COUNT(B16,D16,F16,H16,J16,L16,N16,P16)=0,"",C16+E16+G16+I16+K16+M16+O16+P16)
C17: =IF(B17="","",B17*5) | E17: =IF(D17="","",D17*10) | G17: =IF(F17="","",F17*20) | I17: =IF(H17="","",H17*50) | K17: =IF(J17="","",J17*100) | M17: =IF(L17="","",L17*500) | O17: =IF(N17="","",N17*1000) | Q17: =IF(COUNT(B17,D17,F17,H17,J17,L17,N17,P17)=0,"",C17+E17+G17+I17+K17+M17+O17+P17)
C18: =IF(B18="","",B18*5) | E18: =IF(D18="","",D18*10) | G18: =IF(F18="","",F18*20) | I18: =IF(H18="","",H18*50) | K18: =IF(J18="","",J18*100) | M18: =IF(L18="","",L18*500) | O18: =IF(N18="","",N18*1000) | Q18: =IF(COUNT(B18,D18,F18,H18,J18,L18,N18,P18)=0,"",C18+E18+G18+I18+K18+M18+O18+P18)
... C32: =IF(B32="","",B32*5) | E32: =IF(D32="","",D32*10) | G32: =IF(F32="","",F32*20) | I32: =IF(H32="","",H32*50) | K32: =IF(J32="","",J32*100) | M32: =IF(L32="","",L32*500) | O32: =IF(N32="","",N32*1000) | Q32: =IF(COUNT(B32,D32,F32,H32,J32,L32,N32,P32)=0,"",C32+E32+G32+I32+K32+M32+O32+P32)
A33: TOTAL | B33: =SUM(B2:B32) -> 56 | C33: =SUM(C2:C32) -> 280 | D33: =SUM(D2:D32) -> 49 | E33: =SUM(E2:E32) -> 490 | F33: =SUM(F2:F32) -> 33 | G33: =SUM(G2:G32) -> 660 | H33: =SUM(H2:H32) -> 130 | I33: =SUM(I2:I32) -> 6500 | ... Q33: =SUM(Q2:Q32) -> 77630

Sheet Summary Dashboard
A1: Total Sales | B1: =SUM('Daily Sales'!I2:I32) -> 45440
A2: Total Cash Sales | B2: =SUMIFS('Daily Sales'!I:I,'Daily Sales'!J:J,"Cash") -> 28905
A3: Total Credit Sales | B3: =SUMIFS('Daily Sales'!I:I,'Daily Sales'!J:J,"Credit") -> 8650
A4: Total Cash Collection | B4: =SUM('Cash Collection'!F2:F32) -> 16700
A5: Total Expenses | B5: =SUM('Day Book'!H2:H32,'Day Book'!I2:I32,'Day Book'!J2:J32,'Day Book'!K2:K32,'Day Book'!L2:L32,'Day Book'!M2:M32,'Day Book'!N2:N32,'Day Book'!O2:O32,'Day Book'!P2:P32,'Day Book'!Q2:Q32,'Day Book'!R2:R32) -> 34000
A6: Total Supplier Pymts | B6: =SUM('Supplier Payments'!E2:E32) -> 12000
A7: Total Bank Deposit | B7: =SUM('Day Book'!T2:T32) -> 60300
A8: Total Expected Closing | B8: =SUM('Day Book'!U2:U32) -> -1012860
A9: Total Physical Cash | B9: =SUM('Day Book'!V2:V32) -> #NAME?
A10: Total Difference | B10: =SUM('Day Book'!W2:W32) -> 0
A11: Stock Valuation Total | B11: =SUM('Stock Valuation'!D2:D32) -> 325650
A13: Date | B13: Net Sales | C13: Cash Collection | D13: Total Expenses | E13: Expected Closing Cash | F13: Physical Cash | G13: Difference
A14: =IFERROR('Day Book'!A2,"") -> 46082 | B14: =IFERROR('Day Book'!C2+'Day Book'!D2,"") -> 5440 | C14: =IFERROR('Day Book'!E2,"") -> 7000 | D14: =IFERROR('Day Book'!S2,"") -> 8600 | E14: =IFERROR('Day Book'!U2,"") -> 7860 | F14: =IFERROR('Day Book'!V2,"") | G14: =IFERROR('Day Book'!W2,"")
A15: =IFERROR('Day Book'!A3,"") -> 46083 | B15: =IFERROR('Day Book'!C3+'Day Book'!D3,"") -> 6770 | C15: =IFERROR('Day Book'!E3,"") -> 8200 | D15: =IFERROR('Day Book'!S3,"") -> 7250 | E15: =IFERROR('Day Book'!U3,"") -> 3380 | F15: =IFERROR('Day Book'!V3,"") | G15: =IFERROR('Day Book'!W3,"")
A16: =IFERROR('Day Book'!A4,"") -> 46084 | B16: =IFERROR('Day Book'!C4+'Day Book'!D4,"") -> 6340 | C16: =IFERROR('Day Book'!E4,"") -> 1500 | D16: =IFERROR('Day Book'!S4,"") -> 6500 | E16: =IFERROR('Day Book'!U4,"") -> -8280 | F16: =IFERROR('Day Book'!V4,"") | G16: =IFERROR('Day Book'!W4,"")
A17: =IFERROR('Day Book'!A5,"") -> 46085 | B17: =IFERROR('Day Book'!C5+'Day Book'!D5,"") -> 5475 | C17: =IFERROR('Day Book'!E5,"") -> 0 | D17: =IFERROR('Day Book'!S5,"") -> 5450 | E17: =IFERROR('Day Book'!U5,"") -> -22355 | F17: =IFERROR('Day Book'!V5,"") | G17: =IFERROR('Day Book'!W5,"")
A18: =IFERROR('Day Book'!A6,"") -> 46086 | B18: =IFERROR('Day Book'!C6+'Day Book'!D6,"") -> 13530 | C18: =IFERROR('Day Book'!E6,"") -> 0 | D18: =IFERROR('Day Book'!S6,"") -> 6200 | E18: =IFERROR('Day Book'!U6,"") -> -36795 | F18: =IFERROR('Day Book'!V6,"") | G18: =IFERROR('Day Book'!W6,"")
A19: =IFERROR('Day Book'!A7,"") -> 0 | B19: =IFERROR('Day Book'!C7+'Day Book'!D7,"") -> 0 | C19: =IFERROR('Day Book'!E7,"") -> 0 | D19: =IFERROR('Day Book'!S7,"") -> 0 | E19: =IFERROR('Day Book'!U7,"") -> -36795 | F19: =IFERROR('Day Book'!V7,"") | G19: =IFERROR('Day Book'!W7,"")
A20: =IFERROR('Day Book'!A8,"") -> 0 | B20: =IFERROR('Day Book'!C8+'Day Book'!D8,"") -> 0 | C20: =IFERROR('Day Book'!E8,"") -> 0 | D20: =IFERROR('Day Book'!S8,"") -> 0 | E20: =IFERROR('Day Book'!U8,"") -> -36795 | F20: =IFERROR('Day Book'!V8,"") | G20: =IFERROR('Day Book'!W8,"")
A21: =IFERROR('Day Book'!A9,"") -> 0 | B21: =IFERROR('Day Book'!C9+'Day Book'!D9,"") -> 0 | C21: =IFERROR('Day Book'!E9,"") -> 0 | D21: =IFERROR('Day Book'!S9,"") -> 0 | E21: =IFERROR('Day Book'!U9,"") -> -36795 | F21: =IFERROR('Day Book'!V9,"") | G21: =IFERROR('Day Book'!W9,"")
A22: =IFERROR('Day Book'!A10,"") -> 0 | B22: =IFERROR('Day Book'!C10+'Day Book'!D10,"") -> 0 | C22: =IFERROR('Day Book'!E10,"") -> 0 | D22: =IFERROR('Day Book'!S10,"") -> 0 | E22: =IFERROR('Day Book'!U10,"") -> -36795 | F22: =IFERROR('Day Book'!V10,"") | G22: =IFERROR('Day Book'!W10,"")
A23: =IFERROR('Day Book'!A11,"") -> 0 | B23: =IFERROR('Day Book'!C11+'Day Book'!D11,"") -> 0 | C23: =IFERROR('Day Book'!E11,"") -> 0 | D23: =IFERROR('Day Book'!S11,"") -> 0 | E23: =IFERROR('Day Book'!U11,"") -> -36795 | F23: =IFERROR('Day Book'!V11,"") | G23: =IFERROR('Day Book'!W11,"")
A24: =IFERROR('Day Book'!A12,"") -> 0 | B24: =IFERROR('Day Book'!C12+'Day Book'!D12,"") -> 0 | C24: =IFERROR('Day Book'!E12,"") -> 0 | D24: =IFERROR('Day Book'!S12,"") -> 0 | E24: =IFERROR('Day Book'!U12,"") -> -36795 | F24: =IFERROR('Day Book'!V12,"") | G24: =IFERROR('Day Book'!W12,"")
A25: =IFERROR('Day Book'!A13,"") -> 0 | B25: =IFERROR('Day Book'!C13+'Day Book'!D13,"") -> 0 | C25: =IFERROR('Day Book'!E13,"") -> 0 | D25: =IFERROR('Day Book'!S13,"") -> 0 | E25: =IFERROR('Day Book'!U13,"") -> -36795 | F25: =IFERROR('Day Book'!V13,"") | G25: =IFERROR('Day Book'!W13,"")
... A43: =IFERROR('Day Book'!A31,"") -> 0 | B43: =IFERROR('Day Book'!C31+'Day Book'!D31,"") -> 0 | C43: =IFERROR('Day Book'!E31,"") -> 0 | D43: =IFERROR('Day Book'!S31,"") -> 0 | E43: =IFERROR('Day Book'!U31,"") -> -36795 | F43: =IFERROR('Day Book'!V31,"") | G43: =IFERROR('Day Book'!W31,"")
A44: TOTAL | B44: =SUM(B14:B43) -> 37555 | C44: =SUM(C14:C43) -> 16700 | D44: =SUM(D14:D43) -> 34000 | E44: =SUM(E14:E43) -> -976065 | F44: =SUM(F14:F43) -> 0 | G44: =SUM(G14:G43) -> 0

Sheet Invoice
A1: YOUR BUSINESS NAME
A2: Address • Phone • Email
A4: INVOICE
A6: Bill No: | E6: Date: | F6: =IF(B6="","",XLOOKUP(B6,'Daily Sales'!B:B,'Daily Sales'!A:A))
A7: Customer: | B7: =IF(B6="","",XLOOKUP(B6,'Daily Sales'!B:B,'Daily Sales'!C:C)) | F7: =IF(B6="","",XLOOKUP(B6,'Daily Sales'!B:B,'Daily Sales'!J:J))
A9: # | B9: Item / Particular | C9: Qty | D9: Rate | E9: Gross Amount | F9: Discount | G9: Net Amount
A20: Subtotal (Gross Total): | E20: =IFERROR(SUMIF('Daily Sales'!B:B,B6,'Daily Sales'!G:G),"") -> 0
A21: Total Discount: | E21: =IFERROR(SUMIF('Daily Sales'!B:B,B6,'Daily Sales'!H:H),"") -> 0
A22: Grand Total (Net Amount): | E22: =IFERROR(SUMIF('Daily Sales'!B:B,B6,'Daily Sales'!I:I),"") -> 0
A23: Terms & Conditions:
A24: 1. Goods once sold will not be taken back. 2. Payment due within 15 days. 3. Subject to local jurisdiction.
A26: Authorised Signature | E26: Thank you for your business!

Sheet Supplier Payments
A1: Date | B1: Supplier/Vendor | C1: Voucher No | D1: Invoice Ref | E1: Payment Amount | F1: Payment Mode | G1: Category | H1: Description | I1: Remarks
A2: 46082 | B2: Nepal Dairy | C2: V001 | D2: INV-1001 | E2: 2000 | F2: Bank | G2: Purchase | H2: Milk supply
A3: 46082 | B3: Amul Agency | C3: V002 | D3: INV-1002 | E3: 1500 | F3: Cash | G3: Purchase | H3: Butter order
A4: 46083 | B4: Sagar Suppliers | C4: V003 | D4: INV-1003 | E4: 3000 | F4: Bank | G4: Raw Material | H4: Paneer supply
A5: 46084 | B5: Nepal Dairy | C5: V004 | D5: INV-1004 | E5: 2500 | F5: Bank | G5: Purchase | H5: Milk supply
A6: 46085 | B6: Arrow Trans | C6: V005 | D6: INV-1005 | E6: 1200 | F6: Cash | G6: Transport | H6: Delivery charges
A7: 46086 | B7: Amul Agency | C7: V006 | D7: INV-1006 | E7: 1800 | F7: Online | G7: Purchase | H7: Butter restock
A33: TOTAL | E33: =SUM(E2:E32) -> 12000

Sheet Stock Management
A1: Date | B1: Product | C1: Opening Stock | D1: Production / In | E1: Sales Out (Qty) | F1: Closing Stock | G1: Unit | H1: Unit Cost | I1: Production Cost | J1: Reorder Level | K1: Remarks
A2: 46082 | B2: Milk (1L Pouch) | C2: 200 | D2: 500 | E2: =SUMIFS('Daily Sales'!E:E,'Daily Sales'!A:A,A2,'Daily Sales'!D:D,B2) -> 50 | F2: =C2+D2-E2 -> 650 | G2: Pkt | H2: 60 | I2: =D2*H2 -> 30000 | J2: 100 | K2: Morning production
A3: 46082 | B3: Curd (500g) | C3: 80 | D3: 200 | E3: =SUMIFS('Daily Sales'!E:E,'Daily Sales'!A:A,A3,'Daily Sales'!D:D,B3) -> 30 | F3: =C3+D3-E3 -> 250 | G3: Pkt | H3: 35 | I3: =D3*H3 -> 7000 | J3: 40
A4: 46082 | B4: Paneer (1kg) | C4: 40 | D4: 100 | E4: =SUMIFS('Daily Sales'!E:E,'Daily Sales'!A:A,A4,'Daily Sales'!D:D,B4) -> 0 | F4: =C4+D4-E4 -> 140 | G4: Kg | H4: 280 | I4: =D4*H4 -> 28000 | J4: 20 | K4: Fresh batch
A5: 46083 | B5: Milk (1L Pouch) | C5: 650 | D5: 450 | E5: =SUMIFS('Daily Sales'!E:E,'Daily Sales'!A:A,A5,'Daily Sales'!D:D,B5) -> 0 | F5: =C5+D5-E5 -> 1100 | G5: Pkt | H5: 60 | I5: =D5*H5 -> 27000 | J5: 100
A6: 46083 | B6: Butter (500g) | C6: 60 | D6: 120 | E6: =SUMIFS('Daily Sales'!E:E,'Daily Sales'!A:A,A6,'Daily Sales'!D:D,B6) -> 0 | F6: =C6+D6-E6 -> 180 | G6: Pcs | H6: 180 | I6: =D6*H6 -> 21600 | J6: 30
A7: 46083 | B7: Milk Powder (1kg) | C7: 25 | D7: 50 | E7: =SUMIFS('Daily Sales'!E:E,'Daily Sales'!A:A,A7,'Daily Sales'!D:D,B7) -> 0 | F7: =C7+D7-E7 -> 75 | G7: Kg | H7: 420 | I7: =D7*H7 -> 21000 | J7: 15
A8: 46084 | B8: Milk (1L Pouch) | C8: 1020 | D8: 550 | E8: =SUMIFS('Daily Sales'!E:E,'Daily Sales'!A:A,A8,'Daily Sales'!D:D,B8) -> 80 | F8: =C8+D8-E8 -> 1490 | G8: Pkt | H8: 60 | I8: =D8*H8 -> 33000 | J8: 100
A9: 46084 | B9: Curd (500g) | C9: 220 | D9: 180 | E9: =SUMIFS('Daily Sales'!E:E,'Daily Sales'!A:A,A9,'Daily Sales'!D:D,B9) -> 0 | F9: =C9+D9-E9 -> 400 | G9: Pkt | H9: 35 | I9: =D9*H9 -> 6300 | J9: 40
A10: 46085 | B10: Milk (1L Pouch) | C10: 1490 | D10: 480 | E10: =SUMIFS('Daily Sales'!E:E,'Daily Sales'!A:A,A10,'Daily Sales'!D:D,B10) -> 0 | F10: =C10+D10-E10 -> 1970 | G10: Pkt | H10: 60 | I10: =D10*H10 -> 28800 | J10: 100
A11: 46085 | B11: Paneer (1kg) | C11: 120 | D11: 80 | E11: =SUMIFS('Daily Sales'!E:E,'Daily Sales'!A:A,A11,'Daily Sales'!D:D,B11) -> 0 | F11: =C11+D11-E11 -> 200 | G11: Kg | H11: 280 | I11: =D11*H11 -> 22400 | J11: 20
A12: 46085 | B12: Ghee (1L Tin) | C12: 35 | D12: 20 | E12: =SUMIFS('Daily Sales'!E:E,'Daily Sales'!A:A,A12,'Daily Sales'!D:D,B12) -> 0 | F12: =C12+D12-E12 -> 55 | G12: Ltr | H12: 550 | I12: =D12*H12 -> 11000 | J12: 15
A13: 46086 | B13: Milk (1L Pouch) | C13: 1890 | D13: 500 | E13: =SUMIFS('Daily Sales'!E:E,'Daily Sales'!A:A,A13,'Daily Sales'!D:D,B13) -> 0 | F13: =C13+D13-E13 -> 2390 | G13: Pkt | H13: 60 | I13: =D13*H13 -> 30000 | J13: 100
A14: 46086 | B14: Butter (500g) | C14: 150 | D14: 100 | E14: =SUMIFS('Daily Sales'!E:E,'Daily Sales'!A:A,A14,'Daily Sales'!D:D,B14) -> 0 | F14: =C14+D14-E14 -> 250 | G14: Pcs | H14: 180 | I14: =D14*H14 -> 18000 | J14: 30
A15: 46086 | B15: Milk Powder (1kg) | C15: 65 | D15: 40 | E15: =SUMIFS('Daily Sales'!E:E,'Daily Sales'!A:A,A15,'Daily Sales'!D:D,B15) -> 15 | F15: =C15+D15-E15 -> 90 | G15: Kg | H15: 420 | I15: =D15*H15 -> 16800 | J15: 15
E16: =SUMIFS('Daily Sales'!E:E,'Daily Sales'!A:A,A16,'Daily Sales'!D:D,B16) -> 0 | F16: =IF(C16="","",C16+D16-E16) | I16: =IF(AND(D16<>"",H16<>""),D16*H16,"")
E17: =SUMIFS('Daily Sales'!E:E,'Daily Sales'!A:A,A17,'Daily Sales'!D:D,B17) -> 0 | F17: =IF(C17="","",C17+D17-E17) | I17: =IF(AND(D17<>"",H17<>""),D17*H17,"")
E18: =SUMIFS('Daily Sales'!E:E,'Daily Sales'!A:A,A18,'Daily Sales'!D:D,B18) -> 0 | F18: =IF(C18="","",C18+D18-E18) | I18: =IF(AND(D18<>"",H18<>""),D18*H18,"")
E19: =SUMIFS('Daily Sales'!E:E,'Daily Sales'!A:A,A19,'Daily Sales'!D:D,B19) -> 0 | F19: =IF(C19="","",C19+D19-E19) | I19: =IF(AND(D19<>"",H19<>""),D19*H19,"")
E20: =SUMIFS('Daily Sales'!E:E,'Daily Sales'!A:A,A20,'Daily Sales'!D:D,B20) -> 0 | F20: =IF(C20="","",C20+D20-E20) | I20: =IF(AND(D20<>"",H20<>""),D20*H20,"")
E21: =SUMIFS('Daily Sales'!E:E,'Daily Sales'!A:A,A21,'Daily Sales'!D:D,B21) -> 0 | F21: =IF(C21="","",C21+D21-E21) | I21: =IF(AND(D21<>"",H21<>""),D21*H21,"")
E22: =SUMIFS('Daily Sales'!E:E,'Daily Sales'!A:A,A22,'Daily Sales'!D:D,B22) -> 0 | F22: =IF(C22="","",C22+D22-E22) | I22: =IF(AND(D22<>"",H22<>""),D22*H22,"")
E23: =SUMIFS('Daily Sales'!E:E,'Daily Sales'!A:A,A23,'Daily Sales'!D:D,B23) -> 0 | F23: =IF(C23="","",C23+D23-E23) | I23: =IF(AND(D23<>"",H23<>""),D23*H23,"")
E24: =SUMIFS('Daily Sales'!E:E,'Daily Sales'!A:A,A24,'Daily Sales'!D:D,B24) -> 0 | F24: =IF(C24="","",C24+D24-E24) | I24: =IF(AND(D24<>"",H24<>""),D24*H24,"")
E25: =SUMIFS('Daily Sales'!E:E,'Daily Sales'!A:A,A25,'Daily Sales'!D:D,B25) -> 0 | F25: =IF(C25="","",C25+D25-E25) | I25: =IF(AND(D25<>"",H25<>""),D25*H25,"")
E26: =SUMIFS('Daily Sales'!E:E,'Daily Sales'!A:A,A26,'Daily Sales'!D:D,B26) -> 0 | F26: =IF(C26="","",C26+D26-E26) | I26: =IF(AND(D26<>"",H26<>""),D26*H26,"")
E27: =SUMIFS('Daily Sales'!E:E,'Daily Sales'!A:A,A27,'Daily Sales'!D:D,B27) -> 0 | F27: =IF(C27="","",C27+D27-E27) | I27: =IF(AND(D27<>"",H27<>""),D27*H27,"")
... E32: =SUMIFS('Daily Sales'!E:E,'Daily Sales'!A:A,A32,'Daily Sales'!D:D,B32) -> 0 | F32: =IF(C32="","",C32+D32-E32) | I32: =IF(AND(D32<>"",H32<>""),D32*H32,"")
A33: TOTAL | C33: =SUM(C2:C32) -> 6045 | D33: =SUM(D2:D32) -> 3370 | E33: =SUM(E2:E32) -> 175 | F33: =SUM(F2:F32) -> 9240 | I33: =SUM(I2:I32) -> 300900

Sheet Stock Valuation
A1: Product | B1: Current Stock | C1: Unit Cost | D1: Stock Value (NPR) | E1: Reorder Level | F1: Status | G1: Remarks
A2: Milk (1L Pouch) | B2: 2300 | C2: 60 | D2: =B2*C2 -> 138000 | E2: 100 | F2: =IF(B2="","",IF(B2<=E2,"⚠ Reorder","✓ OK")) -> ✓ OK | G2: Daily supply
A3: Curd (500g) | B3: 350 | C3: 35 | D3: =B3*C3 -> 12250 | E3: 40 | F3: =IF(B3="","",IF(B3<=E3,"⚠ Reorder","✓ OK")) -> ✓ OK
A4: Paneer (1kg) | B4: 175 | C4: 280 | D4: =B4*C4 -> 49000 | E4: 20 | F4: =IF(B4="","",IF(B4<=E4,"⚠ Reorder","✓ OK")) -> ✓ OK | G4: Premium product
A5: Ghee (1L Tin) | B5: 52 | C5: 550 | D5: =B5*C5 -> 28600 | E5: 15 | F5: =IF(B5="","",IF(B5<=E5,"⚠ Reorder","✓ OK")) -> ✓ OK | G5: High value item
A6: Butter (500g) | B6: 240 | C6: 180 | D6: =B6*C6 -> 43200 | E6: 30 | F6: =IF(B6="","",IF(B6<=E6,"⚠ Reorder","✓ OK")) -> ✓ OK | G6: Popular item
A7: Milk Powder (1kg) | B7: 90 | C7: 420 | D7: =B7*C7 -> 37800 | E7: 15 | F7: =IF(B7="","",IF(B7<=E7,"⚠ Reorder","✓ OK")) -> ✓ OK
A8: Cheese (200g) | B8: 120 | C8: 140 | D8: =B8*C8 -> 16800 | E8: 25 | F8: =IF(B8="","",IF(B8<=E8,"⚠ Reorder","✓ OK")) -> ✓ OK
D9: =IF(OR(B9="",C9=""),"",B9*C9) | F9: =IF(B9="","",IF(B9<=E9,"⚠ Reorder","✓ OK"))
D10: =IF(OR(B10="",C10=""),"",B10*C10) | F10: =IF(B10="","",IF(B10<=E10,"⚠ Reorder","✓ OK"))
D11: =IF(OR(B11="",C11=""),"",B11*C11) | F11: =IF(B11="","",IF(B11<=E11,"⚠ Reorder","✓ OK"))
D12: =IF(OR(B12="",C12=""),"",B12*C12) | F12: =IF(B12="","",IF(B12<=E12,"⚠ Reorder","✓ OK"))
D13: =IF(OR(B13="",C13=""),"",B13*C13) | F13: =IF(B13="","",IF(B13<=E13,"⚠ Reorder","✓ OK"))
D14: =IF(OR(B14="",C14=""),"",B14*C14) | F14: =IF(B14="","",IF(B14<=E14,"⚠ Reorder","✓ OK"))
D15: =IF(OR(B15="",C15=""),"",B15*C15) | F15: =IF(B15="","",IF(B15<=E15,"⚠ Reorder","✓ OK"))
D16: =IF(OR(B16="",C16=""),"",B16*C16) | F16: =IF(B16="","",IF(B16<=E16,"⚠ Reorder","✓ OK"))
D17: =IF(OR(B17="",C17=""),"",B17*C17) | F17: =IF(B17="","",IF(B17<=E17,"⚠ Reorder","✓ OK"))
D18: =IF(OR(B18="",C18=""),"",B18*C18) | F18: =IF(B18="","",IF(B18<=E18,"⚠ Reorder","✓ OK"))
D19: =IF(OR(B19="",C19=""),"",B19*C19) | F19: =IF(B19="","",IF(B19<=E19,"⚠ Reorder","✓ OK"))
D20: =IF(OR(B20="",C20=""),"",B20*C20) | F20: =IF(B20="","",IF(B20<=E20,"⚠ Reorder","✓ OK"))
... D32: =IF(OR(B32="",C32=""),"",B32*C32) | F32: =IF(B32="","",IF(B32<=E32,"⚠ Reorder","✓ OK"))
A33: TOTAL | B33: =SUM(B2:B32) -> 3327 | D33: =SUM(D2:D32) -> 325650
A34: Total Stock Valuation (NPR): | D34: =SUM(D2:D32) -> 325650
